Workbook

Sheet MER
A2: En esta hoja se ubica la imagen del modelo, asegurando que sea clara y legible

Sheet Entidades
A1: Entidad | B1: Desripción
A2: Cliente | B2: Objeto de dominio que representa a cada uno de los usuarios registrados que realizan compras en la plataforma de Imexcol.
A3: Administrador | B3: Objeto de dominio que representa al personal interno encargado de gestionar el catálogo, los pedidos y la operación general del sistema.
A4: Direccion | B4: Objeto de dominio que representa la ubicación física y estructurada que registra un cliente para la entrega de sus productos o propósitos de facturación.
A5: Categoria | B5: Objeto de dominio que representa a cada una de las agrupaciones taxonómicas en las que se organizan los productos del catálogo de Imexcol.
A6: Producto | B6: Objeto de dominio que representa a cada uno de los artículos de importación (bolsos, juguetes, etc.) que están disponibles para la venta en la tienda.
A7: ImagenProducto | B7: Objeto de dominio que representa a cada uno de los recursos visuales o fotografías asociadas a un producto para su exhibición.
A8: Resena | B8: Objeto de dominio que representa a cada una de las calificaciones y comentarios dejados por un cliente sobre un producto específico que ya ha comprado.
A9: CarritoCompras | B9: Objeto de dominio que representa la sesión temporal donde un cliente agrupa los productos que tiene intención de adquirir antes de formalizar la transacción.
A10: ItemCarrito | B10: Objeto de dominio que representa a cada una de las selecciones individuales (producto específico y cantidad) dentro del carrito activo de un cliente.
A11: Pedido | B11: Objeto de dominio que representa la confirmación formal, transaccional y definitiva de una compra realizada por un cliente en Imexcol.
A12: LineaPedido | B12: Objeto de dominio que representa el detalle individual de un pedido, permitiendo registrar de forma histórica cada producto adquirido, su cantidad y su valor al momento de confirmar la compra. (Evidencia histórica de la compra)
... A17: EventoRastreo | B17: Objeto de dominio que representa a cada una de las actualizaciones o hitos temporales (ej. en preparación, en tránsito, entregado) que ocurren durante el ciclo de vida de un envío.

Sheet Cliente
A1: <-Volver al inicio
A2: =Entidades!$A$1 -> Entidad | B2: =Entidades!A2 -> Cliente
A3: =Entidades!$B$1 -> Desripción | B3: =Entidades!B2 -> Objeto de dominio que representa a cada uno de los usuarios registrados que realizan compras en la plataforma de Imexcol.
A4: Atributos
A5: Nombre | B5: Tipo de dato | C5: Longitud | D5: Cantidad dígitos parte entera | E5: Cantidad dígitos parte decimal (Precisión) | F5: ¿Es autoincremento? | G5: ¿Es obligatorio? | H5: ¿Es llave primeria o es parte de ella? | I5: Llave Foránea | L5: Restricciones de unicidad | N5: Restricciones de chequeo | P5: Restricciones de índice | S5: Alias | T5: Descripción del campo
I6: ¿Es llave foránea? | J6: Entidad | K6: Columna(s) | L6: ¿Posee restricción de unicidad o es parte de ella? | M6: Nombre restricción unicidad a la que pertenece | N6: ¿Posee restricción de chequeo o es parte de ella? | O6: Nombre restricción chequeo a la que pertenece | P6: ¿Posee restricción de índice o es parte de ella? | Q6: Tipo | R6: Nombre restricción índice a la que pertenece
A7: id | B7: UNIQUEIDENTIFIER | F7: NO | G7: SI | H7: SI | I7: NO | L7: NO | N7: NO | P7: NO | S7: id | T7: Identificador único universal del cliente.
A8: nombre | B8: NVARCHAR | C8: 100 | F8: NO | G8: SI | H8: NO | I8: NO | L8: NO | N8: NO | P8: NO | S8: nombre | T8: Nombre o nombres del cliente.
A9: apellido | B9: NVARCHAR | C9: 100 | F9: NO | G9: SI | H9: NO | I9: NO | L9: NO | N9: NO | P9: NO | S9: apellido | T9: Apellido o apellidos del cliente.
A10: correo_electronico | B10: NVARCHAR | C10: 150 | F10: NO | G10: SI | H10: NO | I10: NO | L10: SI | M10: uq_imex_cliente_correo | N10: NO | P10: NO | S10: correo_electronico | T10: Correo electrónico único de contacto y autenticación.
A11: contrasena | B11: NVARCHAR | C11: 255 | F11: NO | G11: SI | H11: NO | I11: NO | L11: NO | N11: NO | P11: NO | S11: contrasena | T11: Contraseña del cliente almacenada de forma segura.
A12: telefono | B12: NVARCHAR | C12: 20 | F12: NO | G12: NO | H12: NO | I12: NO | L12: NO | N12: NO | P12: NO | S12: telefono | T12: Número de teléfono de contacto (opcional).
A13: estado | B13: BIT | F13: NO | G13: SI | H13: NO | I13: NO | L13: NO | N13: NO | P13: NO | S13: estado | T13: Indica si el cliente está activo (1) o inactivo (0).

Sheet Administrador
A1: <-Volver al inicio
A2: =Entidades!$A$1 -> Entidad | B2: =Entidades!A3 -> Administrador
A3: =Entidades!$B$1 -> Desripción | B3: =Entidades!B3 -> Objeto de dominio que representa al personal interno encargado de gestionar el catálogo, los pedidos y la operación general del sistema.
A4: Atributos
A5: Nombre | B5: Tipo de dato | C5: Longitud | D5: Cantidad dígitos parte entera | E5: Cantidad dígitos parte decimal (Precisión) | F5: ¿Es autoincremento? | G5: ¿Es obligatorio? | H5: ¿Es llave primeria o es parte de ella? | I5: Llave Foránea | L5: Restricciones de unicidad | N5: Restricciones de chequeo | P5: Restricciones de índice | S5: Alias | T5: Descripción del campo
I6: ¿Es llave foránea? | J6: Entidad | K6: Columna(s) | L6: ¿Posee restricción de unicidad o es parte de ella? | M6: Nombre restricción unicidad a la que pertenece | N6: ¿Posee restricción de chequeo o es parte de ella? | O6: Nombre restricción chequeo a la que pertenece | P6: ¿Posee restricción de índice o es parte de ella? | Q6: Tipo | R6: Nombre restricción índice a la que pertenece
A7: id | B7: UNIQUEIDENTIFIER | F7: NO | G7: SI | H7: SI | I7: NO | L7: NO | N7: NO | P7: NO | S7: id | T7: Identificador único universal del administrador.
A8: nombre_usuario | B8: NVARCHAR | C8: 50 | F8: NO | G8: SI | H8: NO | I8: NO | L8: SI | M8: uq_imex_administrador_nombre_usuario | N8: NO | P8: NO | S8: nombre_usuario | T8: Nombre de usuario único del administrador.
A9: correo_electronico | B9: NVARCHAR | C9: 150 | F9: NO | G9: SI | H9: NO | I9: NO | L9: SI | M9: uq_imex_administrador_correo | N9: NO | P9: NO | S9: correo_electronico | T9: Correo electrónico único del administrador.
A10: contrasena | B10: NVARCHAR | C10: 255 | F10: NO | G10: SI | H10: NO | I10: NO | L10: NO | N10: NO | P10: NO | S10: contrasena | T10: Contraseña del administrador almacenada de forma segura.
A11: estado | B11: BIT | F11: NO | G11: SI | H11: NO | I11: NO | L11: NO | N11: NO | P11: NO | S11: estado | T11: Indica si el administrador está activo (1) o inactivo (0).

Sheet Direccion
A1: <-Volver al inicio
A2: =Entidades!$A$1 -> Entidad | B2: =Entidades!A4 -> Direccion
A3: =Entidades!$B$1 -> Desripción | B3: =Entidades!B4 -> Objeto de dominio que representa la ubicación física y estructurada que registra un cliente para la entrega de sus productos o propósitos de facturación.
A4: Atributos
A5: Nombre | B5: Tipo de dato | C5: Longitud | D5: Cantidad dígitos parte entera | E5: Cantidad dígitos parte decimal (Precisión) | F5: ¿Es autoincremento? | G5: ¿Es obligatorio? | H5: ¿Es llave primeria o es parte de ella? | I5: Llave Foránea | L5: Restricciones de unicidad | N5: Restricciones de chequeo | P5: Restricciones de índice | S5: Alias | T5: Descripción del campo
I6: ¿Es llave foránea? | J6: Entidad | K6: Columna(s) | L6: ¿Posee restricción de unicidad o es parte de ella? | M6: Nombre restricción unicidad a la que pertenece | N6: ¿Posee restricción de chequeo o es parte de ella? | O6: Nombre restricción chequeo a la que pertenece | P6: ¿Posee restricción de índice o es parte de ella? | Q6: Tipo | R6: Nombre restricción índice a la que pertenece
A7: id | B7: UNIQUEIDENTIFIER | F7: NO | G7: SI | H7: SI | I7: NO | L7: NO | N7: NO | P7: NO | S7: id | T7: Identificador único universal de la dirección.
A8: cliente_id | B8: UNIQUEIDENTIFIER | F8: NO | G8: SI | H8: NO | I8: SI | J8: Cliente | K8: id | L8: NO | N8: NO | P8: NO | S8: cliente_id | T8: Referencia al cliente al que pertenece la dirección.
A9: calle | B9: NVARCHAR | C9: 200 | F9: NO | G9: SI | H9: NO | I9: NO | L9: NO | N9: NO | P9: NO | S9: calle | T9: Nomenclatura exacta de la dirección.
A10: ciudad | B10: NVARCHAR | C10: 100 | F10: NO | G10: SI | H10: NO | I10: NO | L10: NO | N10: NO | P10: NO | S10: ciudad | T10: Ciudad o municipio donde se ubica la dirección.
A11: departamento | B11: NVARCHAR | C11: 100 | F11: NO | G11: SI | H11: NO | I11: NO | L11: NO | N11: NO | P11: NO | S11: departamento | T11: Departamento o estado donde se ubica la dirección.
A12: codigo_postal | B12: NVARCHAR | C12: 10 | F12: NO | G12: NO | H12: NO | I12: NO | L12: NO | N12: NO | P12: NO | S12: codigo_postal | T12: Código postal de la dirección (opcional).
A13: pais | B13: NVARCHAR | C13: 100 | F13: NO | G13: SI | H13: NO | I13: NO | L13: NO | N13: NO | P13: NO | S13: pais | T13: País donde se ubica la dirección.
A14: es_principal | B14: BIT | F14: NO | G14: SI | H14: NO | I14: NO | L14: NO | N14: NO | P14: NO | S14: es_principal | T14: Indica si es la dirección principal del cliente.

Sheet Categoria
A1: <-Volver al inicio
A2: =Entidades!$A$1 -> Entidad | B2: =Entidades!A5 -> Categoria
A3: =Entidades!$B$1 -> Desripción | B3: =Entidades!B5 -> Objeto de dominio que representa a cada una de las agrupaciones taxonómicas en las que se organizan los productos del catálogo de Imexcol.
A4: Atributos
A5: Nombre | B5: Tipo de dato | C5: Longitud | D5: Cantidad dígitos parte entera | E5: Cantidad dígitos parte decimal (Precisión) | F5: ¿Es autoincremento? | G5: ¿Es obligatorio? | H5: ¿Es llave primeria o es parte de ella? | I5: Llave Foránea | L5: Restricciones de unicidad | N5: Restricciones de chequeo | P5: Restricciones de índice | S5: Alias | T5: Descripción del campo
I6: ¿Es llave foránea? | J6: Entidad | K6: Columna(s) | L6: ¿Posee restricción de unicidad o es parte de ella? | M6: Nombre restricción unicidad a la que pertenece | N6: ¿Posee restricción de chequeo o es parte de ella? | O6: Nombre restricción chequeo a la que pertenece | P6: ¿Posee restricción de índice o es parte de ella? | Q6: Tipo | R6: Nombre restricción índice a la que pertenece
A7: id | B7: UNIQUEIDENTIFIER | F7: NO | G7: SI | H7: SI | I7: NO | L7: NO | N7: NO | P7: NO | S7: id | T7: Identificador único universal de la categoría.
A8: nombre | B8: NVARCHAR | C8: 100 | F8: NO | G8: SI | H8: NO | I8: NO | L8: NO | N8: NO | P8: NO | S8: nombre | T8: Nombre comercial de la categoría.
A9: descripcion | B9: NVARCHAR | C9: 255 | F9: NO | G9: NO | H9: NO | I9: NO | L9: NO | N9: NO | P9: NO | S9: descripcion | T9: Descripción breve de la categoría (opcional).
A10: estado | B10: BIT | F10: NO | G10: SI | H10: NO | I10: NO | L10: NO | N10: NO | P10: NO | S10: estado | T10: Indica si la categoría está activa (1) o inactiva (0).

Sheet Producto
A1: <-Volver al inicio
A2: =Entidades!$A$1 -> Entidad | B2: =Entidades!A6 -> Producto
A3: =Entidades!$B$1 -> Desripción | B3: =Entidades!B6 -> Objeto de dominio que representa a cada uno de los artículos de importación (bolsos, juguetes, etc.) que están disponibles para la venta en la tienda.
A4: Atributos
A5: Nombre | B5: Tipo de dato | C5: Longitud | D5: Cantidad dígitos parte entera | E5: Cantidad dígitos parte decimal (Precisión) | F5: ¿Es autoincremento? | G5: ¿Es obligatorio? | H5: ¿Es llave primeria o es parte de ella? | I5: Llave Foránea | L5: Restricciones de unicidad | N5: Restricciones de chequeo | P5: Restricciones de índice | S5: Alias | T5: Descripción del campo
I6: ¿Es llave foránea? | J6: Entidad | K6: Columna(s) | L6: ¿Posee restricción de unicidad o es parte de ella? | M6: Nombre restricción unicidad a la que pertenece | N6: ¿Posee restricción de chequeo o es parte de ella? | O6: Nombre restricción chequeo a la que pertenece | P6: ¿Posee restricción de índice o es parte de ella? | Q6: Tipo | R6: Nombre restricción índice a la que pertenece
A7: id | B7: UNIQUEIDENTIFIER | F7: NO | G7: SI | H7: SI | I7: NO | L7: NO | N7: NO | P7: NO | S7: id | T7: Identificador único universal del producto.
A8: categoria_id | B8: UNIQUEIDENTIFIER | F8: NO | G8: SI | H8: NO | I8: SI | J8: Categoria | K8: id | L8: NO | N8: NO | P8: SI | Q8: ASC | R8: ix_imex_producto_categoria_id | S8: categoria_id | T8: Referencia a la categoría a la que pertenece el producto.
A9: nombre | B9: NVARCHAR | C9: 100 | F9: NO | G9: SI | H9: NO | I9: NO | L9: NO | N9: NO | P9: NO | S9: nombre | T9: Nombre comercial del producto.
A10: descripcion | B10: NVARCHAR | C10: 1000 | F10: NO | G10: NO | H10: NO | I10: NO | L10: NO | N10: NO | P10: NO | S10: descripcion | T10: Descripción detallada del producto (opcional).
A11: precio | B11: DECIMAL | D11: 12 | E11: 2 | F11: NO | G11: SI | H11: NO | I11: NO | L11: NO | N11: NO | P11: NO | S11: precio | T11: Precio del producto en pesos colombianos (COP).
A12: stock | B12: INT | F12: NO | G12: SI | H12: NO | I12: NO | L12: NO | N12: NO | P12: NO | S12: stock | T12: Cantidad de unidades disponibles en inventario.
A13: imagen_url | B13: NVARCHAR | C13: 255 | F13: NO | G13: NO | H13: NO | I13: NO | L13: NO | N13: NO | P13: NO | S13: imagen_url | T13: Ruta relativa o URL de la imagen del producto (opcional).
A14: estado | B14: BIT | F14: NO | G14: SI | H14: NO | I14: NO | L14: NO | N14: NO | P14: NO | S14: estado | T14: Indica si el producto está activo (1) o inactivo (0).

Sheet ImagenProducto
A1: <-Volver al inicio
A2: =Entidades!$A$1 -> Entidad | B2: =Entidades!A7 -> ImagenProducto
A3: =Entidades!$B$1 -> Desripción | B3: =Entidades!B7 -> Objeto de dominio que representa a cada uno de los recursos visuales o fotografías asociadas a un producto para su exhibición.
A4: Atributos
A5: Nombre | B5: Tipo de dato | C5: Longitud | D5: Cantidad dígitos parte entera | E5: Cantidad dígitos parte decimal (Precisión) | F5: ¿Es autoincremento? | G5: ¿Es obligatorio? | H5: ¿Es llave primeria o es parte de ella? | I5: Llave Foránea | L5: Restricciones de unicidad | N5: Restricciones de chequeo | P5: Restricciones de índice | S5: Alias | T5: Descripción del campo
I6: ¿Es llave foránea? | J6: Entidad | K6: Columna(s) | L6: ¿Posee restricción de unicidad o es parte de ella? | M6: Nombre restricción unicidad a la que pertenece | N6: ¿Posee restricción de chequeo o es parte de ella? | O6: Nombre restricción chequeo a la que pertenece | P6: ¿Posee restricción de índice o es parte de ella? | Q6: Tipo | R6: Nombre restricción índice a la que pertenece
A7: idImagen | B7: VARCHAR | C7: 10 | F7: NO | G7: SI | H7: SI | I7: NO | L7: NO | N7: NO | P7: NO | S7: idimagen | T7: Representa el identificador único de cada imagen generado automáticamente por el sistema.
A8: idProducto | B8: VARCHAR | C8: 10 | F8: NO | G8: SI | H8: NO | I8: SI | J8: Producto | K8: idProducto | L8: NO | N8: NO | P8: SI | Q8: ASC | R8: idx_imagen_producto | S8: idproducto | T8: Representa el producto al cual pertenece esta imagen.
A9: foto | B9: VARCHAR | C9: 255 | F9: NO | G9: SI | H9: NO | I9: NO | L9: SI | M9: uq_imagen_producto_url | N9: NO | P9: NO | S9: foto | T9: Representa la ruta web o enlace donde está alojada la fotografía del artículo.
A10: ordenVisualizacion | B10: INT | D10: 4 | F10: NO | G10: SI | H10: NO | I10: NO | L10: NO | N10: SI | O10: chk_imagen_orden | P10: NO | S10: ordenVisualizacion | T10: Representa el número secuencial que define en qué orden se muestran las fotos en la galería.

Sheet Resena
A1: <-Volver al inicio
A2: =Entidades!$A$1 -> Entidad | B2: =Entidades!A8 -> Resena
A3: =Entidades!$B$1 -> Desripción | B3: =Entidades!B8 -> Objeto de dominio que representa a cada una de las calificaciones y comentarios dejados por un cliente sobre un producto específico que ya ha comprado.
A4: Atributos
A5: Nombre | B5: Tipo de dato | C5: Longitud | D5: Cantidad dígitos parte entera | E5: Cantidad dígitos parte decimal (Precisión) | F5: ¿Es autoincremento? | G5: ¿Es obligatorio? | H5: ¿Es llave primeria o es parte de ella? | I5: Llave Foránea | L5: Restricciones de unicidad | N5: Restricciones de chequeo | P5: Restricciones de índice | S5: Alias | T5: Descripción del campo
I6: ¿Es llave foránea? | J6: Entidad | K6: Columna(s) | L6: ¿Posee restricción de unicidad o es parte de ella? | M6: Nombre restricción unicidad a la que pertenece | N6: ¿Posee restricción de chequeo o es parte de ella? | O6: Nombre restricción chequeo a la que pertenece | P6: ¿Posee restricción de índice o es parte de ella? | Q6: Tipo | R6: Nombre restricción índice a la que pertenece
A7: idResena | B7: VARCHAR | C7: 10 | F7: NO | G7: SI | H7: SI | I7: NO | L7: NO | N7: NO | P7: NO | S7: idReseña | T7: Representa el identificador único de cada reseña generado automáticamente por el sistema.
A8: idCliente | B8: VARCHAR | C8: 10 | F8: NO | G8: SI | H8: NO | I8: SI | J8: Cliente | K8: idCliente | L8: SI | M8: uq_resena_cliente_producto | N8: NO | P8: SI | Q8: ASC | R8: idx_resena_cliente | S8: idCliente | T8: Referencia al cliente que escribe la opinión.
A9: idProducto | B9: VARCHAR | C9: 10 | F9: NO | G9: SI | H9: NO | I9: SI | J9: Producto | K9: idProducto | L9: SI | M9: uq_resena_cliente_producto | N9: NO | P9: SI | Q9: ASC | R9: idx_resena_producto | S9: idProducto | T9: Referencia al producto que es calificado.
A10: calificacion | B10: INT | D10: 1 | F10: NO | G10: SI | H10: NO | I10: NO | L10: NO | N10: SI | O10: chk_resena_calificacion | P10: NO | S10: calificacion | T10: Puntuación otorgada al artículo, generalmente en una escala de 1 a 5 estrellas.
A11: comentario | B11: VARCHAR | C11: 255 | F11: NO | G11: NO | H11: NO | I11: NO | L11: NO | N11: NO | P11: NO | S11: comentario | T11: Representa el texto opcional donde el cliente describe su experiencia de uso y calidad.
A12: fecha | B12: DATETIME | F12: NO | G12: SI | H12: NO | I12: NO | L12: NO | N12: NO | P12: SI | Q12: ASC | R12: idx_resena_fecha | S12: fecha | T12: Representa la fecha y hora en que fue creada la reseña por parte del cliente.

Sheet CarritoCompras
A1: <-Volver al inicio
A2: =Entidades!$A$1 -> Entidad | B2: =Entidades!A9 -> CarritoCompras
A3: =Entidades!$B$1 -> Desripción | B3: =Entidades!B9 -> Objeto de dominio que representa la sesión temporal donde un cliente agrupa los productos que tiene intención de adquirir antes de formalizar la transacción.
A4: Atributos
A5: Nombre | B5: Tipo de dato | C5: Longitud | D5: Cantidad dígitos parte entera | E5: Cantidad dígitos parte decimal (Precisión) | F5: ¿Es autoincremento? | G5: ¿Es obligatorio? | H5: ¿Es llave primeria o es parte de ella? | I5: Llave Foránea | L5: Restricciones de unicidad | N5: Restricciones de chequeo | P5: Restricciones de índice | S5: Alias | T5: Descripción del campo
I6: ¿Es llave foránea? | J6: Entidad | K6: Columna(s) | L6: ¿Posee restricción de unicidad o es parte de ella? | M6: Nombre restricción unicidad a la que pertenece | N6: ¿Posee restricción de chequeo o es parte de ella? | O6: Nombre restricción chequeo a la que pertenece | P6: ¿Posee restricción de índice o es parte de ella? | Q6: Tipo | R6: Nombre restricción índice a la que pertenece
A7: id | B7: UNIQUEIDENTIFIER | F7: NO | G7: SI | H7: SI | I7: NO | L7: NO | N7: NO | P7: NO | S7: id | T7: Identificador único universal del carrito.
A8: cliente_id | B8: UNIQUEIDENTIFIER | F8: NO | G8: SI | H8: NO | I8: SI | J8: Cliente | K8: id | L8: NO | N8: NO | P8: NO | S8: cliente_id | T8: Referencia al cliente propietario del carrito.
A9: fecha_creacion | B9: DATE | F9: NO | G9: SI | H9: NO | I9: NO | L9: NO | N9: NO | P9: NO | S9: fecha_creacion | T9: Fecha de creación del carrito.
A10: estado | B10: NVARCHAR | C10: 20 | F10: NO | G10: SI | H10: NO | I10: NO | L10: NO | N10: NO | P10: NO | S10: estado | T10: Estado del carrito (ACTIVO, ABANDONADO, FINALIZADO).

Sheet ItemCarrito
A1: <-Volver al inicio
A2: =Entidades!$A$1 -> Entidad | B2: =Entidades!A10 -> ItemCarrito
A3: =Entidades!$B$1 -> Desripción | B3: =Entidades!B10 -> Objeto de dominio que representa a cada una de las selecciones individuales (producto específico y cantidad) dentro del carrito activo de un cliente.
A4: Atributos
A5: Nombre | B5: Tipo de dato | C5: Longitud | D5: Cantidad dígitos parte entera | E5: Cantidad dígitos parte decimal (Precisión) | F5: ¿Es autoincremento? | G5: ¿Es obligatorio? | H5: ¿Es llave primeria o es parte de ella? | I5: Llave Foránea | L5: Restricciones de unicidad | N5: Restricciones de chequeo | P5: Restricciones de índice | S5: Alias | T5: Descripción del campo
I6: ¿Es llave foránea? | J6: Entidad | K6: Columna(s) | L6: ¿Posee restricción de unicidad o es parte de ella? | M6: Nombre restricción unicidad a la que pertenece | N6: ¿Posee restricción de chequeo o es parte de ella? | O6: Nombre restricción chequeo a la que pertenece | P6: ¿Posee restricción de índice o es parte de ella? | Q6: Tipo | R6: Nombre restricción índice a la que pertenece
A7: id | B7: UNIQUEIDENTIFIER | F7: NO | G7: SI | H7: SI | I7: NO | L7: NO | N7: NO | P7: NO | S7: id | T7: Identificador único universal del ítem del carrito.
A8: carrito_id | B8: UNIQUEIDENTIFIER | F8: NO | G8: SI | H8: NO | I8: SI | J8: CarritoCompras | K8: id | L8: NO | N8: NO | P8: NO | S8: carrito_id | T8: Referencia al carrito al que pertenece el ítem.
A9: producto_id | B9: UNIQUEIDENTIFIER | F9: NO | G9: SI | H9: NO | I9: SI | J9: Producto | K9: id | L9: NO | N9: NO | P9: NO | S9: producto_id | T9: Referencia al producto agregado al carrito.
A10: cantidad | B10: INT | F10: NO | G10: SI | H10: NO | I10: NO | L10: NO | N10: NO | P10: NO | S10: cantidad | T10: Número de unidades del producto en el carrito.
A11: precio_unitario | B11: DECIMAL | D11: 12 | E11: 2 | F11: NO | G11: SI | H11: NO | I11: NO | L11: NO | N11: NO | P11: NO | S11: precio_unitario | T11: Precio unitario congelado del producto en el carrito.
A12: subtotal | B12: DECIMAL | D12: 18 | E12: 2 | F12: NO | G12: SI | H12: NO | I12: NO | L12: NO | N12: NO | P12: NO | S12: subtotal | T12: Subtotal de la línea del ítem del carrito (cantidad × precio_unitario).

Sheet Pedido
A1: <-Volver al inicio
A2: =Entidades!$A$1 -> Entidad | B2: =Entidades!A11 -> Pedido
A3: =Entidades!$B$1 -> Desripción | B3: =Entidades!B11 -> Objeto de dominio que representa la confirmación formal, transaccional y definitiva de una compra realizada por un cliente en Imexcol.
A4: Atributos
A5: Nombre | B5: Tipo de dato | C5: Longitud | D5: Cantidad dígitos parte entera | E5: Cantidad dígitos parte decimal (Precisión) | F5: ¿Es autoincremento? | G5: ¿Es obligatorio? | H5: ¿Es llave primeria o es parte de ella? | I5: Llave Foránea | L5: Restricciones de unicidad | N5: Restricciones de chequeo | P5: Restricciones de índice | S5: Alias | T5: Descripción del campo
I6: ¿Es llave foránea? | J6: Entidad | K6: Columna(s) | L6: ¿Posee restricción de unicidad o es parte de ella? | M6: Nombre restricción unicidad a la que pertenece | N6: ¿Posee restricción de chequeo o es parte de ella? | O6: Nombre restricción chequeo a la que pertenece | P6: ¿Posee restricción de índice o es parte de ella? | Q6: Tipo | R6: Nombre restricción índice a la que pertenece
A7: id | B7: UNIQUEIDENTIFIER | F7: NO | G7: SI | H7: SI | I7: NO | L7: NO | N7: NO | P7: NO | S7: id | T7: Identificador único universal del pedido.
A8: cliente_id | B8: UNIQUEIDENTIFIER | F8: NO | G8: SI | H8: NO | I8: SI | J8: Cliente | K8: id | L8: NO | N8: NO | P8: SI | Q8: ASC | R8: ix_imex_pedido_cliente_id | S8: cliente_id | T8: Referencia al cliente que realizó el pedido.
A9: fecha_pedido | B9: DATE | F9: NO | G9: SI | H9: NO | I9: NO | L9: NO | N9: NO | P9: NO | S9: fecha_pedido | T9: Fecha en que se generó el pedido.
A10: total | B10: DECIMAL | D10: 12 | E10: 2 | F10: NO | G10: SI | H10: NO | I10: NO | L10: NO | N10: NO | P10: NO | S10: total | T10: Valor total del pedido en pesos colombianos (COP).
A11: estado | B11: NVARCHAR | C11: 50 | F11: NO | G11: SI | H11: NO | I11: NO | L11: NO | N11: NO | P11: SI | Q11: ASC | R11: ix_imex_pedido_estado | S11: estado | T11: Estado del pedido (PENDIENTE, CONFIRMADO, PREPARANDO, ENVIADO, ENTREGADO, CANCELADO).
A12: direccion_id | B12: UNIQUEIDENTIFIER | F12: NO | G12: NO | H12: NO | I12: SI | J12: Direccion | K12: id | L12: NO | N12: NO | P12: NO | S12: direccion_id | T12: Referencia a la dirección de envío del pedido (opcional).

Sheet LineaPedido
A1: <-Volver al inicio
A2: =Entidades!$A$1 -> Entidad | B2: =Entidades!A12 -> LineaPedido
A3: =Entidades!$B$1 -> Desripción | B3: =Entidades!B12 -> Objeto de dominio que representa el detalle individual de un pedido, permitiendo registrar de forma histórica cada producto adquirido, su cantidad y su valor al momento de confirmar la compra. (Evidencia histórica de la compra)
A4: Atributos
A5: Nombre | B5: Tipo de dato | C5: Longitud | D5: Cantidad dígitos parte entera | E5: Cantidad dígitos parte decimal (Precisión) | F5: ¿Es autoincremento? | G5: ¿Es obligatorio? | H5: ¿Es llave primeria o es parte de ella? | I5: Llave Foránea | L5: Restricciones de unicidad | N5: Restricciones de chequeo | P5: Restricciones de índice | S5: Alias | T5: Descripción del campo
I6: ¿Es llave foránea? | J6: Entidad | K6: Columna(s) | L6: ¿Posee restricción de unicidad o es parte de ella? | M6: Nombre restricción unicidad a la que pertenece | N6: ¿Posee restricción de chequeo o es parte de ella? | O6: Nombre restricción chequeo a la que pertenece | P6: ¿Posee restricción de índice o es parte de ella? | Q6: Tipo | R6: Nombre restricción índice a la que pertenece
A7: id | B7: UNIQUEIDENTIFIER | F7: NO | G7: SI | H7: SI | I7: NO | L7: NO | N7: NO | P7: NO | S7: id | T7: Identificador único universal de la línea de pedido.
A8: pedido_id | B8: UNIQUEIDENTIFIER | F8: NO | G8: SI | H8: NO | I8: SI | J8: Pedido | K8: id | L8: NO | N8: NO | P8: NO | S8: pedido_id | T8: Referencia al pedido al que pertenece la línea.
A9: producto_id | B9: UNIQUEIDENTIFIER | F9: NO | G9: SI | H9: NO | I9: SI | J9: Producto | K9: id | L9: NO | N9: NO | P9: NO | S9: producto_id | T9: Referencia al producto incluido en la línea.
A10: cantidad | B10: INT | F10: NO | G10: SI | H10: NO | I10: NO | L10: NO | N10: NO | P10: NO | S10: cantidad | T10: Número de unidades del producto en la línea.
A11: precio_unitario | B11: DECIMAL | D11: 12 | E11: 2 | F11: NO | G11: SI | H11: NO | I11: NO | L11: NO | N11: NO | P11: NO | S11: precio_unitario | T11: Precio unitario congelado del producto al momento del pedido.
A12: subtotal | B12: DECIMAL | D12: 12 | E12: 2 | F12: NO | G12: SI | H12: NO | I12: NO | L12: NO | N12: NO | P12: NO | S12: subtotal | T12: Subtotal de la línea (cantidad × precioUnitario).

Sheet Pago
A1: <-Volver al inicio
A2: =Entidades!$A$1 -> Entidad | B2: =Entidades!A13 -> Pago
A3: =Entidades!$B$1 -> Desripción | B3: =Entidades!B13 -> Objeto de dominio que representa el registro de la transacción financiera procesada a través de la pasarela de pagos para saldar un pedido.
A4: Atributos
A5: Nombre | B5: Tipo de dato | C5: Longitud | D5: Cantidad dígitos parte entera | E5: Cantidad dígitos parte decimal (Precisión) | F5: ¿Es autoincremento? | G5: ¿Es obligatorio? | H5: ¿Es llave primeria o es parte de ella? | I5: Llave Foránea | L5: Restricciones de unicidad | N5: Restricciones de chequeo | P5: Restricciones de índice | S5: Alias | T5: Descripción del campo
I6: ¿Es llave foránea? | J6: Entidad | K6: Columna(s) | L6: ¿Posee restricción de unicidad o es parte de ella? | M6: Nombre restricción unicidad a la que pertenece | N6: ¿Posee restricción de chequeo o es parte de ella? | O6: Nombre restricción chequeo a la que pertenece | P6: ¿Posee restricción de índice o es parte de ella? | Q6: Tipo | R6: Nombre restricción índice a la que pertenece
A7: id | B7: UNIQUEIDENTIFIER | F7: NO | G7: SI | H7: SI | I7: NO | L7: NO | N7: NO | P7: NO | S7: id | T7: Identificador único universal del pago.
A8: pedido_id | B8: UNIQUEIDENTIFIER | F8: NO | G8: SI | H8: NO | I8: SI | J8: Pedido | K8: id | L8: NO | N8: NO | P8: NO | S8: pedido_id | T8: Referencia al pedido asociado al pago.
A9: metodo_pago_id | B9: UNIQUEIDENTIFIER | F9: NO | G9: SI | H9: NO | I9: SI | J9: MetodoPago | K9: id | L9: NO | N9: NO | P9: NO | S9: metodo_pago_id | T9: Referencia al método de pago utilizado.
A10: monto | B10: DECIMAL | D10: 12 | E10: 2 | F10: NO | G10: SI | H10: NO | I10: NO | L10: NO | N10: NO | P10: NO | S10: monto | T10: Monto del pago en pesos colombianos (COP).
A11: fecha_pago | B11: DATE | F11: NO | G11: SI | H11: NO | I11: NO | L11: NO | N11: NO | P11: NO | S11: fecha_pago | T11: Fecha en que se procesó el pago.
A12: estado | B12: NVARCHAR | C12: 50 | F12: NO | G12: SI | H12: NO | I12: NO | L12: NO | N12: NO | P12: NO | S12: estado | T12: Estado del pago (PENDIENTE, EN_PROCESO, APROBADO, RECHAZADO, REEMBOLSADO).

Sheet MetodoPago
A1: <-Volver al inicio
A2: =Entidades!$A$1 -> Entidad | B2: =Entidades!A14 -> MetodoPago
A3: =Entidades!$B$1 -> Desripción | B3: =Entidades!B14 -> Objeto de dominio que representa el instrumento financiero o forma transaccional utilizada por el cliente (tarjeta de crédito, PSE, etc.) para realizar el pago.
A4: Atributos
A5: Nombre | B5: Tipo de dato | C5: Longitud | D5: Cantidad dígitos parte entera | E5: Cantidad dígitos parte decimal (Precisión) | F5: ¿Es autoincremento? | G5: ¿Es obligatorio? | H5: ¿Es llave primeria o es parte de ella? | I5: Llave Foránea | L5: Restricciones de unicidad | N5: Restricciones de chequeo | P5: Restricciones de índice | S5: Alias | T5: Descripción del campo
I6: ¿Es llave foránea? | J6: Entidad | K6: Columna(s) | L6: ¿Posee restricción de unicidad o es parte de ella? | M6: Nombre restricción unicidad a la que pertenece | N6: ¿Posee restricción de chequeo o es parte de ella? | O6: Nombre restricción chequeo a la que pertenece | P6: ¿Posee restricción de índice o es parte de ella? | Q6: Tipo | R6: Nombre restricción índice a la que pertenece
A7: id | B7: UNIQUEIDENTIFIER | F7: NO | G7: SI | H7: SI | I7: NO | L7: NO | N7: NO | P7: NO | S7: id | T7: Identificador único universal del método de pago.
A8: nombre | B8: NVARCHAR | C8: 100 | F8: NO | G8: SI | H8: NO | I8: NO | L8: NO | N8: NO | P8: NO | S8: nombre | T8: Nombre comercial del método de pago.
A9: descripcion | B9: NVARCHAR | C9: 255 | F9: NO | G9: NO | H9: NO | I9: NO | L9: NO | N9: NO | P9: NO | S9: descripcion | T9: Descripción del método de pago (opcional).
A10: estado | B10: BIT | F10: NO | G10: SI | H10: NO | I10: NO | L10: NO | N10: NO | P10: NO | S10: estado | T10: Indica si el método de pago está activo (1) o inactivo (0).

Sheet Factura
A1: <-Volver al inicio
A2: =Entidades!$A$1 -> Entidad | B2: =Entidades!A15 -> Factura
A3: =Entidades!$B$1 -> Desripción | B3: =Entidades!B15 -> Objeto de dominio que representa el comprobante legal y contable emitido al cliente con el desglose de impuestos una vez el pago ha sido exitoso.
A4: Atributos
A5: Nombre | B5: Tipo de dato | C5: Longitud | D5: Cantidad dígitos parte entera | E5: Cantidad dígitos parte decimal (Precisión) | F5: ¿Es autoincremento? | G5: ¿Es obligatorio? | H5: ¿Es llave primeria o es parte de ella? | I5: Llave Foránea | L5: Restricciones de unicidad | N5: Restricciones de chequeo | P5: Restricciones de índice | S5: Alias | T5: Descripción del campo
I6: ¿Es llave foránea? | J6: Entidad | K6: Columna(s) | L6: ¿Posee restricción de unicidad o es parte de ella? | M6: Nombre restricción unicidad a la que pertenece | N6: ¿Posee restricción de chequeo o es parte de ella? | O6: Nombre restricción chequeo a la que pertenece | P6: ¿Posee restricción de índice o es parte de ella? | Q6: Tipo | R6: Nombre restricción índice a la que pertenece
A7: idFactura | B7: VARCHAR | C7: 10 | F7: NO | G7: SI | H7: SI | I7: NO | L7: NO | N7: NO | P7: NO | S7: idFactura | T7: Identificador interno autogenerado por el sistema.
A8: idPago | B8: VARCHAR | C8: 12 | F8: NO | G8: SI | H8: NO | I8: SI | J8: Pago | K8: idPago | L8: SI | M8: uq_factura_pago | N8: NO | P8: SI | Q8: ASC | R8: idx_factura_pago | S8: idPago | T8: Referencia al pago exitoso que originó esta factura.
A9: numeroFactura | B9: VARCHAR | C9: 20 | F9: NO | G9: SI | H9: NO | I9: NO | L9: SI | M9: uq_factura_numero | N9: NO | P9: NO | S9: numeroFactura | T9: Número de factura electrónica.
A10: fechaEmision | B10: DATETIME | F10: NO | G10: SI | H10: NO | I10: NO | L10: NO | N10: NO | P10: NO | S10: fechaEmision | T10: Fecha y hora de emisión del comprobante contable.
A11: subtotal | B11: DECIMAL | D11: 12 | E11: 2 | F11: NO | G11: SI | H11: NO | I11: NO | L11: NO | N11: SI | O11: chk_factura_subtotal | P11: NO | S11: subtotal | T11: Valor base de la compra sin impuestos (COP).
A12: totalImpuestos | B12: DECIMAL | D12: 12 | E12: 2 | F12: NO | G12: SI | H12: NO | I12: NO | L12: NO | N12: SI | O12: chk_factura_impuestos | P12: NO | S12: totalImpuestos | T12: Valor correspondiente al IVA u otros tributos (COP).
A13: totalFacturado | B13: DECIMAL | D13: 12 | E13: 2 | F13: NO | G13: SI | H13: NO | I13: NO | L13: NO | N13: SI | O13: chk_factura_total | P13: NO | S13: totalFacturado | T13: Valor total legalmente facturado al cliente (COP).

Sheet Envio
A1: <-Volver al inicio
A2: =Entidades!$A$1 -> Entidad | B2: =Entidades!A16 -> Envio
A3: =Entidades!$B$1 -> Desripción | B3: =Entidades!B16 -> Objeto de dominio que representa el proceso logístico y de despacho de un pedido aprobado hacia la dirección de entrega del cliente.
A4: Atributos
A5: Nombre | B5: Tipo de dato | C5: Longitud | D5: Cantidad dígitos parte entera | E5: Cantidad dígitos parte decimal (Precisión) | F5: ¿Es autoincremento? | G5: ¿Es obligatorio? | H5: ¿Es llave primeria o es parte de ella? | I5: Llave Foránea | L5: Restricciones de unicidad | N5: Restricciones de chequeo | P5: Restricciones de índice | S5: Alias | T5: Descripción del campo
I6: ¿Es llave foránea? | J6: Entidad | K6: Columna(s) | L6: ¿Posee restricción de unicidad o es parte de ella? | M6: Nombre restricción unicidad a la que pertenece | N6: ¿Posee restricción de chequeo o es parte de ella? | O6: Nombre restricción chequeo a la que pertenece | P6: ¿Posee restricción de índice o es parte de ella? | Q6: Tipo | R6: Nombre restricción índice a la que pertenece
A7: id | B7: UNIQUEIDENTIFIER | F7: NO | G7: SI | H7: SI | I7: NO | L7: NO | N7: NO | P7: NO | S7: id | T7: Identificador único universal del envío.
A8: pedido_id | B8: UNIQUEIDENTIFIER | F8: NO | G8: SI | H8: NO | I8: SI | J8: Pedido | K8: id | L8: NO | N8: NO | P8: NO | S8: pedido_id | T8: Referencia al pedido al que pertenece el envío.
A9: fecha_envio | B9: DATE | F9: NO | G9: SI | H9: NO | I9: NO | L9: NO | N9: NO | P9: NO | S9: fecha_envio | T9: Fecha en que se despachó el envío.
A10: fecha_entrega | B10: DATE | F10: NO | G10: NO | H10: NO | I10: NO | L10: NO | N10: NO | P10: NO | S10: fecha_entrega | T10: Fecha estimada o real de entrega del envío (opcional).
A11: transportadora | B11: NVARCHAR | C11: 100 | F11: NO | G11: SI | H11: NO | I11: NO | L11: NO | N11: NO | P11: NO | S11: transportadora | T11: Nombre de la empresa transportadora.
A12: numero_guia | B12: NVARCHAR | C12: 100 | F12: NO | G12: SI | H12: NO | I12: NO | L12: NO | N12: NO | P12: NO | S12: numero_guia | T12: Número de guía proporcionado por la transportadora.
A13: estado | B13: NVARCHAR | C13: 50 | F13: NO | G13: SI | H13: NO | I13: NO | L13: NO | N13: NO | P13: NO | S13: estado | T13: Estado del envío (PREPARANDO, EN_TRANSITO, ENTREGADO, DEVUELTO, EXTRAVIADO).

Sheet EventoRastreo
A1: <-Volver al inicio
A2: =Entidades!$A$1 -> Entidad | B2: =Entidades!A17 -> EventoRastreo
A3: =Entidades!$B$1 -> Desripción | B3: =Entidades!B17 -> Objeto de dominio que representa a cada una de las actualizaciones o hitos temporales (ej. en preparación, en tránsito, entregado) que ocurren durante el ciclo de vida de un envío.
A4: Atributos
A5: Nombre | B5: Tipo de dato | C5: Longitud | D5: Cantidad dígitos parte entera | E5: Cantidad dígitos parte decimal (Precisión) | F5: ¿Es autoincremento? | G5: ¿Es obligatorio? | H5: ¿Es llave primeria o es parte de ella? | I5: Llave Foránea | L5: Restricciones de unicidad | N5: Restricciones de chequeo | P5: Restricciones de índice | S5: Alias | T5: Descripción del campo
I6: ¿Es llave foránea? | J6: Entidad | K6: Columna(s) | L6: ¿Posee restricción de unicidad o es parte de ella? | M6: Nombre restricción unicidad a la que pertenece | N6: ¿Posee restricción de chequeo o es parte de ella? | O6: Nombre restricción chequeo a la que pertenece | P6: ¿Posee restricción de índice o es parte de ella? | Q6: Tipo | R6: Nombre restricción índice a la que pertenece
A7: idEvento | B7: VARCHAR | C7: 10 | F7: NO | G7: SI | H7: SI | I7: NO | L7: NO | N7: NO | P7: NO | S7: idEvento | T7: Identificador interno autogenerado por el sistema para el evento de rastreo.
A8: idEnvio | B8: VARCHAR | C8: 10 | F8: NO | G8: SI | H8: NO | I8: SI | J8: Envio | K8: idEnvio | L8: SI | M8: uq_evento_envio_estado_fecha | N8: NO | P8: SI | Q8: ASC | R8: idx_evento_envio | S8: idEnvio | T8: Referencia al envío al que pertenece este evento.
A9: estadoLogistico | B9: VARCHAR | C9: 30 | F9: NO | G9: SI | H9: NO | I9: NO | L9: SI | M9: uq_evento_envio_estado_fecha | N9: SI | O9: chk_evento_estado | P9: NO | S9: estadoLogistico | T9: Estado logístico reportado por la transportadora.
A10: fechaHora | B10: DATETIME | F10: NO | G10: SI | H10: NO | I10: NO | L10: SI | M10: uq_evento_envio_estado_fecha | N10: NO | P10: SI | Q10: ASC | R10: idx_evento_fecha | S10: fechaHora | T10: Fecha y hora exacta en la que se registró este estado.
A11: observacion | B11: VARCHAR | C11: 255 | F11: NO | G11: NO | H11: NO | I11: NO | L11: NO | N11: NO | P11: NO | S11: observacion | T11: Observación o detalle adicional del movimiento (ciudad, sede, novedad).

Sheet Valores
A1: Relación | B1: Tipo relación | C1: Estado | D1: TipoIndice
A2: Necesita de | B2: Asociación | C2: SI | D2: ASC
A3: Es usada por | C3: NO | D3: DESC
