Workbook

Sheet Modelo de dominio
A1: Ir al listado de objetos de dominio >>

Sheet Modelo de dominio anémico
A1: Ir al listado de objetos de dominio >>

Sheet ListadoObjetosDominio
A1: <<Ir al modelo de dominio
A2: Línea de vida | B2: Nombre | C2: Descripción | D2: Muestreo de datos | E2: Caracterización objeto | F2: Event Storming | G2: Politicas
A3: 1 | B3: Cliente | C3: Objeto de dominio que representa a cada uno de los usuarios registrados que realizan compras en la plataforma de Imexcol. | D3: Ir | E3: =HYPERLINK("#'C-Cliente'!B2", "Ir") -> Ir | F3: Ir | G3: Ir
A4: 2 | B4: Administrador | C4: Objeto de dominio que representa al personal interno encargado de gestionar el catálogo, los pedidos y la operación general del sistema. | D4: Ir | E4: =HYPERLINK("#'C-Administrador'!B2", "Ir") -> Ir | F4: Ir | G4: Ir
A5: 3 | B5: Dirección | C5: Objeto de dominio que representa la ubicación física y estructurada que registra un cliente para la entrega de sus productos o propósitos de facturación. | D5: Ir | E5: =HYPERLINK("#'C-Direccion'!B2", "Ir") -> Ir | F5: Ir | G5: Ir
A6: 4 | B6: Categoría | C6: Objeto de dominio que representa a cada una de las agrupaciones taxonómicas en las que se organizan los productos del catálogo de Imexcol. | D6: Ir | E6: =HYPERLINK("#'C-Categoria'!B2", "Ir") -> Ir | F6: Ir | G6: Ir
A7: 5 | B7: Producto | C7: Objeto de dominio que representa a cada uno de los artículos de importación (bolsos, juguetes, etc.) que están disponibles para la venta en la tienda. | D7: Ir | E7: =HYPERLINK("#'C-Producto'!B2", "Ir") -> Ir | F7: Ir | G7: Ir
A8: 6 | B8: ImagenProducto | C8: Objeto de dominio que representa a cada uno de los recursos visuales o fotografías asociadas a un producto para su exhibición. | D8: Ir | E8: =HYPERLINK("#'C-ImagenProducto'!B2", "Ir") -> Ir | F8: Ir | G8: Ir
A9: 7 | B9: Reseña | C9: Objeto de dominio que representa a cada una de las calificaciones y comentarios dejados por un cliente sobre un producto específico que ya ha comprado. | D9: Ir | E9: =HYPERLINK("#'C-Reseña'!B2", "Ir") -> Ir | F9: Ir | G9: Ir
A10: 8 | B10: CarritoCompras | C10: Objeto de dominio que representa la sesión temporal donde un cliente agrupa los productos que tiene intención de adquirir antes de formalizar la transacción. | D10: Ir | E10: =HYPERLINK("#'C-CarritoCompras'!B2", "Ir") -> Ir | F10: Ir | G10: Ir
A11: 9 | B11: ItemCarrito | C11: Objeto de dominio que representa a cada una de las selecciones individuales (producto específico y cantidad) dentro del carrito activo de un cliente. | D11: Ir | E11: =HYPERLINK("#'C-ItemCarrito'!B2", "Ir") -> Ir | F11: Ir | G11: Ir
A12: 10 | B12: Pedido | C12: Objeto de dominio que representa la confirmación formal, transaccional y definitiva de una compra realizada por un cliente en Imexcol. | D12: Ir | E12: =HYPERLINK("#'C-Pedido'!B2", "Ir") -> Ir | F12: Ir | G12: Ir
A13: 11 | B13: LineaPedido | C13: Objeto de dominio que representa el detalle individual de un pedido, permitiendo registrar de forma histórica cada producto adquirido, su cantidad y su valor al momento de confirmar la compra. (Evidencia histórica de la compra) | D13: Ir | E13: =HYPERLINK("#'C-LineaPedido'!B2", "Ir") -> Ir | F13: Ir | G13: Ir
A14: 12 | B14: Pago | C14: Objeto de dominio que representa el registro de la transacción financiera procesada a través de la pasarela de pagos para saldar un pedido. | D14: Ir | E14: =HYPERLINK("#'C-Pago'!B2", "Ir") -> Ir | F14: Ir | G14: Ir
A15: 13 | B15: MetodoPago | C15: Objeto de dominio que representa el instrumento financiero o forma transaccional utilizada por el cliente (tarjeta de crédito, PSE, etc.) para realizar el pago. | D15: Ir | E15: =HYPERLINK("#'C-MetodoPago'!B2", "Ir") -> Ir | F15: Ir | G15: Ir
A16: 14 | B16: Factura | C16: Objeto de dominio que representa el comprobante legal y contable emitido al cliente con el desglose de impuestos una vez el pago ha sido exitoso. | D16: Ir | E16: =HYPERLINK("#'C-Factura'!B2", "Ir") -> Ir | F16: Ir | G16: Ir
A17: 15 | B17: Envio | C17: Objeto de dominio que representa el proceso logístico y de despacho de un pedido aprobado hacia la dirección de entrega del cliente. | D17: Ir | E17: =HYPERLINK("#'C-Envio'!B2", "Ir") -> Ir | F17: Ir | G17: Ir
A18: 16 | B18: EventoRastreo | C18: Objeto de dominio que representa a cada una de las actualizaciones o hitos temporales (ej. en preparación, en tránsito, entregado) que ocurren durante el ciclo de vida de un envío. | D18: Ir | E18: =HYPERLINK("#'C-EnvioRastreo'!B2", "Ir") -> Ir | F18: Ir | G18: Ir

Sheet M-Cliente
A1: << Ir al modelo de dominio | I1: << Ir a la caracterización del objeto de dominio
F2: << Ir al listado de objetos de dominio
A3: Nombre | B3: =ListadoObjetosDominio!B3 -> Cliente
A4: Descripción | B4: =ListadoObjetosDominio!C3 -> Objeto de dominio que representa a cada uno de los usuarios registrados que realizan compras en la plataforma de Imexcol.
A5: Representa el identificador único de cada cliente, generado automáticamente por el sistema. | B5: Representa el tipo de documento de identidad del usuario | C5: Número oficial del documento de identidad | D5: Representa el nombre completo del cliente | E5: Representa el correo electrónico principal de contacto del cliente. | F5: Representa el número de teléfono celular de contacto del cliente. | G5: Indica que no pueden existir dos clientes o más con el mismo correo electrónico. | H5: Indica que no pueden existir dos clientes con el mismo id
A6: id | B6: nombre | C6: apellido | D6: correoElectronico | E6: contrasena | F6: telefono | G6: Combinación única 1 | H6: Combinación única 2
A7: 3F2504E0-4F89-11D3-9A0C-0305E82C3301 | B7: Carlos | C7: Restrepo | D7: carlos.restrepo@imexcol.com | E7: ******** | F7: 3001112233 | G7: =D7 -> carlos.restrepo@imexcol.com | H7: =A7 -> 3F2504E0-4F89-11D3-9A0C-0305E82C3301
A8: 3F2504E0-4F89-11D3-9A0C-0305E82C3302 | B8: María | C8: González | D8: maria.gonzalez@imexcol.com | E8: ******** | F8: 3104445566 | G8: =D8 -> maria.gonzalez@imexcol.com | H8: =A8 -> 3F2504E0-4F89-11D3-9A0C-0305E82C3302
A9: 3F2504E0-4F89-11D3-9A0C-0305E82C3303 | B9: Andrés | C9: Mejía | D9: andres.mejia@imexcol.com | E9: ******** | F9: 3207778899 | G9: =D9 -> andres.mejia@imexcol.com | H9: =A9 -> 3F2504E0-4F89-11D3-9A0C-0305E82C3303
A10: 3F2504E0-4F89-11D3-9A0C-0305E82C3304 | B10: Camila | C10: Ramírez | D10: camila.ramirez@imexcol.com | E10: ******** | F10: 3151231234 | G10: =D10 -> camila.ramirez@imexcol.com | H10: =A10 -> 3F2504E0-4F89-11D3-9A0C-0305E82C3304
A11: 3F2504E0-4F89-11D3-9A0C-0305E82C3305 | B11: Daniel | C11: Pérez | D11: daniel.perez@imexcol.com | E11: ******** | F11: 3009998877 | G11: =D11 -> daniel.perez@imexcol.com | H11: =A11 -> 3F2504E0-4F89-11D3-9A0C-0305E82C3305
A14: Corresponde a los datos generales del objeto de dominio (nombre, descripción)
A15: Corresponde a las descripciones de los atributos
A16: Coresponde al nombre de los atributos
A17: Corresponde a los datos que son de libre ingreso
A18: Corresponde a los datos que se generarán automáticamente (idCliente)
A19: Corresponde a la combinación única 1
A20: Corresponde a la combinación única 2

Sheet C-Cliente
A1: << Ir al modelo de dominio | D1: << Ir al listado de objetos de dominio | G1: << Ir a la caracterización del objeto de dominio
A2: Nombre | B2: ='M-Cliente'!B3 -> Cliente
A3: Descripción | B3: ='M-Cliente'!B4 -> Objeto de dominio que representa a cada uno de los usuarios registrados que realizan compras en la plataforma de Imexcol.
A4: Nombre atributo | B4: Descripción atributo | C4: Identificador del objeto de dominio | D4: Tipo de dato | E4: Obligatorio | F4: Longitud minima(si aplica longitud maxima(si aplica) | G4: Longitud maxima(si aplica longitud maxima(si aplica) | H4: Precisión (si aplica) | I4: Redondeo(si aplica) | J4: Rango inicial(si aplica) | K4: Rango final (si aplica) | L4: Formato(Si aplica) | M4: Reglas especiales(si aplica) | N4: Dato calculado | O4: Aplica ajuste del dato(si aplica) | P4: Carácter de ajuste(si aplica) | Q4: Quitar espacios en blanco al inicio(si aplica) | R4: Quitar espacios en blanco al fin(si aplica) | S4: Dato sensible(si aplica) | T4: Valor por defecto(si aplica) | U4: Auto generado
A5: ='M-Cliente'!A6 -> id | B5: ='M-Cliente'!A5 -> Representa el identificador único de cada cliente, generado automáticamente por el sistema. | C5: Si | D5: Alfanumerico | E5: Si | F5: 1 | L5: Mayusculas | N5: No | O5: No | Q5: Si | R5: Si | S5: No | U5: Si
A6: ='M-Cliente'!B6 -> nombre | B6: ='M-Cliente'!B5 -> Representa el tipo de documento de identidad del usuario | C6: No | D6: Alfanumerico | E6: Si | F6: 2 | G6: 100 | L6: Mayusculas | M6: Solo valores: CC, CE, NIT, TI | N6: No | O6: Si | P6: Espacio | Q6: Si | R6: Si | S6: No | U6: No
A7: ='M-Cliente'!C6 -> apellido | B7: ='M-Cliente'!D5 -> Representa el nombre completo del cliente | C7: No | D7: Alfanumerico | E7: Si | F7: 5 | G7: 100 | M7: Solo caracteres alfanuméricos | N7: No | O7: No | Q7: Si | R7: Si | S7: Si | U7: No
A8: ='M-Cliente'!D6 -> correoElectronico | B8: ='M-Cliente'!D5 -> Representa el nombre completo del cliente | C8: No | D8: Alfanumerico | E8: Si | F8: 3 | G8: 150 | L8: Capitalizado | N8: No | O8: No | Q8: Si | R8: Si | S8: No | U8: No
A9: ='M-Cliente'!E6 -> contrasena | B9: ='M-Cliente'!E5 -> Representa el correo electrónico principal de contacto del cliente. | C9: No | D9: Alfanumerico | E9: Si | F9: 5 | G9: 255 | L9: email | M9: Debe contener '@' y dominio válido | N9: No | O9: No | Q9: Si | R9: Si | S9: Si | U9: No
A10: ='M-Cliente'!F6 -> telefono | B10: ='M-Cliente'!F5 -> Representa el número de teléfono celular de contacto del cliente. | C10: No | D10: Alfanumerico | E10: No | F10: 10 | G10: 20 | N10: No | O10: No | Q10: No | R10: No | S10: Si | U10: No
A12: Nombre combinación unica | B12: Descripción | C12: Atributos involucrados
A13: ='M-Cliente'!G6 -> Combinación única 1 | B13: ='M-Cliente'!G5 -> Indica que no pueden existir dos clientes o más con el mismo correo electrónico. | C13: ='M-Cliente'!D6 -> correoElectronico
A14: ='M-Cliente'!H6 -> Combinación única 2 | B14: ='M-Cliente'!H5 -> Indica que no pueden existir dos clientes con el mismo id | C14: ='M-Cliente'!A6 -> id
A16: Responsabilidad | B16: Descripción | C16: Entradas | F16: Salida | H16: Políticas (Reglas de Negocio) | J16: Excepción
C17: Parámetro | D17: Tipo de dato | E17: Descripción | F17: Tipo de Dato | G17: Descripción | H17: Política | I17: Descripción | J17: Detalle | K17: ¿Qué hago?
A18: ='E-Cliente'!B7 -> Registrar información del cliente | B18: ='E-Cliente'!C7 -> Crear una nueva cuenta de usuario en la plataforma de comercio electrónico de Imexcol para poder realizar compras. | C18: clienteNuevo | D18: Cliente | E18: Contiene la información del cliente que se va a registrar. | F18: Logico | G18: Retorna verdadero si el cliente se registró y guardó correctamente. | H18: ='E-Cliente'!G7 -> CLI-POL-01 | I18: ='E-Cliente'!H7 -> Asegurar que los datos requeridos sean válidos a nivel de tipo de dato, formato, rango, longitud y obligatoriedad. | J18: Generar una excepción indicando que se violó la regla: el correo y el teléfono deben ser obligatorios y tener formato válido. | K18: Detener operación
H19: ='E-Cliente'!G8 -> CLI-POL-02 | I19: ='E-Cliente'!H8 -> El correo electrónico ingresado no debe existir previamente en el sistema (Combinación única 1). | J19: Generar excepción indicando que el correo ingresado ya se encuentra registrado por otro usuario. | K19: Detener operación
H20: ='E-Cliente'!G9 -> CLI-POL-03 | I20: ='E-Cliente'!H9 -> La combinación de tipo de documento y número de documento no debe existir previamente en el sistema (Combinación única 2). | J20: Generar excepción indicando que el documento ya está registrado por otro usuario. | K20: Detener operación
A21: ='E-Cliente'!B10 -> Modificar datos del cliente | B21: {='E-Cliente'!C10:C10} -> Actualizar la información personal de contacto (teléfono o nombre) del usuario registrado en el sistema. | C21: clienteModificado | D21: Cliente | E21: Contiene la nueva información del cliente a actualizar. | F21: Logico | G21: Retorna verdadero si la información se actualizó con éxito en la base de datos. | H21: ='E-Cliente'!G10 -> CLI-POL-04 | I21: ='E-Cliente'!H10 -> El identificador del cliente (idCliente) proporcionado debe existir obligatoriamente en el sistema. | J21: Generar excepción indicando que el cliente que se intenta modificar no existe. | K21: Detener operación
A22: ='E-Cliente'!B11 -> Consultar listado de clientes | B22: ='E-Cliente'!C11 -> Listar en el panel de control todos los usuarios registrados para gestión operativa y soporte. | C22: filtros | D22: Texto | E22: Parámetros opcionales para filtrar la búsqueda de clientes. | F22: Lista<Cliente> | G22: Retorna una colección con los objetos de los clientes encontrados. | H22: ='E-Cliente'!G11 -> CLI-POL-05 | I22: ='E-Cliente'!H11 -> El administrador que ejecuta la acción debe tener una sesión válida y activa en el sistema. | J22: Generar excepción indicando acceso denegado por falta de permisos administrativos | K22: Detener operación

Sheet E-Cliente
A1: << Ir al modelo de dominio | E1: << Ir al listado de objetos de dominio | I1: << Ir a la caracterización del objeto de dominio
A2: Objeto de Dominio: | B2: =ListadoObjetosDominio!B3 -> Cliente
A3: Descripción: | B3: =ListadoObjetosDominio!C3 -> Objeto de dominio que representa a cada uno de los usuarios registrados que realizan compras en la plataforma de Imexcol.
A4: Actor | B4: Action/Command | D4: Entity/Aggregate/Object domain | E4: Read Model | G4: Business Rule/Policy | I4: External System | J4: Domain Event | K4: Hotspot/questions/Risk
A5: Actor | B5: Acción | C5: Descripción | D5: Objeto de dominio | E5: Información externa | G5: Políticas | I5: Sistema Externo | J5: Evento | K5: Aspectos por solucionar
E6: Información | F6: Descripción | G6: Número | H6: Descripción
A7: =ListadoObjetosDominio!B3 -> Cliente | B7: Registrar información del cliente | C7: Crear una nueva cuenta de usuario en la plataforma de comercio electrónico de Imexcol para poder realizar compras. | D7: =ListadoObjetosDominio!B3 -> Cliente | E7: tipoDocumento, numeroDocumento, nombre, correo, telefono | F7: Datos mínimos obligatorios requeridos por el sistema para identificar al usuario, facturar y contactarlo. | G7: CLI-POL-01 | H7: Asegurar que los datos requeridos sean válidos a nivel de tipo de dato, formato, rango, longitud y obligatoriedad. | I7: Base de datos | J7: Cliente registrado exitosamente | K7: Riesgo de que el usuario ingrese correos electrónicos temporales o falsos que reboten las facturas.
G8: CLI-POL-02 | H8: El correo electrónico ingresado no debe existir previamente en el sistema (Combinación única 1).
G9: CLI-POL-03 | H9: La combinación de tipo de documento y número de documento no debe existir previamente en el sistema (Combinación única 2).
A10: =_xlfn.CONCAT(ListadoObjetosDominio!B3,"/ ",ListadoObjetosDominio!B4,) -> Cliente/ Administrador | B10: Modificar datos del cliente | C10: Actualizar la información personal de contacto (teléfono o nombre) del usuario registrado en el sistema. | D10: =ListadoObjetosDominio!B3 -> Cliente | E10: idCliente, nombre, telefono | F10: Información editable del perfil del usuario para mantener el contacto actualizado en futuros despachos. | G10: CLI-POL-04 | H10: El identificador del cliente (idCliente) proporcionado debe existir obligatoriamente en el sistema. | I10: Base de datos | J10: Datos de cliente modificados | K10: Un administrador podría cambiar por error el teléfono de un cliente justo antes de un despacho logístico.
A11: =ListadoObjetosDominio!B4 -> Administrador | B11: Consultar listado de clientes | C11: Listar en el panel de control todos los usuarios registrados para gestión operativa y soporte. | D11: =ListadoObjetosDominio!B3 -> Cliente | E11: idCliente, tipoDocumento, numeroDocumento, nombre, correo, telefono | F11: Visualización tabular completa de los datos del cliente para que el administrador pueda auditar el registro. | G11: CLI-POL-05 | H11: El administrador que ejecuta la acción debe tener una sesión válida y activa en el sistema. | I11: Base de datos | J11: Listado de clientes consultado | K11: Si la base de datos crece a miles de clientes, la consulta sin paginación podría saturar la memoria del servidor (TimeOut).

Sheet P-Cliente 
A1: << Ir al modelo de dominio | E1: << Ir al listado de objetos de dominio | I1: << Ir a la caracterización del objeto de dominio
A2: Objeto de Dominio: | B2: =ListadoObjetosDominio!B3 -> Cliente
A3: Descripción: | B3: =ListadoObjetosDominio!C3 -> Objeto de dominio que representa a cada uno de los usuarios registrados que realizan compras en la plataforma de Imexcol.
A4: Business Rule/Policy
A5: Políticas
A6: Número | B6: Descripción
A7: CLI-POL-01 | B7: Asegurar que los datos requeridos sean válidos a nivel de tipo de dato, formato, rango, longitud y obligatoriedad.
A8: CLI-POL-02 | B8: El correo electrónico ingresado no debe existir previamente en el sistema (Combinación única 1).
A9: CLI-POL-03 | B9: La combinación de tipo de documento y número de documento no debe existir previamente en el sistema (Combinación única 2).
A10: CLI-POL-04 | B10: El identificador del cliente (idCliente) proporcionado debe existir obligatoriamente en el sistema.
A11: CLI-POL-05 | B11: El administrador que ejecuta la acción debe tener una sesión válida y activa en el sistema.

Sheet M-Administrador
A1: << Ir al modelo de dominio | D1: << Ir al listado de objetos de dominio | G1: << Ir a la caracterización del objeto de dominio
A2: Nombre | B2: =ListadoObjetosDominio!B4 -> Administrador
A3: Descripción | B3: =ListadoObjetosDominio!C4 -> Objeto de dominio que representa al personal interno encargado de gestionar el catálogo, los pedidos y la operación general del sistema.
A4: Identificador único universal (UUID) del administrador. | B4: Nombre de usuario único del administrador para iniciar sesión. | C4: Correo electrónico de contacto del administrador. | D4: Contraseña del administrador almacenada de forma segura. | E4: Indica que no pueden existir dos administradores o más con el mismo nombre de usuario.
A5: id | B5: nombreUsuario | C5: correoElectronico | D5: contrasena | E5: combinacion unica 1
A6: A1B2C3D4-5566-4F77-8899-AABBCCDDEE01 | B6: admin | C6: admin@imexcol.com | D6: ******** | E6: =B6 -> admin
A7: A1B2C3D4-5566-4F77-8899-AABBCCDDEE02 | B7: lmartinez | C7: l.martinez@imexcol.com | D7: ******** | E7: =B7 -> lmartinez
A8: A1B2C3D4-5566-4F77-8899-AABBCCDDEE03 | B8: sgomez | C8: s.gomez@imexcol.com | D8: ******** | E8: =B8 -> sgomez
A9: A1B2C3D4-5566-4F77-8899-AABBCCDDEE04 | B9: alopez | C9: a.lopez@imexcol.com | D9: ******** | E9: =B9 -> alopez
A10: A1B2C3D4-5566-4F77-8899-AABBCCDDEE05 | B10: mcastro | C10: m.castro@imexcol.com | D10: ******** | E10: =B10 -> mcastro
A13: Corresponde a los datos generales del objeto de dominio (nombre, descripción)
A14: Corresponde a las descripciones de los atributos
A15: Coresponde al nombre de los atributos
A16: Corresponde a los datos que son de libre ingreso
A17: Corresponde a los datos que se generarán automáticamente (IdAdmin)
A18: Corresponde a la combinación única 1

Sheet C-Administrador
A1: << Ir al modelo de dominio | D1: << Ir al listado de objetos de dominio | G1: << Ir a la caracterización del objeto de dominio
A2: Nombre | B2: ='M-Administrador'!B2 -> Administrador
A3: Descripción | B3: ='M-Administrador'!B3 -> Objeto de dominio que representa al personal interno encargado de gestionar el catálogo, los pedidos y la operación general del sistema.
A4: Nombre atributo | B4: Descripción atributo | C4: Identificador del objeto de dominio | D4: Tipo de dato | E4: Obligatorio | F4: Longitud minima(si aplica longitud maxima(si aplica) | G4: Longitud maxima(si aplica longitud maxima(si aplica) | H4: Precisión (si aplica) | I4: Redondeo(si aplica) | J4: Rango inicial(si aplica) | K4: Rango final (si aplica) | L4: Formato(Si aplica) | M4: Reglas especiales(si aplica) | N4: Dato calculado | O4: Aplica ajuste del dato(si aplica) | P4: Carácter de ajuste(si aplica) | Q4: Quitar espacios en blanco al inicio(si aplica) | R4: Quitar espacios en blanco al fin(si aplica) | S4: Dato sensible(si aplica) | T4: Valor por defecto(si aplica) | U4: Auto generado
A5: ='M-Administrador'!A5 -> id | B5: ='M-Administrador'!A4 -> Identificador único universal (UUID) del administrador. | C5: Si | D5: Alfanumerico | E5: Si | J5: 1 | K5: 999999 | M5: Identificador secuencial del administrador | N5: No | S5: No | U5: Si
A6: ='M-Administrador'!B5 -> nombreUsuario | B6: ='M-Administrador'!B4 -> Nombre de usuario único del administrador para iniciar sesión. | C6: No | D6: Alfanumerico | E6: Si | F6: 5 | G6: 50 | L6: Minusculas | M6: No debe contener espacios ni caracteres especiales | N6: No | O6: No | Q6: Si | R6: Si | S6: No | U6: No
A7: ='M-Administrador'!C5 -> correoElectronico | B7: ='M-Administrador'!C4 -> Correo electrónico de contacto del administrador. | C7: No | D7: Alfanumerico | E7: Si | F7: 8 | G7: 150 | M7: Debe almacenarse encriptada por seguridad del sistema | N7: No | O7: No | Q7: No | R7: No | S7: Si | U7: No
A9: Nombre combinación unica | B9: Descripción | C9: Atributos involucrados
A10: ='M-Administrador'!E5 -> combinacion unica 1 | B10: ='M-Administrador'!D4 -> Contraseña del administrador almacenada de forma segura. | C10: ='M-Administrador'!B5 -> nombreUsuario
A12: Responsabilidad | B12: Descripción | C12: Entradas | F12: Salida | H12: Políticas (Reglas de Negocio) | J12: Excepción
C13: Parámettro | D13: Tipo de dato | E13: Descripci | F13: Tipo de Dato | G13: Descripción | H13: Política | I13: Descripción | J13: Detalle | K13: ¿Qué hago?
A14: ='E-Administrador'!B7 -> Registrar nuevo administrador | B14: ='E-Administrador'!C7 -> Crear un nuevo usuario con credenciales para que un empleado pueda ingresar al panel de control de Imexcol. | C14: adminNuevo | D14: Administrador | E14: Contiene la información del administrador que se va a registrar. | F14: Logico | G14: Retorna verdadero si el administrador se registró correctamente. | H14: ='E-Administrador'!G7 -> ADM-POL-01 | I14: ='E-Administrador'!H7 -> Asegurar que los datos requeridos sean válidos a nivel de tipo de dato, formato, rango, longitud y obligatoriedad | J14: Generar excepción indicando qué campo no cumple con el formato o es obligatorio. | K14: Detener operación
H15: ='E-Administrador'!G8 -> ADM-POL-02 | I15: ='E-Administrador'!H8 -> El nombre de usuario ingresado no debe existir previamente en el sistema (Combinación única 1). | J15: Generar excepción indicando que el nombre de usuario ya se encuentra en uso por otro empleado. | K15: Detener operación
A17: ='E-Administrador'!B9 -> Modificar contraseña | B17: ='E-Administrador'!C9 -> Actualizar la clave de acceso de un administrador existente por motivos de seguridad o bloqueo. | C17: adminModificado | D17: Administrador | E17: Contiene el identificador y la nueva credencial a actualizar. | F17: Logico | G17: Retorna verdadero si la contraseña se actualizó con éxito en la base de datos. | H17: ='E-Administrador'!G9 -> ADM-POL-03 | I17: ='E-Administrador'!H9 -> El idAdmin proporcionado debe existir obligatoriamente en el sistema. | J17: Generar excepción indicando que el administrador que se intenta modificar no existe. | K17: Detener operación
A18: ='E-Administrador'!B10 -> Eliminar administrador | B18: ='E-Administrador'!C10 -> Revocar el acceso de un empleado al sistema eliminando su registro de la base de datos | C18: idAdmin | D18: alfanumerico | E18: Identificador exacto del administrador al que se le retirarán los privilegios. | F18: Logico | G18: Retorna verdadero si el administrador fue eliminado correctamente. | H18: ='E-Administrador'!G10 -> ADM-POL-04 | I18: ='E-Administrador'!H10 -> El idAdmin a eliminar debe existir previamente en la base de datos. | J18: Generar excepción indicando que el administrador a eliminar no se encuentra registrado. | K18: Detener operación
H19: ='E-Administrador'!G11 -> ADM-POL-05 | I19: ='E-Administrador'!H11 -> El sistema debe impedir la eliminación si el usuario a borrar es el único administrador restante en la base de datos. | J19: Generar excepción indicando que no se puede eliminar al último administrador del sistema. | K19: Detener operación
A20: ='E-Administrador'!B12 -> Iniciar sesión (Autenticar) | B20: ='E-Administrador'!C12 -> Validar las credenciales del empleado para otorgarle acceso seguro al panel de control del e-commerce | C20: credenciales | D20: Administrador | E20: Contiene el usuario y la contraseña que el empleado intenta validar. | F20: Logico | G20: Retorna verdadero si la autenticación fue exitosa. | H20: ='E-Administrador'!G12 -> ADM-POL-06 | I20: ='E-Administrador'!H12 -> El usuario y la contraseña ingresados deben coincidir exactamente con un registro existente en la base de datos. | J20: Generar excepción indicando que el nombre de usuario o la contraseña son incorrectos. | K20: Detener operación
A21: ='E-Administrador'!B13 -> Consultar administradores | B21: ='E-Administrador'!C13 -> Listar todos los empleados que actualmente tienen acceso al panel administrativo del e-commerce. | C21: filtros | D21: Texto | E21: Parámetros opcionales para filtrar la búsqueda de empleados. | F21: Lista<Administrador> | G21: Retorna una colección con los objetos de los administradores encontrados. | H21: ='E-Administrador'!G13 -> ADM-POL-07 | I21: ='E-Administrador'!H13 -> El administrador que ejecuta la consulta debe contar con una sesión activa en el sistema. | J21: Generar excepción indicando acceso denegado por sesión inactiva o falta de permisos. | K21: Detener operación

Sheet E-Administrador
A1: << Ir al modelo de dominio | E1: << Ir al listado de objetos de dominio | I1: << Ir a la caracterización del objeto de dominio
A2: Objeto de Dominio: | B2: =ListadoObjetosDominio!B4 -> Administrador
A3: Descripción: | B3: =ListadoObjetosDominio!C4 -> Objeto de dominio que representa al personal interno encargado de gestionar el catálogo, los pedidos y la operación general del sistema.
A4: Actor | B4: Action/Command | D4: Entity/Aggregate/Object domain | E4: Read Model | G4: Business Rule/Policy | I4: External System | J4: Domain Event | K4: Hotspot/questions/Risk
A5: Actor | B5: Acción | C5: Descripción | D5: Objeto de dominio | E5: Información externa | G5: Políticas | I5: Sistema Externo | J5: Evento | K5: Aspectos por solucionar
E6: Información | F6: Descripción | G6: Número | H6: Descripción
A7: =ListadoObjetosDominio!B4 -> Administrador | B7: Registrar nuevo administrador | C7: Crear un nuevo usuario con credenciales para que un empleado pueda ingresar al panel de control de Imexcol. | D7: =ListadoObjetosDominio!B4 -> Administrador | E7: usuario, password | F7: Credenciales de acceso requeridas para autenticar al nuevo empleado en el sistema. | G7: ADM-POL-01 | H7: Asegurar que los datos requeridos sean válidos a nivel de tipo de dato, formato, rango, longitud y obligatoriedad | I7: Base de datos | J7: Administrador registrado | K7: Riesgo de que la contraseña asignada inicialmente sea muy débil o predecible (ej. 12345678).
G8: ADM-POL-02 | H8: El nombre de usuario ingresado no debe existir previamente en el sistema (Combinación única 1).
A9: =ListadoObjetosDominio!B4 -> Administrador | B9: Modificar contraseña | C9: Actualizar la clave de acceso de un administrador existente por motivos de seguridad o bloqueo. | D9: =ListadoObjetosDominio!B4 -> Administrador | E9: idAdmin, password | F9: Identificador del empleado y la nueva credencial de seguridad a actualizar. | G9: ADM-POL-03 | H9: El idAdmin proporcionado debe existir obligatoriamente en el sistema. | I9: Base de datos | J9: Contraseña de administrador modificada | K9: Contraseña de administrador modificada Si un administrador cambia la contraseña de otro sin autorización, podría generar un bloqueo operativo en la tienda.
A10: =ListadoObjetosDominio!B4 -> Administrador | B10: Eliminar administrador | C10: Revocar el acceso de un empleado al sistema eliminando su registro de la base de datos | D10: =ListadoObjetosDominio!B4 -> Administrador | E10: idAdmin | F10: Identificador exacto del empleado al que se le retirarán los privilegios de acceso. | G10: ADM-POL-04 | H10: El idAdmin a eliminar debe existir previamente en la base de datos. | I10: Base de datos | J10: Administrador eliminado | K10: Riesgo de que el último o único administrador del sistema sea eliminado, bloqueando el acceso total a la plataforma.
G11: ADM-POL-05 | H11: El sistema debe impedir la eliminación si el usuario a borrar es el único administrador restante en la base de datos.
A12: =ListadoObjetosDominio!B4 -> Administrador | B12: Iniciar sesión (Autenticar) | C12: Validar las credenciales del empleado para otorgarle acceso seguro al panel de control del e-commerce | D12: =ListadoObjetosDominio!B4 -> Administrador | E12: usuario, password | F12: Formulario de login donde el empleado ingresa sus credenciales de acceso. | G12: ADM-POL-06 | H12: El usuario y la contraseña ingresados deben coincidir exactamente con un registro existente en la base de datos. | I12: Sistema Auth | J12: Sesión de administrador iniciada | K12: Riesgo de ataques de fuerza bruta (intentar adivinar la clave repetidamente). ¿Se debería bloquear el usuario tras 3 intentos fallidos?
A13: =ListadoObjetosDominio!B4 -> Administrador | B13: Consultar administradores | C13: Listar todos los empleados que actualmente tienen acceso al panel administrativo del e-commerce. | D13: =ListadoObjetosDominio!B4 -> Administrador | E13: idAdmin, usuario | F13: Vista de auditoría para revisar quiénes tienen credenciales activas en el sistema. | G13: ADM-POL-07 | H13: El administrador que ejecuta la consulta debe contar con una sesión activa en el sistema. | I13: Base de datos | J13: Listado de administradores consultado | K13: Exposición de nombres de usuario a empleados que no deberían tener permisos de auditoría de personal.

Sheet P-Administrador
A1: << Ir al modelo de dominio | E1: << Ir al listado de objetos de dominio | I1: << Ir a la caracterización del objeto de dominio
A2: Objeto de Dominio: | B2: =ListadoObjetosDominio!B4 -> Administrador
A3: Descripción: | B3: =ListadoObjetosDominio!C4 -> Objeto de dominio que representa al personal interno encargado de gestionar el catálogo, los pedidos y la operación general del sistema.
A4: Business Rule/Policy
A5: Políticas
A6: Número | B6: Descripción
A7: ADM-POL-01 | B7: Asegurar que los datos requeridos sean válidos a nivel de tipo de dato, formato, rango, longitud y obligatoriedad
A8: ADM-POL-02 | B8: El nombre de usuario ingresado no debe existir previamente en el sistema (Combinación única 1).
A9: ADM-POL-03 | B9: El idAdmin proporcionado debe existir obligatoriamente en el sistema.
A10: ADM-POL-04 | B10: El idAdmin a eliminar debe existir previamente en la base de datos.
A11: ADM-POL-05 | B11: El sistema debe impedir la eliminación si el usuario a borrar es el único administrador restante en la base de datos.
A12: ADM-POL-06 | B12: El usuario y la contraseña ingresados deben coincidir exactamente con un registro existente en la base de datos.
A13: ADM-POL-07 | B13: El administrador que ejecuta la consulta debe contar con una sesión activa en el sistema.

Sheet M-Dirección
A1: << Ir al modelo de dominio | I1: << Ir al listado de objetos de dominio | L1: << Ir a la caracterización del objeto de dominio
A2: Nombre: | B2: =ListadoObjetosDominio!B5 -> Dirección
A3: Descripción: | B3: =ListadoObjetosDominio!C5 -> Objeto de dominio que representa la ubicación física y estructurada que registra un cliente para la entrega de sus productos o propósitos de facturación.
A4: Identificador único universal (UUID) de la dirección. | B4: Referencia al cliente al que pertenece esta dirección. | C4: Nomenclatura exacta de la dirección (calle, carrera, número). | D4: Ciudad o municipio donde se ubica la dirección. | E4: Departamento o estado donde se ubica la dirección. | F4: País donde se ubica la dirección. | G4: Código postal de la dirección (opcional). | H4: Indica que un cliente no puede registrar dos veces exactamente la misma dirección física
A5: id | B5: cliente | C5: calle | D5: ciudad | E5: departamento | F5: pais | G5: codigoPostal | H5: Combinación Unica 1
A6: D1234567-8901-4234-5678-90123456D001 | B6: 3F2504E0-4F89-11D3-9A0C-0305E82C3301 | C6: Calle 10 # 43-20 | D6: Medellín | E6: Antioquia | F6: Colombia | G6: 050021 | H6: =C6 -> Calle 10 # 43-20
A7: D1234567-8901-4234-5678-90123456D002 | B7: 3F2504E0-4F89-11D3-9A0C-0305E82C3302 | C7: Carrera 48 # 32-15 | D7: Envigado | E7: Antioquia | F7: Colombia | G7: 055422 | H7: =C7 -> Carrera 48 # 32-15
A8: D1234567-8901-4234-5678-90123456D003 | B8: 3F2504E0-4F89-11D3-9A0C-0305E82C3303 | C8: Carrera 15 # 85-30 | D8: Bogotá | E8: Cundinamarca | F8: Colombia | G8: 110221 | H8: =C8 -> Carrera 15 # 85-30
A9: D1234567-8901-4234-5678-90123456D004 | B9: 3F2504E0-4F89-11D3-9A0C-0305E82C3304 | C9: Avenida 6N # 24-10 | D9: Cali | E9: Valle del Cauca | F9: Colombia | G9: 760045 | H9: =C9 -> Avenida 6N # 24-10
A10: D1234567-8901-4234-5678-90123456D005 | B10: 3F2504E0-4F89-11D3-9A0C-0305E82C3305 | C10: Calle 84 # 51B-20 | D10: Barranquilla | E10: Atlántico | F10: Colombia | G10: 080020 | H10: =C10 -> Calle 84 # 51B-20
A13: Corresponde a los datos generales del objeto de dominio (nombre, descripción)
A14: Corresponde a las descripciones de los atributos
A15: Coresponde al nombre de los atributos
A16: Corresponde a los datos que son de libre ingreso
A17: Corresponde a los datos que se generarán automáticamente (IdDireccion, idCliente)
A18: Corresponde a la combinación única 1

Sheet C-Direccion
A1: << Ir al modelo de dominio | D1: << Ir al listado de objetos de dominio | G1: << Ir a la caracterización del objeto de dominio
A3: Nombre | B3: ='M-Dirección'!B2 -> Dirección
A4: Descripción | B4: ='M-Dirección'!B3 -> Objeto de dominio que representa la ubicación física y estructurada que registra un cliente para la entrega de sus productos o propósitos de facturación.
A5: Nombre atributo | B5: Descripción atributo | C5: Identificador del objeto de dominio | D5: Tipo de dato | E5: Obligatorio | F5: Longitud minima(si aplica longitud maxima(si aplica) | G5: Longitud maxima(si aplica longitud maxima(si aplica) | H5: Precisión (si aplica) | I5: Redondeo(si aplica) | J5: Rango inicial(si aplica) | K5: Rango final (si aplica) | L5: Formato(Si aplica) | M5: Reglas especiales(si aplica) | N5: Dato calculado | O5: Aplica ajuste del dato(si aplica) | P5: Carácter de ajuste(si aplica) | Q5: Quitar espacios en blanco al inicio(si aplica) | R5: Quitar espacios en blanco al fin(si aplica) | S5: Dato sensible(si aplica) | T5: Valor por defecto(si aplica) | U5: Auto generado | V5: Registrar una nueva categoría | W5: Consultar la información de las categorías | X5: Permite listar las categorías en la página web para filtrar y buscar productos. | Y5: Actualizar el nombre de una categoría | Z5: Eliminar una categoría
A6: ='M-Dirección'!A5 -> id | B6: ='M-Dirección'!A4 -> Identificador único universal (UUID) de la dirección. | C6: Si | D6: Alfanumerico | E6: Si | F6: 1 | L6: Mayusculas | N6: No | O6: No | Q6: Si | R6: Si | S6: No | U6: Si | V6: No requerido | W6: No Requerido | X6: No requerido | Y6: No requerido | Z6: No requerido
A7: ='M-Dirección'!B5 -> cliente | B7: ='M-Dirección'!B4 -> Referencia al cliente al que pertenece esta dirección. | C7: No | D7: <Cliente> | E7: Si | M7: Debe existir un cliente previamente registrado | N7: No | S7: No | U7: No | V7: Requerido | W7: Requerido | X7: Requerido | Y7: Requerido | Z7: Requerido
A8: ='M-Dirección'!C5 -> calle | B8: ='M-Dirección'!C4 -> Nomenclatura exacta de la dirección (calle, carrera, número). | C8: No | D8: Texto | E8: Si | F8: 4 | G8: 200 | L8: Capitalizado | M8: Solo nombres válidos de divisiones territoriales | N8: No | O8: No | Q8: Si | R8: Si | S8: No | U8: No
A9: ='M-Dirección'!D5 -> ciudad | B9: ='M-Dirección'!D4 -> Ciudad o municipio donde se ubica la dirección. | C9: No | D9: Texto | E9: Si | F9: 3 | G9: 100 | L9: Capitalizado | M9: Solo nombres válidos de municipios | N9: No | O9: No | Q9: Si | R9: Si | S9: No | U9: No
A10: ='M-Dirección'!E5 -> departamento | B10: ='M-Dirección'!E4 -> Departamento o estado donde se ubica la dirección. | C10: No | D10: Texto | E10: Si | F10: 5 | G10: 100 | M10: Formato de nomenclatura urbana estándar | N10: No | O10: No | Q10: Si | R10: Si | S10: No | U10: No
A11: ='M-Dirección'!F5 -> pais | B11: ='M-Dirección'!F4 -> País donde se ubica la dirección. | C11: No | D11: Texto | E11: Si | F11: 0 | G11: 100 | M11: Datos complementarios para ubicación | N11: No | O11: No | Q11: Si | R11: Si | S11: No | U11: No
A13: Nombre combinación unica | B13: Descripción | C13: Atributos involucrados
A14: ='M-Dirección'!G5 -> codigoPostal | B14: ='M-Dirección'!G4 -> Código postal de la dirección (opcional). | C14: {='M-Dirección'!E5:F5} -> departamento | D14: pais
A16: Responsabilidad | B16: Descripción | C16: Entradas | F16: Salida | H16: Políticas (Reglas de Negocio) | J16: Excepción
C17: Parámettro | D17: Tipo de dato | E17: Descripci | F17: Tipo de Dato | G17: Descripción | H17: Política | I17: Descripción | J17: Detalle | K17: ¿Qué hago?
A18: ='E-Direccion'!B7 -> Agregar dirección | B18: ='E-Direccion'!C7 -> Registrar una nueva ubicación física para la entrega de pedidos o facturación. | C18: direccionNueva | D18: Dirección | E18: Contiene la información de la nueva dirección a registrar. | F18: Logico | G18: Retorna verdadero si la dirección se agregó correctamente al perfil del cliente. | H18: ='E-Direccion'!G7 -> DIR-POL-01 | I18: ='E-Direccion'!H7 -> Asegurar que los datos requeridos sean válidos a nivel de tipo de dato, formato, longitud y obligatoriedad. | J18: Generar excepción indicando qué campo de la dirección no cumple con el formato o es obligatorio. | K18: Detener operación
H19: ='E-Direccion'!G8 -> DIR-POL-02 | I19: ='E-Direccion'!H8 -> El idCliente asociado debe existir previamente | J19: Generar excepción indicando que el cliente asociado a la dirección no existe en la base de datos. | K19: Detener operación
A21: ='E-Direccion'!B10 -> Modificar dirección | B21: ='E-Direccion'!C10 -> Actualizar los detalles de una dirección existente (ej. corrección de calle o apartamento). | C21: direccionModificada | D21: Dirección | E21: Contiene la nueva información de la ubicación a actualizar. | F21: Logico | G21: Retorna verdadero si la dirección se modificó exitosamente. | H21: ='E-Direccion'!G10 -> DIR-POL-04 | I21: ='E-Direccion'!H10 -> El idDireccion a modificar debe existir previamente en el sistema | J21: Generar excepción indicando que la dirección no existe o el usuario no tiene permisos para editarla. | K21: Detener operación
A22: ='E-Direccion'!B11 -> Eliminar dirección | B22: ='E-Direccion'!C11 -> Quitar una dirección de la libreta de direcciones del usuario para que no aparezca en futuras compras. | C22: idDireccion | D22: alfanumerico | E22: Identificador exacto de la ubicación que el usuario desea borrar. | F22: Logico | G22: Retorna verdadero si la dirección fue eliminada o inactivada correctamente. | H22: ='E-Direccion'!G11 -> DIR-POL-05 | I22: ='E-Direccion'!H11 -> El idDireccion a eliminar debe existir previamente en el sistema | J22: Generar excepción indicando que la dirección a borrar no existe o no es de su propiedad. | K22: Detener operación
H23: ='E-Direccion'!#REF! -> #REF! | I23: ='E-Direccion'!H12 -> 0 | J23: Generar excepción indicando que la dirección está bloqueada temporalmente porque tiene un envío en curso. | K23: Detener operación
A24: ='E-Direccion'!B13 -> 0 | B24: ='E-Direccion'!C11 -> Quitar una dirección de la libreta de direcciones del usuario para que no aparezca en futuras compras. | C24: idCliente | D24: alfanumerico | E24: Identificador del cliente del cual se quieren obtener las ubicaciones guardadas. | F24: Lista<Dirección> | G24: Retorna una colección con los objetos de las direcciones encontradas. | H24: ='E-Direccion'!G13 -> 0 | I24: ='E-Direccion'!H13 -> 0 | J24: Generar excepción indicando acceso denegado por intentar consultar direcciones de otro usuario sin rol de administrador. | K24: Detener operación

Sheet E-Direccion
A1: << Ir al modelo de dominio | D1: << Ir al listado de objetos de dominio | H1: << Ir a la caracterización del objeto de dominio | L1: Ir al muestreo de datos del objeto de dominio >>
A2: Objeto de Dominio: | B2: =ListadoObjetosDominio!B5 -> Dirección
A3: Descripción: | B3: =ListadoObjetosDominio!C5 -> Objeto de dominio que representa la ubicación física y estructurada que registra un cliente para la entrega de sus productos o propósitos de facturación.
A4: Actor | B4: Action/Command | D4: Entity/Aggregate/Object domain | E4: Read Model | G4: Business Rule/Policy | I4: External System | J4: Domain Event | K4: Hotspot/questions/Risk
A5: Actor | B5: Acción | C5: Descripción | D5: Objeto de dominio | E5: Información externa | G5: Políticas | I5: Sistema Externo | J5: Evento | K5: Aspectos por solucionar
E6: Información | F6: Descripción | G6: Número | H6: Descripción
A7: =ListadoObjetosDominio!B3 -> Cliente | B7: Agregar dirección | C7: Registrar una nueva ubicación física para la entrega de pedidos o facturación. | D7: =ListadoObjetosDominio!B5 -> Dirección | E7: idCliente, departamento, ciudad, calle, detalleAdicional | F7: Formulario de creación con los datos de ubicación vinculados al perfil del usuario. | G7: DIR-POL-01 | H7: Asegurar que los datos requeridos sean válidos a nivel de tipo de dato, formato, longitud y obligatoriedad. | I7: Base de datos | J7: Dirección agregada | K7: Riesgo de que el cliente ingrese una nomenclatura errónea que la transportadora no pueda encontrar
G8: DIR-POL-02 | H8: El idCliente asociado debe existir previamente
G9: DIR-POL-03 | H9: Un cliente no puede registrar dos direcciones con la misma combinación de calle, ciudad, departamento
A10: =ListadoObjetosDominio!B3 -> Cliente | B10: Modificar dirección | C10: Actualizar los detalles de una dirección existente (ej. corrección de calle o apartamento). | D10: =ListadoObjetosDominio!B5 -> Dirección | E10: idDireccion, departamento, ciudad, calle, detalleAdicional | F10: Formulario pre-poblado con la información actual de la dirección a editar. | G10: DIR-POL-04 | H10: El idDireccion a modificar debe existir previamente en el sistema | I10: Base de datos | J10: Dirección modificada | K10: ¿Qué pasa si el cliente modifica una dirección mientras un pedido en curso ya va en camino hacia la dirección anterior?
A11: Cliente | B11: Eliminar dirección | C11: Quitar una dirección de la libreta de direcciones del usuario para que no aparezca en futuras compras. | D11: =ListadoObjetosDominio!B5 -> Dirección | E11: idDireccion | F11: Identificador de la ubicación que el usuario desea borrar de su perfil. | G11: DIR-POL-05 | H11: El idDireccion a eliminar debe existir previamente en el sistema | I11: Base de datos | J11: Direccion eliminada | K11: Si se elimina físicamente la dirección, se puede dañar el historial de facturas pasadas.

Sheet P-Dirección
A1: << Ir al modelo de dominio | D1: << Ir al listado de objetos de dominio | H1: << Ir a la caracterización del objeto de dominio | L1: Ir al muestreo de datos del objeto de dominio >>
A2: Objeto de Dominio: | B2: =ListadoObjetosDominio!B5 -> Dirección
A3: Descripción: | B3: =ListadoObjetosDominio!C5 -> Objeto de dominio que representa la ubicación física y estructurada que registra un cliente para la entrega de sus productos o propósitos de facturación.
A4: Business Rule/Policy
A5: Políticas
A6: Número | B6: Descripción
A7: DIR-POL-01 | B7: Asegurar que los datos requeridos sean válidos a nivel de tipo de dato, formato, longitud y obligatoriedad.
A8: DIR-POL-02 | B8: El idCliente asociado debe existir previamente
A9: DIR-POL-03 | B9: Un cliente no puede registrar dos direcciones con la misma combinación de calle, ciudad, departamento
A10: DIR-POL-04 | B10: El idDireccion a modificar debe existir previamente en el sistema
A11: DIR-POL-05 | B11: El idDireccion a eliminar debe existir previamente en el sistema

Sheet M-Categoria
A1: << Ir al modelo de dominio | E1: << Ir al listado de objetos de dominio | H1: << Ir a la caracterización del objeto de dominio
A2: Nombre: | B2: =ListadoObjetosDominio!B6 -> Categoría
A3: Descripción: | B3: =ListadoObjetosDominio!C6 -> Objeto de dominio que representa a cada una de las agrupaciones taxonómicas en las que se organizan los productos del catálogo de Imexcol.
A4: Identificador único universal (UUID) de la categoría. | B4: Nombre comercial de la categoría de productos. | C4: Descripción breve de la categoría (opcional). | D4: Indica que no pueden existir dos categorías o más con el mismo nombre
A5: id | B5: nombre | C5: descripcion | D5: combinación unica 1
A6: CA111111-1111-4111-8111-111111111101 | B6: Hogar | C6: Productos decorativos y utilitarios para el hogar. | D6: =B6 -> Hogar
A7: CA111111-1111-4111-8111-111111111102 | B7: Moda | C7: Prendas de vestir y accesorios de moda. | D7: =B7 -> Moda
A8: CA111111-1111-4111-8111-111111111103 | B8: Accesorios | C8: Accesorios personales y complementos. | D8: =B8 -> Accesorios
A9: CA111111-1111-4111-8111-111111111104 | B9: Tecnología | C9: Dispositivos y accesorios tecnológicos. | D9: =B9 -> Tecnología
A10: CA111111-1111-4111-8111-111111111105 | B10: Cocina | C10: Utensilios y menaje de cocina. | D10: =B10 -> Cocina
A12: Corresponde a los datos generales del objeto de dominio (nombre, descripción)
A13: Corresponde a las descripciones de los atributos
A14: Coresponde al nombre de los atributos
A15: Corresponde a los datos que son de libre ingreso (referencia, nombre, descripcion, precio y estado)
A16: Corresponde a los datos que se generarán automáticamente (idCategoria)
A17: Corresponde a la combinación única 1

Sheet C-Categoria
A1: << Ir al modelo de dominio | D1: << Ir al listado de objetos de dominio | G1: << Ir a la caracterización del objeto de dominio
A3: Nombre | B3: ='M-Categoria'!B2 -> Categoría
A4: Descripción | B4: ='M-Categoria'!B3 -> Objeto de dominio que representa a cada una de las agrupaciones taxonómicas en las que se organizan los productos del catálogo de Imexcol.
A5: Nombre atributo | B5: Descripción atributo | C5: Identificador del objeto de dominio | D5: Tipo de dato | E5: Obligatorio | F5: Longitud minima(si aplica longitud maxima(si aplica) | G5: Longitud maxima(si aplica longitud maxima(si aplica) | H5: Precisión (si aplica) | I5: Redondeo(si aplica) | J5: Rango inicial(si aplica) | K5: Rango final (si aplica) | L5: Formato(Si aplica) | M5: Reglas especiales(si aplica) | N5: Dato calculado | O5: Aplica ajuste del dato(si aplica) | P5: Carácter de ajuste(si aplica) | Q5: Quitar espacios en blanco al inicio(si aplica) | R5: Quitar espacios en blanco al fin(si aplica) | S5: Dato sensible(si aplica) | T5: Valor por defecto(si aplica) | U5: Auto generado | V5: Registrar una nueva categoría | W5: Consultar la información de las categorías | X5: Permite listar las categorías en la página web para filtrar y buscar productos. | Y5: Actualizar el nombre de una categoría | Z5: Eliminar una categoría
A6: ='M-Categoria'!A5 -> id | B6: ='M-Categoria'!A4 -> Identificador único universal (UUID) de la categoría. | C6: Si | D6: Alfanumerico | E6: Si | F6: 3 | L6: Mayusculas | N6: No | O6: No | Q6: Si | R6: Si | S6: No | U6: Si | V6: No requerido | W6: No Requerido | X6: No requerido | Y6: No requerido | Z6: No requerido
A7: ='M-Categoria'!B5 -> nombre | B7: ='M-Categoria'!B4 -> Nombre comercial de la categoría de productos. | C7: No | D7: Alfanumerico | E7: Si | F7: 3 | G7: 100 | L7: Capitalizado | M7: Nombre comercial de la categoría | N7: No | O7: No | Q7: Si | R7: Si | S7: No | T7: Activo | U7: No | V7: Requerido | W7: Requerido | X7: Requerido | Y7: Requerido | Z7: Requerido
A8: ='M-Categoria'!C5 -> descripcion | B8: ='M-Categoria'!C4 -> Descripción breve de la categoría (opcional). | C8: No | D8: Texto | E8: No | G8: 255 | L8: N/A | M8: Solo permite valores 'Activo' o 'Inactivo' | N8: No | O8: No | Q8: Si | R8: Si | S8: No | T8: Activo | U8: No
A10: Nombre combinación unica | B10: Descripción | C10: Atributos involucrados
A11: ='M-Categoria'!D5 -> combinación unica 1 | B11: ='M-Categoria'!D4 -> Indica que no pueden existir dos categorías o más con el mismo nombre | C11: ='M-Categoria'!B5 -> nombre
A13: Responsabilidad | B13: Descripción | C13: Entradas | F13: Salida | H13: Políticas (Reglas de Negocio) | J13: Excepción
C14: Parámettro | D14: Tipo de dato | E14: Descripci | F14: Tipo de Dato | G14: Descripción | H14: Política | I14: Descripción | J14: Detalle | K14: ¿Qué hago?
A15: ='E-Categoria'!B7 -> Crear Categoria | B15: ='E-Categoria'!C7 -> Permite ingresar al sistema una nueva categoría para agrupar los productos del catálogo. | C15: categoriaNueva | D15: Categoría | E15: Contiene la información de la nueva categoría a registrar. | F15: Logico | G15: Retorna verdadero si la categoría se agregó correctamente al sistema. | H15: ='E-Categoria'!G7 -> CAT-POL-01 | I15: ='E-Categoria'!H7 -> Asegurar que los datos requeridos sean válidos a nivel de tipo de dato, formato, longitud y obligatoriedad. | J15: Generar excepción indicando qué campo no cumple con el formato o es obligatorio. | K15: Detener operación
H16: ='E-Categoria'!G8 -> CAT-POL-02 | I16: ='E-Categoria'!H8 -> El nombre de la categoría debe ser único en el sistema para evitar duplicidad. | J16: Generar excepción indicando que ya existe otra categoría registrada con ese mismo nombre. | K16: Detener operación
A17: ='E-Categoria'!B9 -> Modificar categoría | B17: ='E-Categoria'!C9 -> Actualizar los detalles de una categoría existente (ej. corregir ortografía o ampliar la descripción). | C17: ategoriaModificada | D17: Categoría | E17: Contiene la nueva información de la categoría a actualizar. | F17: Logico | G17: Retorna verdadero si la categoría se modificó exitosamente. | H17: ='E-Categoria'!G9 -> CAT-POL-03 | I17: ='E-Categoria'!H9 -> El idCategoria a modificar debe existir previamente en el sistema. | J17: Generar excepción indicando que la categoría que se intenta modificar no existe en la base de datos. | K17: Detener operación
A18: ='E-Categoria'!B10 -> Eliminar categoría | B18: ='E-Categoria'!C10 -> Quitar una categoría del catálogo para que ya no esté disponible en la tienda. | C18: idCategoria | D18: alfanumerico | E18: Identificador exacto de la categoría que se desea borrar. | F18: Logico | G18: Retorna verdadero si la categoría fue eliminada correctamente. | H18: ='E-Categoria'!G10 -> CAT-POL-04 | I18: ='E-Categoria'!H10 -> El idCategoria a eliminar debe existir previamente en el sistema. | J18: Generar excepción indicando que la categoría a borrar no se encuentra registrada. | K18: Detener operación
H19: ='E-Categoria'!G11 -> CAT-POL-05 | I19: ='E-Categoria'!H11 -> El sistema debe impedir la eliminación de la categoría si esta tiene uno o más productos asociados actualmente. | J19: Generar excepción indicando que la categoría está en uso por productos existentes y no puede ser eliminada. | K19: Detener operación
A20: ='E-Categoria'!B12 -> Consultar categorías | B20: ='E-Categoria'!C12 -> Listar las categorías disponibles para desplegarlas en el menú de navegación o panel administrativo. | C20: filtros | D20: Texto | E20: Parámetros opcionales para filtrar la búsqueda de categorías. | F20: Lista<Categoría> | G20: Retorna una colección con los objetos de las categorías encontradas. | H20: ='E-Categoria'!G12 -> CAT-POL-06 | I20: ='E-Categoria'!H12 -> Asegurar que los datos requeridos sean válidos a nivel de tipo de dato, formato, longitud y obligatoriedad. | J20: Generar excepción indicando que los parámetros de búsqueda tienen un formato incorrecto. | K20: Detener operación

Sheet E-Categoria
A1: << Ir al modelo de dominio | D1: << Ir al listado de objetos de dominio | H1: << Ir a la caracterización del objeto de dominio | L1: Ir al muestreo de datos del objeto de dominio >>
A2: Objeto de Dominio: | B2: =ListadoObjetosDominio!B6 -> Categoría
A3: Descripción: | B3: =ListadoObjetosDominio!C6 -> Objeto de dominio que representa a cada una de las agrupaciones taxonómicas en las que se organizan los productos del catálogo de Imexcol.
A4: Actor | B4: Action/Command | D4: Entity/Aggregate/Object domain | E4: Read Model | G4: Business Rule/Policy | I4: External System | J4: Domain Event | K4: Hotspot/questions/Risk
A5: Actor | B5: Acción | C5: Descripción | D5: Objeto de dominio | E5: Información externa | G5: Políticas | I5: Sistema Externo | J5: Evento | K5: Aspectos por solucionar
E6: Información | F6: Descripción | G6: Número | H6: Descripción
A7: Administrador | B7: Crear Categoria | C7: Permite ingresar al sistema una nueva categoría para agrupar los productos del catálogo. | D7: =ListadoObjetosDominio!B6 -> Categoría | E7: nombre, descripcion | F7: Formulario para ingresar el nombre y detalles de la nueva familia de productos. | G7: CAT-POL-01 | H7: Asegurar que los datos requeridos sean válidos a nivel de tipo de dato, formato, longitud y obligatoriedad. | I7: Base de datos | J7: Categoría creada | K7: Riesgo de crear categorías duplicadas o con nombres muy similares que confundan al cliente.
G8: CAT-POL-02 | H8: El nombre de la categoría debe ser único en el sistema para evitar duplicidad.
A9: Administrador | B9: Modificar categoría | C9: Actualizar los detalles de una categoría existente (ej. corregir ortografía o ampliar la descripción). | D9: =ListadoObjetosDominio!B6 -> Categoría | E9: idCategoria, nombre, descripcion | F9: Formulario pre-poblado con la información actual de la categoría a editar. | G9: CAT-POL-03 | H9: El idCategoria a modificar debe existir previamente en el sistema. | I9: Base de datos | J9: Categoría modificada | K9: Cambiar el nombre drásticamente podría desorientar a los clientes que buscan productos específicos.
A10: Administrador | B10: Eliminar categoría | C10: Quitar una categoría del catálogo para que ya no esté disponible en la tienda. | D10: =ListadoObjetosDominio!B6 -> Categoría | E10: idCategoria | F10: Identificador de la agrupación que el administrador desea retirar. | G10: CAT-POL-04 | H10: El idCategoria a eliminar debe existir previamente en el sistema. | I10: Base de datos | J10: Categoría eliminada | K10: Riesgo crítico: dejar productos "huérfanos". ¿Qué pasa con los productos si se borra su categoría?
G11: CAT-POL-05 | H11: El sistema debe impedir la eliminación de la categoría si esta tiene uno o más productos asociados actualmente.
A12: Cliente / Administrador | B12: Consultar categorías | C12: Listar las categorías disponibles para desplegarlas en el menú de navegación o panel administrativo. | D12: Categoría | E12: idCategoria, nombre, descripcion | F12: Menú visual en la tienda web o grilla en el panel de control del administrador. | G12: CAT-POL-06 | H12: Asegurar que los datos requeridos sean válidos a nivel de tipo de dato, formato, longitud y obligatoriedad. | I12: Base de datos | J12: Categorías consultadas | K12: Si hay demasiadas categorías cargadas al mismo tiempo, el menú principal podría volverse inmanejable.

Sheet P-Categoría
A1: << Ir al modelo de dominio | D1: << Ir al listado de objetos de dominio | H1: << Ir a la caracterización del objeto de dominio | L1: Ir al muestreo de datos del objeto de dominio >>
A2: Objeto de Dominio: | B2: =ListadoObjetosDominio!B6 -> Categoría
A3: Descripción: | B3: =ListadoObjetosDominio!C6 -> Objeto de dominio que representa a cada una de las agrupaciones taxonómicas en las que se organizan los productos del catálogo de Imexcol.
A4: Business Rule/Policy
A5: Políticas
A6: Número | B6: Descripción
A7: CAT-POL-01 | B7: Asegurar que los datos requeridos sean válidos a nivel de tipo de dato, formato, longitud y obligatoriedad.
A8: CAT-POL-02 | B8: El nombre de la categoría debe ser único en el sistema para evitar duplicidad.
A9: CAT-POL-03 | B9: El idCategoria a modificar debe existir previamente en el sistema.
A10: CAT-POL-04 | B10: El idCategoria a eliminar debe existir previamente en el sistema.
A11: CAT-POL-05 | B11: El sistema debe impedir la eliminación de la categoría si esta tiene uno o más productos asociados actualmente.
A12: CAT-POL-06 | B12: Asegurar que los datos requeridos sean válidos a nivel de tipo de dato, formato, longitud y obligatoriedad.

Sheet M-Producto
A1: <<< Ir al modelo de dominio | D1: << Ir al listado de objetos de dominio | G1: << Ir a la caracterización del objeto de dominio
A2: Nombre | B2: =ListadoObjetosDominio!B7 -> Producto
A3: Descripción | B3: =ListadoObjetosDominio!C7 -> Objeto de dominio que representa a cada uno de los artículos de importación (bolsos, juguetes, etc.) que están disponibles para la venta en la tienda.
A4: Identificador único universal (UUID) del producto. | B4: Referencia a la categoría a la que pertenece el producto. | C4: Nombre comercial del producto. | D4: Descripción detallada de las características del producto. | E4: Precio del producto en pesos colombianos (COP). | F4: Cantidad de unidades disponibles en inventario. | G4: Ruta relativa a la imagen representativa del producto (opcional). | H4: Indica que no pueden existir dos productos o más con la misma referencia en el sistema.
A5: id | B5: categoria | C5: nombre | D5: descripcion | E5: precio | F5: stock | G5: imagenUrl | H5: CombinacionUnica1
A6: 4F8A0001-2222-4333-8444-555566667701 | B6: CA111111-1111-4111-8111-111111111101 | C6: Lámpara decorativa NP5115 | D6: Lámpara de mesa decorativa con base metálica y pantalla en tela. | E6: 89900 | F6: 25 | G6: img/Lampara_NP5115.png | H6: =A6 -> 4F8A0001-2222-4333-8444-555566667701
A7: 4F8A0001-2222-4333-8444-555566667702 | B7: CA111111-1111-4111-8111-111111111103 | C7: Sombrilla antiviento NP4292 | D7: Sombrilla plegable antiviento con forro reforzado y mango ergonómico. | E7: 145000 | F7: 40 | G7: img/Sombrilla_antiviento_NP4292.png | H7: =A7 -> 4F8A0001-2222-4333-8444-555566667702
A8: 4F8A0001-2222-4333-8444-555566667703 | B8: CA111111-1111-4111-8111-111111111102 | C8: Gorra para hombre NP5275 | D8: Gorra deportiva para hombre con visera curva y ajuste trasero. | E8: 35500 | F8: 60 | G8: img/Gorra_hombre_NP5275.png | H8: =A8 -> 4F8A0001-2222-4333-8444-555566667703
A9: 4F8A0001-2222-4333-8444-555566667704 | B9: CA111111-1111-4111-8111-111111111105 | C9: Set de cucharas inoxidables x 12 | D9: Set de 12 cucharas en acero inoxidable con diseño labrado. | E9: 32000 | F9: 0 | G9: img/Set_Cucharas_NP712.png | H9: =A9 -> 4F8A0001-2222-4333-8444-555566667704
A10: 4F8A0001-2222-4333-8444-555566667705 | B10: CA111111-1111-4111-8111-111111111104 | C10: Audífonos inalámbricos | D10: Audífonos bluetooth con cancelación de ruido y estuche de carga. | E10: 189900 | F10: 15 | G10: img/Audifonos_inalam_NP0314.png | H10: =A10 -> 4F8A0001-2222-4333-8444-555566667705
A13: Corresponde a los datos generales del objeto de dominio (nombre, descripción)
A14: Corresponde a las descripciones de los atributos
A15: Coresponde al nombre de los atributos
A16: Corresponde a los datos que son de libre ingreso (referencia, nombre, descripcion, precio y estado)
A17: Corresponde a referencias a otros objetos de dominio (idCategoria)
A18: Corresponde a los datos que se generarán automáticamente (idProducto)
A19: Corresponde a la combinación única 1

Sheet C-Producto
A1: << Ir al modelo de dominio | D1: << Ir al listado de objetos de dominio | G1: << Ir a la caracterización del objeto de dominio
A2: Nombre | B2: ='M-Producto'!B2 -> Producto
A3: Descripción | B3: ='M-Producto'!B3 -> Objeto de dominio que representa a cada uno de los artículos de importación (bolsos, juguetes, etc.) que están disponibles para la venta en la tienda.
A4: Nombre atributo | B4: Descripción atributo | C4: Identificador del objeto de dominio | D4: Tipo de dato | E4: Obligatorio | F4: Longitud minima(si aplica longitud maxima(si aplica) | G4: Longitud maxima(si aplica longitud maxima(si aplica) | H4: Precisión (si aplica) | I4: Redondeo(si aplica) | J4: Rango inicial(si aplica) | K4: Rango final (si aplica) | L4: Formato(Si aplica) | M4: Reglas especiales(si aplica) | N4: Dato calculado | O4: Aplica ajuste del dato(si aplica) | P4: Carácter de ajuste(si aplica) | Q4: Quitar espacios en blanco al inicio(si aplica) | R4: Quitar espacios en blanco al fin(si aplica) | S4: Dato sensible(si aplica) | T4: Valor por defecto(si aplica) | U4: Auto generado | V4: Registrar un nuevo producto | W4: Consultar la información de los productos | X4: Consultar la información de los productos | Y4: Actualizar la información de un producto | Z4: Eliminar un producto
A5: ='M-Producto'!A5 -> id | B5: ='M-Producto'!A4 -> Identificador único universal (UUID) del producto. | C5: Si | D5: Alfanumerico | E5: Si | F5: 1 | L5: Mayusculas | N5: No | O5: No | Q5: Si | R5: Si | S5: No | U5: Si | V5: No requerido | W5: No requerido | X5: No requerido | Y5: Requerido | Z5: Requerido
A6: ='M-Producto'!B5 -> categoria | B6: ='M-Producto'!B4 -> Referencia a la categoría a la que pertenece el producto. | C6: No | D6: <Categoria> | E6: Si | F6: 1 | M6: Debe corresponder a una categoría válida del catálogo | N6: No | O6: No | S6: No | U6: No | V6: Requerido | W6: No requerido | X6: No requerido | Y6: Requerido | Z6: No requerido
A7: ='M-Producto'!C5 -> nombre | B7: ='M-Producto'!C4 -> Nombre comercial del producto. | C7: No | D7: Alfanumerico | E7: Si | F7: 1 | G7: 100 | L7: Mayusculas | M7: Debe corresponder a una categoría válida del catálogo | N7: No | O7: No | Q7: Si | R7: Si | S7: No | U7: No | V7: Requerido | W7: No requerido | X7: No requerido | Y7: Requerido | Z7: No requerido
A8: ='M-Producto'!D5 -> descripcion | B8: ='M-Producto'!D4 -> Descripción detallada de las características del producto. | C8: No | D8: Texto | E8: No | F8: 5 | G8: 1000 | L8: Capitalizado | N8: No | O8: No | Q8: Si | R8: Si | S8: No | U8: No | V8: Requerido | W8: No requerido | X8: No requerido | Y8: Requerido | Z8: No requerido
A9: ='M-Producto'!E5 -> precio | B9: ='M-Producto'!E4 -> Precio del producto en pesos colombianos (COP). | C9: No | D9: Numerico decimal | E9: Si | H9: 2 | I9: Truncamiento | J9: 1 | K9: 99999999 | M9: El valor no puede ser menor o igual a cero | N9: No | S9: No | U9: No | V9: No requerido | W9: No requerido | X9: No requerido | Y9: No requerido | Z9: No requerido
A10: ='M-Producto'!F5 -> stock | B10: ='M-Producto'!F4 -> Cantidad de unidades disponibles en inventario. | C10: No | D10: Numerico entero | E10: Si | F10: 0 | N10: No | O10: No | Q10: Si | R10: Si | S10: No | U10: No | V10: No requerido | W10: No requerido | X10: No requerido | Y10: Requerido | Z10: No requerido
A11: ='M-Producto'!G5 -> imagenUrl | B11: ='M-Producto'!G4 -> Ruta relativa a la imagen representativa del producto (opcional). | C11: No | D11: Texto | E11: No | F11: 5 | G11: 255 | L11: Capitalizado | M11: Solo permite los valores 'Activo' o 'Inactivo' | N11: No | O11: No | Q11: No | R11: Si | S11: No | T11: Activo | U11: No | V11: Requerido | W11: No requerido | X11: No requerido | Y11: Requerido | Z11: No requerido
A13: Nombre combinación unica | B13: Descripción | C13: Atributos involucrados
A14: ='M-Producto'!H5 -> CombinacionUnica1 | B14: ='M-Producto'!H4 -> Indica que no pueden existir dos productos o más con la misma referencia en el sistema. | C14: ='M-Producto'!C5 -> nombre
A16: Responsabilidad | B16: Descripción | C16: Entradas | F16: Salida | H16: Políticas (Reglas de Negocio) | J16: Excepción
C17: Parámettro | D17: Tipo de dato | E17: Descripci | F17: Tipo de Dato | G17: Descripción | H17: Política | I17: Descripción | J17: Detalle | K17: ¿Qué hago?
A18: ='E-Producto'!B7 -> Registrar un nuevo producto | B18: ='E-Producto'!C7 -> Añadir un nuevo artículo (ej. un portátil) al catálogo de ventas asociándolo a una categoría. | C18: productoNuevo | D18: Producto | E18: Contiene la información del producto que se va a registrar. | F18: Logico | G18: Retorna verdadero si el producto se agregó correctamente. | H18: ='E-Producto'!G7 -> PRO-POL-01 | I18: ='E-Producto'!H7 -> Asegurar que los datos requeridos sean válidos a nivel de tipo, formato, rango y obligatoriedad. | J18: Generar excepción indicando qué campo no cumple con el formato o es obligatorio. | K18: Detener operación
H19: ='E-Producto'!G8 -> PRO-POL-02 | I19: ='E-Producto'!H8 -> El idCategoria asociado debe existir previamente en el sistema. | J19: Generar excepción indicando que la categoría asignada al producto no existe. | K19: Detener operación
H20: ='E-Producto'!G9 -> PRO-POL-03 | I20: ='E-Producto'!H9 -> La referencia(SKU) no debe existir previamente en el sistema (Combinación única). | J20: Generar excepción indicando que el SKU ya está en uso por otro producto. | K20: Detener operación
A21: ='E-Categoria'!B12 -> Consultar categorías | B21: ='E-Categoria'!C12 -> Listar las categorías disponibles para desplegarlas en el menú de navegación o panel administrativo. | C21: productoModificado | D21: Producto | E21: Contiene la nueva información del producto a actualizar. | F21: Logico | G21: Retorna verdadero si el producto se modificó exitosamente. | H21: ='E-Producto'!G10 -> PRO-POL-04 | I21: ='E-Producto'!H10 -> El idProducto proporcionado debe existir obligatoriamente en el catálogo. | J21: Generar excepción indicando que el producto a modificar no existe en la base de datos. | K21: Detener operación
H22: ='E-Producto'!G11 -> PRO-POL-05 | I22: ='E-Producto'!H11 -> Si se modifica la referencia(SKU), la nueva no debe colisionar con otra existente. | J22: Generar excepción indicando que el nuevo SKU ingresado ya pertenece a otro producto. | K22: Detener operación
A23: ='E-Producto'!B12 -> Eliminar producto | B23: ='E-Producto'!C12 -> Retirar un producto del catálogo para que no pueda ser visualizado ni comprado por los clientes. | C23: idProducto | D23: alfanumerico | E23: Identificador exacto del producto que se desea borrar o inactivar. | F23: Logico | G23: Retorna verdadero si el producto fue eliminado o desactivado correctamente. | H23: ='E-Producto'!G12 -> PRO-POL-06 | I23: ='E-Producto'!H12 -> El idProducto a eliminar debe existir previamente en el sistema. | J23: Generar excepción indicando que el producto a eliminar no se encuentra registrado. | K23: Detener operación
H24: ='E-Producto'!G13 -> PRO-POL-07 | I24: ='E-Producto'!H13 -> El sistema no debe permitir eliminar el producto si este ya se encuentra asociado a un pedido histórico (se recomienda desactivarlo). | J24: Generar excepción indicando que el producto tiene historial de ventas y solo puede ser inactivado. | K24: Detener operación
A25: ='E-Producto'!B14 -> Consultar productos | B25: ='E-Producto'!C14 -> Listar y visualizar los detalles de los productos disponibles en la tienda web o panel de control. | C25: filtros | D25: Texto | E25: Parámetros opcionales para filtrar la búsqueda de productos. | F25: Lista<Producto> | G25: Retorna una colección con los objetos de los productos encontrados. | H25: ='E-Producto'!G14 -> PRO-POL-08 | I25: ='E-Producto'!H14 -> El Cliente solo puede ver productos en estado "Activo"; el Administrador puede ver todos los estados. | J25: Generar excepción indicando acceso denegado por intentar consultar productos inactivos sin permisos administrativos. | K25: Detener operación

Sheet E-Producto
A1: << Ir al modelo de dominio | E1: << Ir al listado de objetos de dominio | I1: << Ir a la caracterización del objeto de dominio
A2: Objeto de Dominio: | B2: =ListadoObjetosDominio!B7 -> Producto
A3: Descripción: | B3: =ListadoObjetosDominio!C7 -> Objeto de dominio que representa a cada uno de los artículos de importación (bolsos, juguetes, etc.) que están disponibles para la venta en la tienda.
A4: Actor | B4: Action/Command | D4: Entity/Aggregate/Object domain | E4: Read Model | G4: Business Rule/Policy | I4: External System | J4: Domain Event | K4: Hotspot/questions/Risk
A5: Actor | B5: Acción | C5: Descripción | D5: Objeto de dominio | E5: Información externa | G5: Políticas | I5: Sistema Externo | J5: Evento | K5: Aspectos por solucionar
E6: Información | F6: Descripción | G6: Número | H6: Descripción
A7: Administrador | B7: Registrar un nuevo producto | C7: Añadir un nuevo artículo (ej. un portátil) al catálogo de ventas asociándolo a una categoría. | D7: =ListadoObjetosDominio!B7 -> Producto | E7: idcategoria, referencia(SKU), nombre, precio, descripcion, estado | F7: Formulario para ingresar las características, valor y cantidad inicial del artículo. | G7: PRO-POL-01 | H7: Asegurar que los datos requeridos sean válidos a nivel de tipo, formato, rango y obligatoriedad. | I7: Base de datos | J7: Producto registrado | K7: ¿Qué pasa si se registra un producto sin imagen? ¿El sistema debe asignar una imagen "por defecto" (placeholder)?
G8: PRO-POL-02 | H8: El idCategoria asociado debe existir previamente en el sistema.
G9: PRO-POL-03 | H9: La referencia(SKU) no debe existir previamente en el sistema (Combinación única).
A10: Administrador | B10: Modificar producto | C10: Actualizar la información de un producto, como cambiar su precio o ajustar el inventario manualmente. | D10: =ListadoObjetosDominio!B7 -> Producto | E10: idProducto, idcategoria, referencia(SKU), nombre, precio, descripcion, estado | F10: Formulario pre-poblado con los datos actuales del producto para ser editados. | G10: PRO-POL-04 | H10: El idProducto proporcionado debe existir obligatoriamente en el catálogo. | I10: Base de datos | J10: Producto modificado | K10: Si se cambia el precio de un producto, ¿esto afecta automáticamente a los carritos de compras que los clientes aún no han pagado?
G11: PRO-POL-05 | H11: Si se modifica la referencia(SKU), la nueva no debe colisionar con otra existente.
A12: Administrador | B12: Eliminar producto | C12: Retirar un producto del catálogo para que no pueda ser visualizado ni comprado por los clientes. | D12: =ListadoObjetosDominio!B7 -> Producto | E12: idProducto | F12: Identificador del producto que el administrador desea eliminar. | G12: PRO-POL-06 | H12: El idProducto a eliminar debe existir previamente en el sistema. | I12: Base de datos | J12: Producto eliminado | K12: Afectación en el SEO de la página web si se desactiva masivamente la URL de productos muy visitados.
G13: PRO-POL-07 | H13: El sistema no debe permitir eliminar el producto si este ya se encuentra asociado a un pedido histórico (se recomienda desactivarlo).
A14: Cliente/Administrador | B14: Consultar productos | C14: Listar y visualizar los detalles de los productos disponibles en la tienda web o panel de control. | D14: =ListadoObjetosDominio!B7 -> Producto | E14: idProducto, idcategoria, referencia(SKU), nombre, precio, estado | F14: Vitrina virtual (Storefront) para el cliente o tabla de gestión para el administrador. | G14: PRO-POL-08 | H14: El Cliente solo puede ver productos en estado "Activo"; el Administrador puede ver todos los estados. | I14: Base de datos | J14: Productos consultados | K14: Si hay miles de productos, la consulta puede volver lento el sistema (se requiere paginación).

Sheet P-Producto
A1: << Ir al modelo de dominio | E1: << Ir al listado de objetos de dominio | I1: << Ir a la caracterización del objeto de dominio
A2: Objeto de Dominio: | B2: =ListadoObjetosDominio!B7 -> Producto
A3: Descripción: | B3: =ListadoObjetosDominio!C7 -> Objeto de dominio que representa a cada uno de los artículos de importación (bolsos, juguetes, etc.) que están disponibles para la venta en la tienda.
A4: Business Rule/Policy
A5: Políticas
A6: Número | B6: Descripción
A7: PRO-POL-01 | B7: Asegurar que los datos requeridos sean válidos a nivel de tipo, formato, rango y obligatoriedad.
A8: PRO-POL-02 | B8: El idCategoria asociado debe existir previamente en el sistema.
A9: PRO-POL-03 | B9: La referencia(SKU) no debe existir previamente en el sistema (Combinación única).
A10: PRO-POL-04 | B10: El idProducto proporcionado debe existir obligatoriamente en el catálogo.
A11: PRO-POL-05 | B11: Si se modifica la referencia(SKU), la nueva no debe colisionar con otra existente.
A12: PRO-POL-06 | B12: El idProducto a eliminar debe existir previamente en el sistema.
A13: PRO-POL-07 | B13: El sistema no debe permitir eliminar el producto si este ya se encuentra asociado a un pedido histórico (se recomienda desactivarlo).
A14: PRO-POL-08 | B14: El Cliente solo puede ver productos en estado "Activo"; el Administrador puede ver todos los estados.

Sheet M-ImagenProducto
A1: << Ir al modelo de dominio | D1: << Ir al listado de objetos de dominio | G1: << Ir a la caracterización del objeto de dominio
A3: Nombre | B3: =ListadoObjetosDominio!B8 -> ImagenProducto
A4: Descripción | B4: =ListadoObjetosDominio!C8 -> Objeto de dominio que representa a cada uno de los recursos visuales o fotografías asociadas a un producto para su exhibición.
A5: Representa el identificador único de cada imagen generado automáticamente por el sistema. | B5: Representa el objeto de dominio Producto al cual pertenece esta imagen. | C5: Representa la ruta web o enlace donde está alojada la fotografía del artículo | D5: Representa el número secuencial que define en qué orden se muestran las fotos en la galería | E5: Indica que no pueden existir dos imágenes con la misma URL asociadas al mismo producto.
A6: idimagen | B6: idproducto | C6: foto | D6: ordenVisualizacion | E6: Combinación única 1
A7: IMG-001 | B7: ='M-Producto'!A6 -> 4F8A0001-2222-4333-8444-555566667701 | C7: /assets/sombrilla-antiviento-1.jpg | D7: 1 | E7: =C7 -> /assets/sombrilla-antiviento-1.jpg
A8: IMG-002 | B8: ='M-Producto'!A6 -> 4F8A0001-2222-4333-8444-555566667701 | C8: /assets/sombrilla-antiviento-abierta.jpg | D8: 2 | E8: =C8 -> /assets/sombrilla-antiviento-abierta.jpg
A9: IMG-003 | B9: ='M-Producto'!A7 -> 4F8A0001-2222-4333-8444-555566667702 | C9: /assets/gorra-ninos-azul.jpg | D9: 1 | E9: =C9 -> /assets/gorra-ninos-azul.jpg
A10: IMG-004 | B10: P-0002 | C10: /assets/gorra-ninos-beige.jpg | D10: 2 | E10: =C10 -> /assets/gorra-ninos-beige.jpg
A11: IMG-005 | B11: ='M-Producto'!A8 -> 4F8A0001-2222-4333-8444-555566667703 | C11: /assets/tapete-bienvenido-verde.jpg | D11: 1 | E11: =C11 -> /assets/tapete-bienvenido-verde.jpg
A14: Corresponde a los datos generales del objeto de dominio (nombre, descripción)
A15: Corresponde a las descripciones de los atributos
A16: Coresponde al nombre de los atributos
A17: Corresponde a los datos que son de libre ingreso
A18: Corresponde a los datos que se generarán automáticamente
A19: Corresponde a la combinación única 1
A20: Corresponde a referencias a otros objetos de dominio

Sheet C-ImagenProducto 
A1: << Ir al modelo de dominio | D1: << Ir al listado de objetos de dominio | G1: << Ir a la caracterización del objeto de dominio
A2: Nombre | B2: ='M-ImagenProducto'!B3 -> ImagenProducto
A3: Descripción | B3: ='M-ImagenProducto'!B4 -> Objeto de dominio que representa a cada uno de los recursos visuales o fotografías asociadas a un producto para su exhibición.
A4: Nombre atributo | B4: Descripción atributo | C4: Identificador del objeto de dominio | D4: Tipo de dato | E4: Obligatorio | F4: Longitud minima(si aplica longitud maxima(si aplica) | G4: Longitud maxima(si aplica longitud maxima(si aplica) | H4: Precisión (si aplica) | I4: Redondeo(si aplica) | J4: Rango inicial(si aplica) | K4: Rango final (si aplica) | L4: Formato(Si aplica) | M4: Reglas especiales(si aplica) | N4: Dato calculado | O4: Aplica ajuste del dato(si aplica) | P4: Carácter de ajuste(si aplica) | Q4: Quitar espacios en blanco al inicio(si aplica) | R4: Quitar espacios en blanco al fin(si aplica) | S4: Dato sensible(si aplica) | T4: Valor por defecto(si aplica) | U4: Auto generado | V4: =A16 -> Agregar imagen | W4: =A19 -> Modificar imagen | X4: =A21 -> Eliminar imagen | Y4: =A23 -> Consultar imágenes
A5: ='M-ImagenProducto'!A6 -> idimagen | B5: ='M-ImagenProducto'!A5 -> Representa el identificador único de cada imagen generado automáticamente por el sistema. | C5: Si | D5: Alfanumerico | E5: Si | F5: 1 | G5: 20 | N5: No | O5: No | Q5: Si | R5: Si | S5: No | U5: Si | V5: Requerido | W5: No requerido
A6: ='M-ImagenProducto'!B6 -> idproducto | B6: ='M-ImagenProducto'!B5 -> Representa el objeto de dominio Producto al cual pertenece esta imagen. | C6: No | D6: <Producto> | E6: Si | M6: Debe corresponder a un producto existente en el catálogo | N6: No | S6: No | U6: No | V6: No requerido | W6: No requerido
A7: ='M-ImagenProducto'!C6 -> foto | B7: ='M-ImagenProducto'!C5 -> Representa la ruta web o enlace donde está alojada la fotografía del artículo | C7: No | D7: Texto | E7: Si | F7: 5 | G7: 500 | L7: URL / Minúsculas | M7: Debe ser una ruta válida terminada en extensión de imagen (ej. .jpg, .png, .webp) | N7: No | O7: No | Q7: Si | R7: Si | S7: No | U7: No | V7: Norequerido | W7: No requerido
A8: ='M-ImagenProducto'!D6 -> ordenVisualizacion | B8: ='M-ImagenProducto'!D5 -> Representa el número secuencial que define en qué orden se muestran las fotos en la galería | C8: No | D8: Numerico entero | E8: Si | J8: 1 | K8: 20 | M8: Determina la posición de la foto en la galería del producto (1 es la foto principal) | N8: No | S8: No | T8: 1 | U8: No
A10: Nombre combinación unica | B10: Descripción | C10: Atributos involucrados
A11: ='M-ImagenProducto'!E6 -> Combinación única 1 | B11: ='M-ImagenProducto'!E5 -> Indica que no pueden existir dos imágenes con la misma URL asociadas al mismo producto. | C11: ='M-ImagenProducto'!B6 -> idproducto
C12: ='M-ImagenProducto'!D6 -> ordenVisualizacion
A14: Responsabilidad | B14: Descripción | C14: Entradas | F14: Salida | H14: Políticas (Reglas de Negocio) | J14: Excepción
C15: Parámettro | D15: Tipo de dato | E15: Descripci | F15: Tipo de Dato | G15: Descripción | H15: Política | I15: Descripción | J15: Detalle | K15: ¿Qué hago?
A16: ='E-ImagenProducto'!B7 -> Agregar imagen | B16: ='E-ImagenProducto'!C7 -> Subir y asociar una nueva fotografía o render a la galería de un producto específico. | C16: magenNueva | D16: ImagenProducto | E16: Contiene la información y el archivo de la nueva imagen a registrar. | F16: Logico | G16: Retorna verdadero si la imagen se agregó correctamente al producto. | H16: ='E-ImagenProducto'!G7 -> P1 | I16: ='E-ImagenProducto'!H7 -> Asegurar que los datos requeridos sean válidos a nivel de tipo, formato, longitud y obligatoriedad. | J16: Generar excepción indicando qué campo no cumple con el formato o es obligatorio. | K16: Detener operación
H17: P2 | I17: El idProducto asociado debe existir previamente en el sistema. | J17: Generar excepción indicando que el producto asociado no existe. | K17: Detener operación
H18: ='E-ImagenProducto'!G9 -> P3 | I18: ='E-ImagenProducto'!H9 -> El sistema debe validar que la extensión del archivo sea permitida (ej. .jpg, .png, .webp). | J18: Generar excepción indicando que el formato del archivo subido no es permitido. | K18: Detener operación
A19: ='E-ImagenProducto'!B10 -> Modificar imagen | B19: ='E-ImagenProducto'!F10 -> Listado de miniaturas del producto con inputs numéricos para definir el orden. | C19: imagenModificada | D19: ImagenProducto | E19: Contiene la nueva información de la imagen y su orden de visualización. | F19: Logico | G19: Retorna verdadero si la imagen o su orden se modificó exitosamente. | H19: ='E-ImagenProducto'!G10 -> P4 | I19: ='E-ImagenProducto'!H10 -> El idImagen a modificar debe existir previamente en el sistema. | J19: Generar excepción indicando que la imagen a modificar no existe en la base de datos. | K19: Detener operación
H20: ='E-ImagenProducto'!G11 -> P5 | I20: ='E-ImagenProducto'!H11 -> No pueden existir dos imágenes con el mismo ordenVisualizacion para un mismo producto. | J20: Generar excepción indicando que el orden de visualización ya está ocupado por otra imagen. | K20: Detener operación
A21: ='E-ImagenProducto'!B12 -> Eliminar imagen | B21: ='E-ImagenProducto'!C12 -> Retirar una fotografía específica de la galería de un producto. | C21: idImagen | D21: alfanumerico | E21: Identificador exacto de la imagen que se desea borrar. | F21: Logico | G21: Retorna verdadero si la imagen fue eliminada correctamente. | H21: ='E-ImagenProducto'!G12 -> P6 | I21: ='E-ImagenProducto'!H12 -> El idImagen a eliminar debe existir previamente en el sistema. | J21: Generar excepción indicando que la imagen a eliminar no se encuentra registrada. | K21: Detener operación
H22: ='E-ImagenProducto'!G13 -> P7 | I22: ='E-ImagenProducto'!H13 -> El sistema debe impedir borrar la última imagen si la regla de negocio exige que todo producto tenga al menos una foto. | J22: Generar excepción indicando que no se puede eliminar porque el producto debe conservar al menos una imagen. | K22: Detener operación
A23: ='E-ImagenProducto'!B14 -> Consultar imágenes | B23: ='E-ImagenProducto'!C14 -> Obtener la galería de fotos asociada a un producto para mostrarla en el catálogo o en el detalle del artículo. | C23: idProducto | D23: alfanumerico | E23: Identificador del producto del cual se quieren obtener las fotos. | F23: Lista<ImagenProducto> | G23: Retorna una colección con los objetos de las imágenes encontradas. | H23: ='E-ImagenProducto'!G14 -> P8 | I23: ='E-ImagenProducto'!H14 -> Asegurar que los datos requeridos sean válidos a nivel de tipo, formato, longitud y obligatoriedad. | J23: Generar excepción indicando que los parámetros de consulta tienen un formato incorrecto. | K23: Detener operación

Sheet E-ImagenProducto
A1: << Ir al modelo de dominio | E1: << Ir al listado de objetos de dominio | I1: << Ir a la caracterización del objeto de dominio
A2: Objeto de Dominio: | B2: =ListadoObjetosDominio!B8 -> ImagenProducto
A3: Descripción: | B3: =ListadoObjetosDominio!C8 -> Objeto de dominio que representa a cada uno de los recursos visuales o fotografías asociadas a un producto para su exhibición.
A4: Actor | B4: Action/Command | D4: Entity/Aggregate/Object domain | E4: Read Model | G4: Business Rule/Policy | I4: External System | J4: Domain Event | K4: Hotspot/questions/Risk
A5: Actor | B5: Acción | C5: Descripción | D5: Objeto de dominio | E5: Información externa | G5: Políticas | I5: Sistema Externo | J5: Evento | K5: Aspectos por solucionar
E6: Información | F6: Descripción | G6: Número | H6: Descripción
A7: Administrador | B7: Agregar imagen | C7: Subir y asociar una nueva fotografía o render a la galería de un producto específico. | D7: =ListadoObjetosDominio!B8 -> ImagenProducto | E7: idproducto, foto, ordenVisualizacion | F7: Formulario de carga de archivos multimedia asociado a un artículo del catálogo. | G7: P1 | H7: Asegurar que los datos requeridos sean válidos a nivel de tipo, formato, longitud y obligatoriedad. | I7: Cloud Storage (Almacenamiento) | J7: Imagen registrada | K7: Riesgo de que se suban imágenes muy pesadas (ej. 5MB) que pongan lenta la carga de la página para los clientes.
G8: P2 | H8: El idProducto asociado debe existir previamente en el sistema.
G9: P3 | H9: El sistema debe validar que la extensión del archivo sea permitida (ej. .jpg, .png, .webp).
A10: Administrador | B10: Modificar imagen | C10: Actualizar la ruta del archivo o cambiar el estado para definir si es la foto principal (de portada) del producto. | D10: =ListadoObjetosDominio!B8 -> ImagenProducto | E10: idimagen, idproducto, foto, ordenVisualizacion | F10: Listado de miniaturas del producto con inputs numéricos para definir el orden. | G10: P4 | H10: El idImagen a modificar debe existir previamente en el sistema. | J10: Imagen modificada | K10: Si dos imágenes del mismo producto quedan con el mismo número de ordenVisualizacion, la galería podría romperse o mostrarse aleatoriamente.
G11: P5 | H11: No pueden existir dos imágenes con el mismo ordenVisualizacion para un mismo producto.
A12: Administrador | B12: Eliminar imagen | C12: Retirar una fotografía específica de la galería de un producto. | D12: =ListadoObjetosDominio!B8 -> ImagenProducto | E12: idImagen | F12: Botón de eliminar sobre la miniatura de la imagen en el panel de control. | G12: P6 | H12: El idImagen a eliminar debe existir previamente en el sistema. | I12: Cloud Storage (Almacenamiento) | J12: Imagen eliminada | K12: Si falla la conexión con el sistema externo, la imagen se borra de la base de datos pero el archivo físico queda ocupando espacio basura en la nube.
G13: P7 | H13: El sistema debe impedir borrar la última imagen si la regla de negocio exige que todo producto tenga al menos una foto.
A14: Cliente / Administrador | B14: Consultar imágenes | C14: Obtener la galería de fotos asociada a un producto para mostrarla en el catálogo o en el detalle del artículo. | D14: =ListadoObjetosDominio!B8 -> ImagenProducto | E14: idimagen, idproducto, foto, ordenVisualizacion | F14: Carrusel de fotos en la página del producto, ordenado ascendentemente por ordenVisualizacion. | G14: P8 | H14: Asegurar que los datos requeridos sean válidos a nivel de tipo, formato, longitud y obligatoriedad. | I14: CDN (Content Delivery Network) | J14: Imágenes consultadas | K14: Si el sistema externo (CDN) se cae, los productos se mostrarán sin fotos (enlaces rotos).

Sheet P-ImagenProducto 
A1: << Ir al modelo de dominio | E1: << Ir al listado de objetos de dominio | I1: << Ir a la caracterización del objeto de dominio
A2: Objeto de Dominio: | B2: =ListadoObjetosDominio!B8 -> ImagenProducto
A3: Descripción: | B3: =ListadoObjetosDominio!C8 -> Objeto de dominio que representa a cada uno de los recursos visuales o fotografías asociadas a un producto para su exhibición.
A4: Business Rule/Policy
A5: Políticas
A6: Número | B6: Descripción
A7: P1 | B7: Asegurar que los datos requeridos sean válidos a nivel de tipo, formato, longitud y obligatoriedad.
A8: P2 | B8: El idProducto asociado debe existir previamente en el sistema.
A9: P3 | B9: El sistema debe validar que la extensión del archivo sea permitida (ej. .jpg, .png, .webp).
A10: P4 | B10: El idImagen a modificar debe existir previamente en el sistema.
A11: P5 | B11: No pueden existir dos imágenes con el mismo ordenVisualizacion para un mismo producto.
A12: P6 | B12: El idImagen a eliminar debe existir previamente en el sistema.
A13: P7 | B13: El sistema debe impedir borrar la última imagen si la regla de negocio exige que todo producto tenga al menos una foto.
A14: P8 | B14: Asegurar que los datos requeridos sean válidos a nivel de tipo, formato, longitud y obligatoriedad.

Sheet M-Reseña
A1: << Ir al modelo de dominio | H1: << Ir al listado de objetos de dominio | K1: << Ir a la caracterización del objeto de dominio
A2: Nombre | B2: =ListadoObjetosDominio!B9 -> Reseña
A3: Descripción | B3: =ListadoObjetosDominio!C9 -> Objeto de dominio que representa a cada una de las calificaciones y comentarios dejados por un cliente sobre un producto específico que ya ha comprado.
A4: Representa el identificador único de cada cotización generado automáticamente por el sistema. | B4: Referencia al objeto de dominio "Cliente" que escribe la opinión | C4: Referencia al objeto de dominio "Producto" que es calificado | D4: Puntuación otorgada al artículo, generalmente en una escala de 1 a 5 estrellas | E4: Representa el texto opcional donde el cliente describe su experiencia de uso y calidad | F4: Representa la fecha y hora en que fue creada la solicitud de cotización por parte del cliente. | G4: Indica que un mismo cliente no puede publicar más de una reseña para un mismo producto
A5: idResena | B5: idCliente | C5: idProducto | D5: calificacion | E5: comentario | F5: fecha | G5: Combinación única 1
A6: RES-001 | B6: ='M-Cliente'!A7 -> 3F2504E0-4F89-11D3-9A0C-0305E82C3301 | C6: ='M-Producto'!A6 -> 4F8A0001-2222-4333-8444-555566667701 | D6: 5 | E6: "Excelente sombrilla, resiste muy bien el viento y es de buen tamaño." | F6: 46082 | G6: =A6 -> RES-001
A7: RES-002 | B7: ='M-Cliente'!A8 -> 3F2504E0-4F89-11D3-9A0C-0305E82C3302 | C7: ='M-Producto'!A7 -> 4F8A0001-2222-4333-8444-555566667702 | D7: 4 | E7: "El tapete es bonito, pero el color verde es un poco más oscuro que en la foto." | F7: 46083 | G7: =A7 -> RES-002
A8: RES-003 | B8: ='M-Cliente'!A9 -> 3F2504E0-4F89-11D3-9A0C-0305E82C3303 | C8: ='M-Producto'!A8 -> 4F8A0001-2222-4333-8444-555566667703 | D8: 5 | E8: "Las cucharas son de excelente calidad, gruesas y no se doblan fácil." | F8: 46084 | G8: =A8 -> RES-003
A9: RES-004 | B9: ='M-Cliente'!A10 -> 3F2504E0-4F89-11D3-9A0C-0305E82C3304 | C9: ='M-Producto'!A9 -> 4F8A0001-2222-4333-8444-555566667704 | D9: 5 | E9: "A mi hijo le encantó la gorra de osito, el material es muy fresco." | F9: 46085 | G9: =A9 -> RES-004
A10: RES-005 | B10: ='M-Cliente'!A7 -> 3F2504E0-4F89-11D3-9A0C-0305E82C3301 | C10: ='M-Producto'!A10 -> 4F8A0001-2222-4333-8444-555566667705 | D10: 4 | E10: "Buena bolsa" | F10: 46086 | G10: =A10 -> RES-005
A13: Corresponde a los datos generales del objeto de dominio (nombre, descripción)
A14: Corresponde a las descripciones de los atributos
A15: Coresponde al nombre de los atributos
A16: Corresponde a los datos que son de libre ingreso
A17: Corresponde a los datos que se generarán automáticamente
A18: Corresponde a la combinación única 1
A19: Corresponde a referencias a otros objetos de dominio

Sheet C-Reseña
A1: << Ir al modelo de dominio | D1: << Ir al listado de objetos de dominio | G1: << Ir a la caracterización del objeto de dominio
A2: Nombre | B2: ='M-Reseña'!B2 -> Reseña
A3: Descripción | B3: ='M-Reseña'!B3 -> Objeto de dominio que representa a cada una de las calificaciones y comentarios dejados por un cliente sobre un producto específico que ya ha comprado.
A4: Nombre atributo | B4: Descripción atributo | C4: Identificador del objeto de dominio | D4: Tipo de dato | E4: Obligatorio | F4: Longitud minima(si aplica longitud maxima(si aplica) | G4: Longitud maxima(si aplica longitud maxima(si aplica) | H4: Precisión (si aplica) | I4: Redondeo(si aplica) | J4: Rango inicial(si aplica) | K4: Rango final (si aplica) | L4: Formato(Si aplica) | M4: Reglas especiales(si aplica) | N4: Dato calculado | O4: Aplica ajuste del dato(si aplica) | P4: Carácter de ajuste(si aplica) | Q4: Quitar espacios en blanco al inicio(si aplica) | R4: Quitar espacios en blanco al fin(si aplica) | S4: Dato sensible(si aplica) | T4: Valor por defecto(si aplica) | U4: Auto generado
A5: ='M-Reseña'!A5 -> idResena | B5: ='M-Reseña'!A4 -> Representa el identificador único de cada cotización generado automáticamente por el sistema. | C5: Si | D5: alfanumerico | E5: Si | F5: 1 | G5: 20 | L5: Mayusculas | N5: No | O5: No | Q5: Si | R5: Si | S5: No | U5: Si
A6: ='M-Reseña'!B5 -> idCliente | B6: ='M-Reseña'!B4 -> Referencia al objeto de dominio "Cliente" que escribe la opinión | C6: No | D6: <Cliente> | E6: Si | M6: El cliente debe existir y haber comprado el producto | N6: No | S6: No | U6: No
A7: ='M-Reseña'!C5 -> idProducto | B7: ='M-Reseña'!C4 -> Referencia al objeto de dominio "Producto" que es calificado | C7: No | D7: <Producto> | E7: Si | M7: El producto debe existir en el catálogo | N7: No | S7: No | U7: No
A8: ='M-Reseña'!D5 -> calificacion | B8: ='M-Reseña'!D4 -> Puntuación otorgada al artículo, generalmente en una escala de 1 a 5 estrellas | C8: No | D8: Numerico entero | E8: Si | J8: 1 | K8: 5 | M8: La cotización debe estar asociada obligatoriamente a un cliente registrado. | N8: No | S8: No | U8: No
A9: ='M-Reseña'!E5 -> comentario | B9: ='M-Reseña'!E4 -> Representa el texto opcional donde el cliente describe su experiencia de uso y calidad | C9: No | D9: Texto | E9: No | F9: 0 | G9: 1000 | M9: No debe contener lenguaje ofensivo | N9: No | O9: No | Q9: Si | R9: Si | S9: No | U9: No
A10: ='M-Reseña'!F5 -> fecha | B10: ='M-Reseña'!F4 -> Representa la fecha y hora en que fue creada la solicitud de cotización por parte del cliente. | C10: No | D10: Fecha/Hora | E10: Si | M10: Registra el momento exacto en el que se publicó o editó la calificación | N10: No | S10: No | U10: Si
A12: Nombre combinación unica | B12: Descripción | C12: Atributos involucrados
A13: ='M-Reseña'!G5 -> Combinación única 1 | B13: ='M-Reseña'!G4 -> Indica que un mismo cliente no puede publicar más de una reseña para un mismo producto | C13: {='M-Reseña'!B5:C5} -> idCliente | D13: idProducto
A15: Responsabilidad | B15: Descripción | C15: Entradas | F15: Salida | H15: Políticas (Reglas de Negocio) | J15: Excepción
C16: Parámettro | D16: Tipo de dato | E16: Descripci | F16: Tipo de Dato | G16: Descripción | H16: Política | I16: Descripción | J16: Detalle | K16: ¿Qué hago?
A17: ='E-Reseña'!B7 -> Crear reseña | B17: ='E-Reseña'!C7 -> Publicar una calificación y un comentario sobre un producto específico de la tienda. | C17: resenaNueva | D17: Reseña | E17: Contiene la información de la reseña a registrar (calificación, comentario). | F17: Logico | G17: Retorna verdadero si la reseña se publicó exitosamente. | H17: ='E-Reseña'!G7 -> RES-POL-01 | I17: ='E-ImagenProducto'!H8 -> El idProducto asociado debe existir previamente en el sistema. | J17: Generar excepción indicando qué campo no cumple con el formato o es obligatorio. | K17: Detener operación
H18: ='E-Reseña'!G8 -> RES-POL-02 | I18: El idProducto asociado debe existir previamente en el sistema. | J18: Generar excepción indicando que el cliente no puede calificar un producto que no ha comprado. | K18: Detener operación
H19: ='E-Reseña'!G9 -> RES-POL-03 | I19: ='E-ImagenProducto'!H10 -> El idImagen a modificar debe existir previamente en el sistema. | J19: Generar excepción indicando que la calificación debe estar entre 1 y 5. | K19: Detener operación
A20: ='E-Reseña'!B10 -> Eliminar reseña | B20: ='E-Reseña'!C10 -> Borrar una reseña porque incumple las normas de la comunidad (insultos) o por deseo del autor. | C20: idResena | D20: alfanumerico | E20: Identificador exacto de la reseña que se desea borrar. | F20: Logico | G20: Retorna verdadero si la reseña fue eliminada correctamente. | H20: ='E-Reseña'!G10 -> RES-POL-05 | I20: ='E-ImagenProducto'!H11 -> No pueden existir dos imágenes con el mismo ordenVisualizacion para un mismo producto. | J20: Generar excepción indicando que la reseña a eliminar no se encuentra registrada. | K20: Detener operación
H21: ='E-Reseña'!G11 -> RES-POL-06 | I21: ='E-ImagenProducto'!H12 -> El idImagen a eliminar debe existir previamente en el sistema. | J21: Generar excepción indicando acceso denegado por intentar borrar una reseña de otro usuario sin rol de administrador. | K21: Detener operación
A22: ='E-Reseña'!B12 -> Consultar reseñas | B22: ='E-Reseña'!C12 -> Leer los comentarios y ver el promedio de calificaciones que otros han dejado sobre un producto. | C22: idProducto | D22: alfanumerico | E22: Identificador del producto del cual se quieren consultar las opiniones. | F22: Lista<Reseña> | G22: Retorna una colección con los objetos de las reseñas encontradas. | H22: ='E-Reseña'!G12 -> RES-POL-07 | I22: ='E-ImagenProducto'!H13 -> El sistema debe impedir borrar la última imagen si la regla de negocio exige que todo producto tenga al menos una foto. | J22: Generar excepción indicando que los parámetros de búsqueda tienen un formato incorrecto. | K22: Detener operación

Sheet E-Reseña
A1: << Ir al modelo de dominio | E1: << Ir al listado de objetos de dominio | I1: << Ir a la caracterización del objeto de dominio
A2: Objeto de Dominio: | B2: =ListadoObjetosDominio!B9 -> Reseña
A3: Descripción: | B3: =ListadoObjetosDominio!C9 -> Objeto de dominio que representa a cada una de las calificaciones y comentarios dejados por un cliente sobre un producto específico que ya ha comprado.
A4: Actor | B4: Action/Command | D4: Entity/Aggregate/Object domain | E4: Read Model | G4: Business Rule/Policy | I4: External System | J4: Domain Event | K4: Hotspot/questions/Risk
A5: Actor | B5: Acción | C5: Descripción | D5: Objeto de dominio | E5: Información externa | G5: Políticas | I5: Sistema Externo | J5: Evento | K5: Aspectos por solucionar
E6: Información | F6: Descripción | G6: Número | H6: Descripción
A7: Cliente | B7: Crear reseña | C7: Publicar una calificación y un comentario sobre un producto específico de la tienda. | D7: =ListadoObjetosDominio!B9 -> Reseña | E7: idCliente, idProducto, calificacion, comentario, fecha | F7: Formulario de valoración (estrellas y texto) en la página del producto. | G7: RES-POL-01 | H7: Asegurar que los datos requeridos sean válidos a nivel de tipo, formato, longitud y obligatoriedad. | I7: API de Moderación de Texto / Filtro Antispam | J7: Reseña creada | K7: Riesgo de "Fake Reviews" (Spam). ¿Debería el sistema permitir reseñas de personas que no han comprado el producto?
G8: RES-POL-02 | H8: El idCliente debe haber realizado una compra exitosa del idProducto previamente (Compra Verificada).
G9: RES-POL-03 | H9: El valor de 'calificacion' debe estar estrictamente en el rango permitido (ej. 1 a 5).
A10: Cliente / Administrador | B10: Eliminar reseña | C10: Borrar una reseña porque incumple las normas de la comunidad (insultos) o por deseo del autor. | D10: =ListadoObjetosDominio!B9 -> Reseña | E10: idResena | F10: Botón de eliminación en el panel del administrador o en el perfil del cliente. | G10: RES-POL-05 | H10: El idResena a eliminar debe existir previamente en el sistema. | J10: Reseña eliminada | K10: Si un administrador elimina reseñas negativas sistemáticamente para inflar la calificación, se pierde la ética y confianza del sitio.
G11: RES-POL-06 | H11: El cliente solo puede eliminar sus propias reseñas; el administrador puede eliminar cualquiera que viole las políticas (lenguaje ofensivo).
A12: Cliente / Administrador | B12: Consultar reseñas | C12: Leer los comentarios y ver el promedio de calificaciones que otros han dejado sobre un producto. | D12: =ListadoObjetosDominio!B9 -> Reseña | E12: idResena, idCliente, idProducto, calificacion, comentario, fecha | F12: Sección de comentarios al final del detalle del producto en la tienda. | G12: RES-POL-07 | H12: Asegurar que los datos requeridos sean válidos a nivel de tipo, formato, longitud y obligatoriedad. | J12: Reseñas consultadas | K12: Cargar miles de reseñas al mismo tiempo al abrir un producto puede colapsar la página (se requiere paginación).

Sheet P-Reseña
A1: << Ir al modelo de dominio | E1: << Ir al listado de objetos de dominio | I1: << Ir a la caracterización del objeto de dominio
A2: Objeto de Dominio: | B2: =ListadoObjetosDominio!B9 -> Reseña
A3: Descripción: | B3: =ListadoObjetosDominio!C9 -> Objeto de dominio que representa a cada una de las calificaciones y comentarios dejados por un cliente sobre un producto específico que ya ha comprado.
A4: Business Rule/Policy
A5: Políticas
A6: Número | B6: Descripción
A7: RES-POL-01 | B7: Asegurar que los datos requeridos sean válidos a nivel de tipo, formato, longitud y obligatoriedad.
A8: RES-POL-02 | B8: El idCliente debe haber realizado una compra exitosa del idProducto previamente (Compra Verificada).
A9: RES-POL-03 | B9: El valor de 'calificacion' debe estar estrictamente en el rango permitido (ej. 1 a 5).
A10: RES-POL-05 | B10: El idResena a eliminar debe existir previamente en el sistema.
A11: RES-POL-06 | B11: El cliente solo puede eliminar sus propias reseñas; el administrador puede eliminar cualquiera que viole las políticas (lenguaje ofensivo).
A12: RES-POL-07 | B12: Asegurar que los datos requeridos sean válidos a nivel de tipo, formato, longitud y obligatoriedad.

Sheet M-CarritoCompras
A1: << Ir al modelo de dominio | E1: << Ir al listado de objetos de dominio | G1: << Ir a la caracterización del objeto de dominio
A2: Nombre | B2: =ListadoObjetosDominio!B10 -> CarritoCompras
A3: Descripción | B3: =ListadoObjetosDominio!C10 -> Objeto de dominio que representa la sesión temporal donde un cliente agrupa los productos que tiene intención de adquirir antes de formalizar la transacción.
A4: Identificador único universal (UUID) del carrito de compras. | B4: Referencia al cliente propietario del carrito. | C4: Fecha de creación del carrito (LocalDate). | D4: Estado del carrito (ACTIVO, ABANDONADO, FINALIZADO). | E4: Indica que un cliente no puede tener más de un carrito “Activo” simultáneamente
A5: id | B5: cliente | C5: fechaCreacion | D5: estado | E5: CombinacionUnica1
A6: CC000001-AAAA-4BBB-8CCC-DDDDEEEEFF01 | B6: 3F2504E0-4F89-11D3-9A0C-0305E82C3301 | C6: 2026-05-18 | D6: ACTIVO | E6: =D6 -> ACTIVO
A7: CC000001-AAAA-4BBB-8CCC-DDDDEEEEFF02 | B7: 3F2504E0-4F89-11D3-9A0C-0305E82C3302 | C7: 2026-05-19 | D7: FINALIZADO | E7: =D7 -> FINALIZADO
A8: CC000001-AAAA-4BBB-8CCC-DDDDEEEEFF03 | B8: 3F2504E0-4F89-11D3-9A0C-0305E82C3303 | C8: 2026-05-19 | D8: ACTIVO | E8: =D8 -> ACTIVO
A9: CC000001-AAAA-4BBB-8CCC-DDDDEEEEFF04 | B9: 3F2504E0-4F89-11D3-9A0C-0305E82C3304 | C9: 2026-05-20 | D9: ABANDONADO | E9: =D9 -> ABANDONADO
A10: CC000001-AAAA-4BBB-8CCC-DDDDEEEEFF05 | B10: 3F2504E0-4F89-11D3-9A0C-0305E82C3305 | C10: 2026-05-21 | D10: ACTIVO | E10: =D10 -> ACTIVO
A13: Corresponde a los datos generales del objeto de dominio (nombre, descripción)
A14: Corresponde a las descripciones de los atributos
A15: Coresponde al nombre de los atributos
A16: Corresponde a los datos que son de libre ingreso
A17: Corresponde a los datos que se generarán automáticamente
A18: Corresponde a la combinación única 1
A19: Corresponde a referencias a otros objetos de dominio

Sheet C-CarritoCompras
A1: << Ir al modelo de dominio | D1: << Ir al listado de objetos de dominio | G1: << Ir a la caracterización del objeto de dominio
A2: Nombre | B2: ='M-CarritoCompras'!B2 -> CarritoCompras
A3: Descripción | B3: ='M-CarritoCompras'!B3 -> Objeto de dominio que representa la sesión temporal donde un cliente agrupa los productos que tiene intención de adquirir antes de formalizar la transacción.
A4: Nombre atributo | B4: Descripción atributo | C4: Identificador del objeto de dominio | D4: Tipo de dato | E4: Obligatorio | F4: Longitud minima(si aplica longitud maxima(si aplica) | G4: Longitud maxima(si aplica longitud maxima(si aplica) | H4: Precisión (si aplica) | I4: Redondeo(si aplica) | J4: Rango inicial(si aplica) | K4: Rango final (si aplica) | L4: Formato(Si aplica) | M4: Reglas especiales(si aplica) | N4: Dato calculado | O4: Aplica ajuste del dato(si aplica) | P4: Carácter de ajuste(si aplica) | Q4: Quitar espacios en blanco al inicio(si aplica) | R4: Quitar espacios en blanco al fin(si aplica) | S4: Dato sensible(si aplica) | T4: Valor por defecto(si aplica) | U4: Auto generado | V4: =#REF! -> #REF! | W4: =#REF! -> #REF! | X4: =#REF! -> #REF! | Y4: =#REF! -> #REF!
A5: ='M-CarritoCompras'!A5 -> id | B5: ='M-CarritoCompras'!A4 -> Identificador único universal (UUID) del carrito de compras. | C5: Si | D5: Alfanumerico | E5: Si | F5: 1 | L5: Mayúsculas | N5: No | O5: No | Q5: Si | R5: Si | S5: No | U5: Si | V5: Requerido | W5: No requerido
A6: ='M-CarritoCompras'!B5 -> cliente | B6: ='M-CarritoCompras'!B4 -> Referencia al cliente propietario del carrito. | C6: No | D6: <Cliente> | E6: Si | M6: El cliente debe existir en el sistema para asignarle una sesión de carrito | N6: No | S6: No | U6: No | V6: No requerido | W6: No requerido
A7: ='M-CarritoCompras'!C5 -> fechaCreacion | B7: ='M-CarritoCompras'!C4 -> Fecha de creación del carrito (LocalDate). | C7: No | D7: Fecha | E7: Si | M7: Registra el momento exacto en el que el cliente inició la intención de compra | N7: No | S7: No | U7: Si | V7: Norequerido | W7: No requerido
A8: ='M-CarritoCompras'!D5 -> estado | B8: ='M-CarritoCompras'!D4 -> Estado del carrito (ACTIVO, ABANDONADO, FINALIZADO). | C8: No | D8: Texto | E8: Si | F8: 5 | G8: 20 | L8: Capitalizado | M8: Solo permite los valores 'Activo', 'Abandonado' o 'Convertido' | N8: No | O8: No | Q8: Si | R8: Si | S8: No | T8: Activo | U8: No
A10: Nombre combinación unica | B10: Descripción | C10: Atributos involucrados
A11: ='M-CarritoCompras'!E5 -> CombinacionUnica1 | B11: ='M-CarritoCompras'!E4 -> Indica que un cliente no puede tener más de un carrito “Activo” simultáneamente | C11: ='M-CarritoCompras'!B5 -> cliente
C12: ='M-CarritoCompras'!D5 -> estado
A14: Responsabilidad | B14: Descripción | C14: Entradas | F14: Salida | H14: Políticas (Reglas de Negocio) | J14: Excepción
C15: Parámettro | D15: Tipo de dato | E15: Descripci | F15: Tipo de Dato | G15: Descripción | H15: Política | I15: Descripción | J15: Detalle | K15: ¿Qué hago?
A16: ='E-CarritoCompras'!B7 -> Crear carrito | B16: ='E-CarritoCompras'!C7 -> Iniciar una nueva sesión de compras asignando un contenedor vacío al usuario. | C16: carritoNuevo | D16: CarritoCompras | E16: Contiene la información base del nuevo carrito a crear. | F16: Logico | G16: Retorna verdadero si el carrito se creó exitosamente. | H16: ='E-CarritoCompras'!G7 -> CAR-POL-01 | I16: ='E-CarritoCompras'!H7 -> Asegurar que los datos requeridos sean válidos a nivel de tipo, formato, longitud y obligatoriedad. | J16: Generar excepción indicando qué campo no cumple con el formato o es obligatorio. | K16: Detener operación
H17: ='E-CarritoCompras'!G8 -> CAR-POL-02 | I17: ='E-CarritoCompras'!H8 -> El idCliente asociado debe existir previamente en el sistema. | J17: Generar excepción indicando que el cliente asociado no se encuentra registrado. | K17: Detener operación
H18: ='E-CarritoCompras'!G9 -> CAR-POL-03 | I18: ='E-CarritoCompras'!H9 -> Un cliente solo puede tener un (1) carrito en estado "Activo" a la vez. | J18: Generar excepción indicando que el usuario ya tiene un carrito de compras en curso. | K18: Detener operación
A19: ='E-CarritoCompras'!B10 -> Actualizar carrito (Añadir/Modificar) | B19: ='E-CarritoCompras'!C10 -> Recalcular el total del carrito cuando el usuario agrega nuevos productos o cambia cantidades. | C19: carritoModificado | D19: CarritoCompras | E19: Contiene el carrito con los valores actualizados. | F19: Logico | G19: Retorna verdadero si el carrito se actualizó correctamente. | H19: ='E-CarritoCompras'!G10 -> CAR-POL-04 | I19: ='E-CarritoCompras'!H10 -> El idCarrito a actualizar debe existir y pertenecer al cliente en sesión. | J19: Generar excepción indicando que el carrito no existe o no pertenece al usuario actual. | K19: Detener operación
H20: ='E-CarritoCompras'!G11 -> CAR-POL-05 | I20: ='E-CarritoCompras'!H11 -> El nuevo total calculado no puede ser un valor negativo. | J20: Generar excepción indicando que el cálculo del total generó un valor inconsistente (negativo). | K20: Detener operación
A21: ='E-CarritoCompras'!B12 -> Vaciar carrito | B21: ='E-CarritoCompras'!C12 -> Eliminar todos los artículos seleccionados y reiniciar el valor del carrito para empezar de cero. | C21: idCarrito | D21: alfanumerico | E21: Identificador exacto del carrito que se desea vaciar. | F21: Logico | G21: Retorna verdadero si el carrito fue vaciado exitosamente. | H21: ='E-CarritoCompras'!G12 -> CAR-POL-06 | I21: ='E-CarritoCompras'!H12 -> El idCarrito a vaciar debe existir previamente en el sistema. | J21: Generar excepción indicando que el carrito a vaciar no se encuentra en el sistema. | K21: Detener operación
H22: ='E-CarritoCompras'!G13 -> CAR-POL-07 | I22: ='E-CarritoCompras'!H13 -> El sistema solo puede vaciar el carrito si no ha sido transformado ya en un "Pedido" pagado. | J22: Generar excepción indicando que no se puede alterar un carrito que ya finalizó su proceso de compra. | K22: Detener operación
A23: ='E-CarritoCompras'!B14 -> Consultar carrito | B23: ='E-CarritoCompras'!C14 -> Visualizar el resumen de la compra, incluyendo el monto total acumulado antes del checkout. | C23: idCarrito | D23: alfanumerico | E23: Identificador del carrito que se transformará en pedido. | F23: Logico | G23: Retorna verdadero si el carrito cambió de estado exitosamente. | H23: ='E-CarritoCompras'!G14 -> CAR-POL-08 | I23: ='E-CarritoCompras'!H14 -> Asegurar que los datos requeridos sean válidos a nivel de tipo, formato, longitud y obligatoriedad. | J23: Generar excepción indicando que no se puede procesar la compra de un carrito vacío. | K23: Detener operación
A24: ='E-CarritoCompras'!B15 -> Cambiar estado (Convertir a Pedido) | B24: ='E-CarritoCompras'!C15 -> Actualizar el carrito para indicar que ya fue pagado y cerrado exitosamente | C24: idCliente | D24: alfanumerico | E24: Identificador del cliente del cual se quiere consultar el carrito activo. | F24: CarritoCompras | G24: Retorna el objeto del carrito de compras activo con su estado. | H24: ='E-CarritoCompras'!G15 -> CAR-POL-09 | I24: ='E-CarritoCompras'!H15 -> El estado solo puede pasar a "Convertido" si el carrito tenía al menos un producto en su detalle. | J24: Generar excepción indicando que los parámetros de consulta tienen un formato incorrecto. | K24: Detener operación

Sheet E-CarritoCompras
A1: << Ir al modelo de dominio | E1: << Ir al listado de objetos de dominio | I1: << Ir a la caracterización del objeto de dominio
A2: Objeto de Dominio: | B2: =ListadoObjetosDominio!B10 -> CarritoCompras
A3: Descripción: | B3: =ListadoObjetosDominio!C10 -> Objeto de dominio que representa la sesión temporal donde un cliente agrupa los productos que tiene intención de adquirir antes de formalizar la transacción.
A4: Actor | B4: Action/Command | D4: Entity/Aggregate/Object domain | E4: Read Model | G4: Business Rule/Policy | I4: External System | J4: Domain Event | K4: Hotspot/questions/Risk
A5: Actor | B5: Acción | C5: Descripción | D5: Objeto de dominio | E5: Información externa | G5: Políticas | I5: Sistema Externo | J5: Evento | K5: Aspectos por solucionar
E6: Información | F6: Descripción | G6: Número | H6: Descripción
A7: Cliente | B7: Crear carrito | C7: Iniciar una nueva sesión de compras asignando un contenedor vacío al usuario. | D7: =ListadoObjetosDominio!B10 -> CarritoCompras | E7: idCliente, fechaCreacion | F7: Registro inicial del carrito asociado al perfil del comprador. | G7: CAR-POL-01 | H7: Asegurar que los datos requeridos sean válidos a nivel de tipo, formato, longitud y obligatoriedad. | I7: Motor de Caché | J7: Carrito creado | K7: Riesgo de "Carritos abandonados" (usuarios que crean el carrito pero nunca pagan), ocupando espacio inútil en la BD y que saturen la memoria si el cliente nunca agrega nada.
G8: CAR-POL-02 | H8: El idCliente asociado debe existir previamente en el sistema.
G9: CAR-POL-03 | H9: Un cliente solo puede tener un (1) carrito en estado "Activo" a la vez.
A10: Cliente | B10: Actualizar carrito (Añadir/Modificar) | C10: Recalcular el total del carrito cuando el usuario agrega nuevos productos o cambia cantidades. | D10: =ListadoObjetosDominio!B10 -> CarritoCompras | E10: idCarrito, total | F10: Formulario interno que ajusta el valor a pagar según los productos seleccionados. | G10: CAR-POL-04 | H10: El idCarrito a actualizar debe existir y pertenecer al cliente en sesión. | I10: Motor de Caché | J10: Carrito actualizado | K10: Dilema arquitectónico: ¿Se debe descontar (reservar) el stock del producto al meterlo al carrito, o solo al momento de pagar?
G11: CAR-POL-05 | H11: El nuevo total calculado no puede ser un valor negativo.
A12: Cliente | B12: Vaciar carrito | C12: Eliminar todos los artículos seleccionados y reiniciar el valor del carrito para empezar de cero. | D12: =ListadoObjetosDominio!B10 -> CarritoCompras | E12: idCarrito,estado | F12: Acción de limpieza del carrtio de compras. | G12: CAR-POL-06 | H12: El idCarrito a vaciar debe existir previamente en el sistema. | I12: Motor de Caché | J12: Carrito vaciado | K12: Si el cliente presiona "Vaciar" por error, no hay forma nativa de recuperar la lista de productos que ya había seleccionado.
G13: CAR-POL-07 | H13: El sistema solo puede vaciar el carrito si no ha sido transformado ya en un "Pedido" pagado.
A14: Cliente | B14: Consultar carrito | C14: Visualizar el resumen de la compra, incluyendo el monto total acumulado antes del checkout. | D14: =ListadoObjetosDominio!B10 -> CarritoCompras | E14: idCarrito, idCliente, fechaCreacion, total | F14: Vista desplegable lateral o página de "Mi Carrito" con el resumen financiero. | G14: CAR-POL-08 | H14: Asegurar que los datos requeridos sean válidos a nivel de tipo, formato, longitud y obligatoriedad. | I14: Motor de Caché | J14: Carrito consultado | K14: Si el administrador cambia el precio de un producto, ¿el total del carrito se actualiza automáticamente o se le respeta el precio viejo al cliente?
A15: Sistema | B15: Cambiar estado (Convertir a Pedido) | C15: Actualizar el carrito para indicar que ya fue pagado y cerrado exitosamente | D15: CarritoCompras | E15: idCarrito, estado | F15: Acción invisible al usuario, ocurre al finalizar el checkout. | G15: CAR-POL-09 | H15: El estado solo puede pasar a "Convertido" si el carrito tenía al menos un producto en su detalle. | J15: Carrito convertido exitosamente | K15: N/A

Sheet P-CarritoCompras
A1: << Ir al modelo de dominio | E1: << Ir al listado de objetos de dominio | I1: << Ir a la caracterización del objeto de dominio
A2: Objeto de Dominio: | B2: =ListadoObjetosDominio!B10 -> CarritoCompras
A3: Descripción: | B3: =ListadoObjetosDominio!C10 -> Objeto de dominio que representa la sesión temporal donde un cliente agrupa los productos que tiene intención de adquirir antes de formalizar la transacción.
A4: Business Rule/Policy
A5: Políticas
A6: Número | B6: Descripción
A7: CAR-POL-01 | B7: Asegurar que los datos requeridos sean válidos a nivel de tipo, formato, longitud y obligatoriedad.
A8: CAR-POL-02 | B8: El idCliente asociado debe existir previamente en el sistema.
A9: CAR-POL-03 | B9: Un cliente solo puede tener un (1) carrito en estado "Activo" a la vez.
A10: CAR-POL-04 | B10: El idCarrito a actualizar debe existir y pertenecer al cliente en sesión.
A11: CAR-POL-05 | B11: El nuevo total calculado no puede ser un valor negativo.
A12: CAR-POL-06 | B12: El idCarrito a vaciar debe existir previamente en el sistema.
A13: CAR-POL-07 | B13: El sistema solo puede vaciar el carrito si no ha sido transformado ya en un "Pedido" pagado.
A14: CAR-POL-08 | B14: Asegurar que los datos requeridos sean válidos a nivel de tipo, formato, longitud y obligatoriedad.
A15: CAR-POL-09 | B15: El estado solo puede pasar a "Convertido" si el carrito tenía al menos un producto en su detalle.

Sheet M-ItemCarrito
A1: << Ir al modelo de dominio | E1: << Ir al listado de objetos de dominio | G1: << Ir a la caracterización del objeto de dominio
A2: Nombre | B2: =ListadoObjetosDominio!B11 -> ItemCarrito
A3: Descripción | B3: =ListadoObjetosDominio!C11 -> Objeto de dominio que representa a cada una de las selecciones individuales (producto específico y cantidad) dentro del carrito activo de un cliente.
A4: Identificador único universal (UUID) del ítem del carrito. | B4: Referencia al carrito de compras al que pertenece el ítem. | C4: Referencia al producto agregado al carrito. | D4: Número de unidades del producto en el carrito. | E4: Precio unitario congelado del producto al momento de agregarlo. | F4: Subtotal del ítem (cantidad × precioUnitario). | G4: Indica que el sistema evita productos duplicados en el carrito agrupándolos: al agregar un producto que ya está presente, se incrementa su cantidad en lugar de crear una nueva línea.
A5: id | B5: carritoCompras | C5: producto | D5: cantidad | E5: precioUnitario | F5: subtotal | G5: Combinacion Unica 1
A6: 1C100000-AAAA-4BBB-8CCC-000000000001 | B6: CC000001-AAAA-4BBB-8CCC-DDDDEEEEFF01 | C6: 4F8A0001-2222-4333-8444-555566667701 | D6: 1 | E6: 89900 | F6: 89900 | G6: =C6 -> 4F8A0001-2222-4333-8444-555566667701
A7: 1C100000-AAAA-4BBB-8CCC-000000000002 | B7: CC000001-AAAA-4BBB-8CCC-DDDDEEEEFF02 | C7: 4F8A0001-2222-4333-8444-555566667702 | D7: 2 | E7: 145000 | F7: 290000 | G7: =C7 -> 4F8A0001-2222-4333-8444-555566667702
A8: 1C100000-AAAA-4BBB-8CCC-000000000003 | B8: CC000001-AAAA-4BBB-8CCC-DDDDEEEEFF03 | C8: 4F8A0001-2222-4333-8444-555566667703 | D8: 3 | E8: 35500 | F8: 106500 | G8: =C8 -> 4F8A0001-2222-4333-8444-555566667703
A9: 1C100000-AAAA-4BBB-8CCC-000000000004 | B9: CC000001-AAAA-4BBB-8CCC-DDDDEEEEFF04 | C9: 4F8A0001-2222-4333-8444-555566667705 | D9: 1 | E9: 189900 | F9: 189900 | G9: =C9 -> 4F8A0001-2222-4333-8444-555566667705
A10: 1C100000-AAAA-4BBB-8CCC-000000000005 | B10: CC000001-AAAA-4BBB-8CCC-DDDDEEEEFF05 | C10: 4F8A0001-2222-4333-8444-555566667701 | D10: 2 | E10: 89900 | F10: 179800 | G10: =C10 -> 4F8A0001-2222-4333-8444-555566667701
A13: Corresponde a los datos generales del objeto de dominio (nombre, descripción)
A14: Corresponde a las descripciones de los atributos
A15: Coresponde al nombre de los atributos
A16: Corresponde a los datos que son de libre ingreso
A17: Corresponde a los datos que se generarán automáticamente
A18: Corresponde a la combinación única 1
A19: Corresponde a referencias a otros objetos de dominio

Sheet C-ItemCarrito
A1: << Ir al modelo de dominio | D1: << Ir al listado de objetos de dominio | G1: << Ir a la caracterización del objeto de dominio
A2: Nombre | B2: ='M-ItemCarrito'!B2 -> ItemCarrito
A3: Descripción | B3: ='M-ItemCarrito'!B3 -> Objeto de dominio que representa a cada una de las selecciones individuales (producto específico y cantidad) dentro del carrito activo de un cliente.
A4: Nombre atributo | B4: Descripción atributo | C4: Identificador del objeto de dominio | D4: Tipo de dato | E4: Obligatorio | F4: Longitud minima(si aplica longitud maxima(si aplica) | G4: Longitud maxima(si aplica longitud maxima(si aplica) | H4: Precisión (si aplica) | I4: Redondeo(si aplica) | J4: Rango inicial(si aplica) | K4: Rango final (si aplica) | L4: Formato(Si aplica) | M4: Reglas especiales(si aplica) | N4: Dato calculado | O4: Aplica ajuste del dato(si aplica) | P4: Carácter de ajuste(si aplica) | Q4: Quitar espacios en blanco al inicio(si aplica) | R4: Quitar espacios en blanco al fin(si aplica) | S4: Dato sensible(si aplica) | T4: Valor por defecto(si aplica) | U4: Auto generado | V4: =#REF! -> #REF! | W4: =#REF! -> #REF! | X4: =#REF! -> #REF! | Y4: =#REF! -> #REF!
A5: ='M-ItemCarrito'!A5 -> id | B5: ='M-ItemCarrito'!A4 -> Identificador único universal (UUID) del ítem del carrito. | C5: Si | D5: Alfanumerico | E5: Si | F5: 1 | L5: Mayúsculas | N5: No | O5: No | Q5: Si | R5: Si | S5: No | U5: Si | V5: Requerido | W5: No requerido
A6: ='M-ItemCarrito'!B5 -> carritoCompras | B6: ='M-ItemCarrito'!B4 -> Referencia al carrito de compras al que pertenece el ítem. | C6: No | D6: <CarritoCompras> | E6: Si | M6: El carrito debe existir y estar en estado Activo | N6: No | S6: No | U6: No | V6: No requerido | W6: No requerido
A7: ='M-ItemCarrito'!C5 -> producto | B7: ='M-ItemCarrito'!C4 -> Referencia al producto agregado al carrito. | C7: No | D7: <Producto> | E7: Si | M7: El producto debe existir y estar Activo en el catálogo | N7: No | S7: No | U7: No | V7: Norequerido | W7: No requerido
A8: ='M-ItemCarrito'!D5 -> cantidad | B8: ='M-ItemCarrito'!D4 -> Número de unidades del producto en el carrito. | C8: No | D8: Numerico entero | E8: Si | J8: 1 | K8: 9999 | M8: No puede ser cero o negativa. Si el cliente pone cero, el ítem se elimina del carrito | N8: No | S8: No | T8: 1 | U8: No
A10: Nombre combinación unica | B10: Descripción | C10: Atributos involucrados
A11: ='M-ItemCarrito'!G5 -> Combinacion Unica 1 | B11: ='M-ItemCarrito'!G4 -> Indica que el sistema evita productos duplicados en el carrito agrupándolos: al agregar un producto que ya está presente, se incrementa su cantidad en lugar de crear una nueva línea. | C11: ='M-ItemCarrito'!B5 -> carritoCompras
C12: ='M-ItemCarrito'!C5 -> producto
A14: Responsabilidad | B14: Descripción | C14: Entradas | F14: Salida | H14: Políticas (Reglas de Negocio) | J14: Excepción
C15: Parámettro | D15: Tipo de dato | E15: Descripci | F15: Tipo de Dato | G15: Descripción | H15: Política | I15: Descripción | J15: Detalle | K15: ¿Qué hago?
A16: ='E-ItemCarrito'!B7 -> Agregar producto al carrito | B16: ='E-ItemCarrito'!C7 -> Insertar un producto específico con su cantidad y precio en el carrito de compras activo. | C16: itemNuevo | D16: ItemCarrito | E16: Contiene la información del producto y la cantidad a agregar. | F16: Logico | G16: Retorna verdadero si el producto se agregó exitosamente. | H16: ='E-ItemCarrito'!G7 -> ITC-POL-01 | I16: ='E-ItemCarrito'!H7 -> Asegurar que los datos requeridos sean válidos a nivel de tipo, formato, longitud y obligatoriedad. | J16: Generar excepción indicando qué campo no cumple con el formato o es obligatorio. | K16: Detener operación
H17: ='E-ItemCarrito'!G8 -> ITC-POL-02 | I17: ='E-ItemCarrito'!H8 -> El idCarrito y el idProducto deben existir; la integridad se garantiza por las llaves foráneas de la base de datos | J17: Generar excepción indicando que el carrito o el producto no se encuentran registrados. | K17: Detener operación
H18: ='E-ItemCarrito'!G9 -> ITC-POL-03 | I18: ='E-ItemCarrito'!H9 -> La cantidad ingresada debe ser estrictamente mayor a cero (0). | J18: Generar excepción indicando que la cantidad a agregar debe ser al menos 1. | K18: Detener operación
A19: ='E-ItemCarrito'!B10 -> Modificar cantidad del item | B19: ='E-ItemCarrito'!C10 -> Aumentar o disminuir las unidades de un producto que ya se encuentra dentro del carrito. | C19: itemModificado | D19: ItemCarrito | E19: Contiene el identificador del ítem y la nueva cantidad deseada. | F19: Logico | G19: Retorna verdadero si la cantidad se actualizó correctamente. | H19: ='E-ItemCarrito'!G10 -> ITC-POL-04 | I19: ='E-ItemCarrito'!H10 -> El idItem a modificar debe existir previamente en el sistema | J19: Generar excepción indicando que el ítem a modificar no existe en el carrito actual. | K19: Detener operación
H20: ='E-ItemCarrito'!G11 -> 0 | I20: ='E-ItemCarrito'!H11 -> 0 | J20: Generar excepción o notificación (si aplica) indicando que el producto fue removido por cantidad cero. | K20: Detener operación
A21: ='E-ItemCarrito'!B12 -> Eliminar producto del carrito | B21: ='E-ItemCarrito'!C12 -> Retirar por completo una línea de producto del carrito de compras. | C21: idItemCarrito | D21: alfanumerico | E21: Identificador exacto del ítem que se desea borrar del carrito. | F21: Logico | G21: Retorna verdadero si el ítem fue eliminado correctamente de la cesta. | H21: ='E-ItemCarrito'!G12 -> ITC-POL-05 | I21: ='E-ItemCarrito'!H12 -> El idItem a eliminar debe existir previamente en el sistema | J21: Generar excepción indicando que el ítem a eliminar ya no se encuentra en el carrito. | K21: Detener operación
A22: ='E-ItemCarrito'!#REF! -> #REF! | B22: ='E-ItemCarrito'!#REF! -> #REF! | C22: idCarrito | D22: alfanumerico | E22: Identificador del carrito del cual se quieren obtener los ítems. | F22: Lista<ItemCarrito> | G22: Retorna una colección con los objetos de los ítems encontrados. | H22: ='E-ItemCarrito'!#REF! -> #REF! | I22: ='E-ItemCarrito'!#REF! -> #REF! | J22: Generar excepción indicando acceso denegado por intentar consultar un carrito ajeno. | K22: Detener operación

Sheet E-ItemCarrito
A1: << Ir al modelo de dominio | E1: << Ir al listado de objetos de dominio | I1: << Ir a la caracterización del objeto de dominio
A2: Objeto de Dominio: | B2: =ListadoObjetosDominio!B11 -> ItemCarrito
A3: Descripción: | B3: =ListadoObjetosDominio!C11 -> Objeto de dominio que representa a cada una de las selecciones individuales (producto específico y cantidad) dentro del carrito activo de un cliente.
A4: Actor | B4: Action/Command | D4: Entity/Aggregate/Object domain | E4: Read Model | G4: Business Rule/Policy | I4: External System | J4: Domain Event | K4: Hotspot/questions/Risk
A5: Actor | B5: Acción | C5: Descripción | D5: Objeto de dominio | E5: Información externa | G5: Políticas | I5: Sistema Externo | J5: Evento | K5: Aspectos por solucionar
E6: Información | F6: Descripción | G6: Número | H6: Descripción
A7: Cliente | B7: Agregar producto al carrito | C7: Insertar un producto específico con su cantidad y precio en el carrito de compras activo. | D7: =ListadoObjetosDominio!B11 -> ItemCarrito | E7: Idcarrito, idProducto, cantidad | F7: Detalle del producto a añadir, especificando cuántas unidades y su costo. | G7: ITC-POL-01 | H7: Asegurar que los datos requeridos sean válidos a nivel de tipo, formato, longitud y obligatoriedad. | I7: Motor de Caché | J7: Producto agregado al carrito | K7: Si dos clientes agregan la última unidad de un producto a sus carritos al mismo tiempo, ¿a quién se le respeta la compra en el checkout?
G8: ITC-POL-02 | H8: El idCarrito y el idProducto deben existir; la integridad se garantiza por las llaves foráneas de la base de datos
G9: ITC-POL-03 | H9: La cantidad ingresada debe ser estrictamente mayor a cero (0).
A10: Cliente | B10: Modificar cantidad del item | C10: Aumentar o disminuir las unidades de un producto que ya se encuentra dentro del carrito. | D10: =ListadoObjetosDominio!B11 -> ItemCarrito | E10: idItemCarrito, Idcarrito, idProducto, cantidad | F10: Interfaz con botones de (+) y (-) para ajustar las unidades y recalcular el subtotal. | G10: ITC-POL-04 | H10: El idItem a modificar debe existir previamente en el sistema | I10: Motor de Caché | J10: Cantidad de item modificada | K10: Riesgo de inconsistencia si el cliente en múltiples pestañas del navegador modifica las cantidades al mismo tiempo.
A12: Cliente | B12: Eliminar producto del carrito | C12: Retirar por completo una línea de producto del carrito de compras. | D12: =ListadoObjetosDominio!B11 -> ItemCarrito | E12: idItem | F12: Botón de "basurero" o "eliminar" junto al producto en el resumen de la compra. | G12: ITC-POL-05 | H12: El idItem a eliminar debe existir previamente en el sistema | I12: Base de datos | J12: Producto eliminado del carrito | K12: Si se elimina el último y único item que había, ¿el sistema debería eliminar automáticamente también la cabecera (CarritoCompras) o dejarla vacía?

Sheet P-ItemCarrito
A1: << Ir al modelo de dominio | E1: << Ir al listado de objetos de dominio | I1: << Ir a la caracterización del objeto de dominio
A2: Objeto de Dominio: | B2: =ListadoObjetosDominio!B11 -> ItemCarrito
A3: Descripción: | B3: =ListadoObjetosDominio!C11 -> Objeto de dominio que representa a cada una de las selecciones individuales (producto específico y cantidad) dentro del carrito activo de un cliente.
A4: Business Rule/Policy
A5: Políticas
A6: Número | B6: Descripción
A7: ITC-POL-01 | B7: Asegurar que los datos requeridos sean válidos a nivel de tipo, formato, longitud y obligatoriedad.
A8: ITC-POL-02 | B8: El idCarrito y el idProducto deben existir; la integridad se garantiza por las llaves foráneas de la base de datos
A9: ITC-POL-03 | B9: La cantidad ingresada debe ser estrictamente mayor a cero (0).
A10: ITC-POL-04 | B10: El idItem a modificar debe existir previamente en el sistema
A12: ITC-POL-05 | B12: El idItem a eliminar debe existir previamente en el sistema

Sheet M-Pedido
A1: << Ir al modelo de dominio | F1: << Ir al listado de objetos de dominio | H1: << Ir a la caracterización del objeto de dominio
A2: Nombre | B2: =ListadoObjetosDominio!B12 -> Pedido
A3: Descripción | B3: =ListadoObjetosDominio!C10 -> Objeto de dominio que representa la sesión temporal donde un cliente agrupa los productos que tiene intención de adquirir antes de formalizar la transacción.
A4: Identificador único universal (UUID) del pedido. | B4: Referencia al cliente que realizó el pedido. | C4: Fecha en que se generó el pedido (LocalDate). | D4: Valor total del pedido en pesos colombianos (COP). | E4: Estado del pedido (PENDIENTE, CONFIRMADO, PREPARANDO, ENVIADO, ENTREGADO, CANCELADO). | F4: Indica que el número de pedido es un comprobante único en todo el sistema
A5: id | B5: cliente | C5: fechaPedido | D5: total | E5: estado | F5: CombinaciónUnica1
A6: PED12345-A1B2-4C3D-8E4F-000000000001 | B6: 3F2504E0-4F89-11D3-9A0C-0305E82C3301 | C6: 2026-05-15 | D6: 89900 | E6: PENDIENTE | F6: =A6 -> PED12345-A1B2-4C3D-8E4F-000000000001
A7: PED12345-A1B2-4C3D-8E4F-000000000002 | B7: 3F2504E0-4F89-11D3-9A0C-0305E82C3302 | C7: 2026-05-16 | D7: 290000 | E7: CONFIRMADO | F7: =A7 -> PED12345-A1B2-4C3D-8E4F-000000000002
A8: PED12345-A1B2-4C3D-8E4F-000000000003 | B8: 3F2504E0-4F89-11D3-9A0C-0305E82C3303 | C8: 2026-05-17 | D8: 106500 | E8: PREPARANDO | F8: =A8 -> PED12345-A1B2-4C3D-8E4F-000000000003
A9: PED12345-A1B2-4C3D-8E4F-000000000004 | B9: 3F2504E0-4F89-11D3-9A0C-0305E82C3304 | C9: 2026-05-18 | D9: 189900 | E9: ENVIADO | F9: =A9 -> PED12345-A1B2-4C3D-8E4F-000000000004
A10: PED12345-A1B2-4C3D-8E4F-000000000005 | B10: 3F2504E0-4F89-11D3-9A0C-0305E82C3305 | C10: 2026-05-19 | D10: 179800 | E10: ENTREGADO | F10: =A10 -> PED12345-A1B2-4C3D-8E4F-000000000005
A13: Corresponde a los datos generales del objeto de dominio (nombre, descripción)
A14: Corresponde a las descripciones de los atributos
A15: Coresponde al nombre de los atributos
A16: Corresponde a los datos que son de libre ingreso
A17: Corresponde a los datos que se generarán automáticamente
A18: Corresponde a la combinación única 1
A19: Corresponde a referencias a otros objetos de dominio

Sheet C-Pedido
A1: << Ir al modelo de dominio | D1: << Ir al listado de objetos de dominio | G1: << Ir a la caracterización del objeto de dominio
A2: Nombre | B2: ='M-Pedido'!B2 -> Pedido
A3: Descripción | B3: ='M-Pedido'!B3 -> Objeto de dominio que representa la sesión temporal donde un cliente agrupa los productos que tiene intención de adquirir antes de formalizar la transacción.
A4: Nombre atributo | B4: Descripción atributo | C4: Identificador del objeto de dominio | D4: Tipo de dato | E4: Obligatorio | F4: Longitud minima(si aplica longitud maxima(si aplica) | G4: Longitud maxima(si aplica longitud maxima(si aplica) | H4: Precisión (si aplica) | I4: Redondeo(si aplica) | J4: Rango inicial(si aplica) | K4: Rango final (si aplica) | L4: Formato(Si aplica) | M4: Reglas especiales(si aplica) | N4: Dato calculado | O4: Aplica ajuste del dato(si aplica) | P4: Carácter de ajuste(si aplica) | Q4: Quitar espacios en blanco al inicio(si aplica) | R4: Quitar espacios en blanco al fin(si aplica) | S4: Dato sensible(si aplica) | T4: Valor por defecto(si aplica) | U4: Auto generado | V4: =A18 -> Crear pedido (Checkout) | W4: =A20 -> Actualizar estado del pedido | X4: =A22 -> Cancelar pedido | Y4: =A24 -> Consultar pedidos (Tracking)
A5: ='M-Pedido'!A5 -> id | B5: ='M-Pedido'!A4 -> Identificador único universal (UUID) del pedido. | C5: Si | D5: Alfanumerico | E5: Si | F5: 1 | L5: Mayusculas | M5: El formato suele incluir año y prefijo (Ej: PED-2026-001) | N5: No | O5: No | Q5: Si | R5: Si | S5: No | U5: Si | V5: Requerido | W5: No requerido
A6: ='M-Pedido'!B5 -> cliente | B6: ='M-Pedido'!B4 -> Referencia al cliente que realizó el pedido. | C6: No | D6: <Cliente> | E6: Si | M6: El cliente debe existir y estar activo en el sistema | N6: No | S6: No | U6: No | V6: No requerido | W6: No requerido
A7: ='M-Pedido'!C5 -> fechaPedido | B7: ='M-Pedido'!C4 -> Fecha en que se generó el pedido (LocalDate). | C7: No | D7: Fecha | E7: Si | M7: La dirección de entrega debe pertenecer al cliente que realiza el pedido | N7: No | S7: No | U7: No | V7: Norequerido | W7: No requerido
A8: ='M-Pedido'!D5 -> total | B8: ='M-Pedido'!D4 -> Valor total del pedido en pesos colombianos (COP). | C8: No | D8: Numerico decimal | E8: Si | M8: Se captura el momento exacto en el que el cliente confirma la compra | N8: No | S8: No | U8: Si
A9: ='M-Pedido'!E5 -> estado | B9: ='M-Pedido'!E4 -> Estado del pedido (PENDIENTE, CONFIRMADO, PREPARANDO, ENVIADO, ENTREGADO, CANCELADO). | C9: No | D9: Texto | E9: Si | F9: 6 | G9: 50 | L9: Capitalizado | M9: Solo permite valores del flujo (PendientePago, Pagado, Despachado, Entregado) | N9: No | O9: No | Q9: Si | R9: Si | S9: No | T9: PendientePago | U9: No
A10: ='M-Pedido'!#REF! -> #REF! | B10: ='M-Pedido'!#REF! -> #REF! | C10: No | D10: Numerico decimal | E10: Si | H10: 2 | I10: Truncamiento | J10: 1 | K10: 999999 | M10: Debe ser la sumatoria exacta de los precios congelados en las líneas del pedido | N10: Si | S10: No | U10: Si
A12: Nombre combinación unica | B12: Descripción | C12: Atributos involucrados
A13: ='M-Pedido'!F5 -> CombinaciónUnica1 | B13: ='M-Pedido'!F4 -> Indica que el número de pedido es un comprobante único en todo el sistema | C13: ='M-Pedido'!A5 -> id
A16: Responsabilidad | B16: Descripción | C16: Entradas | F16: Salida | H16: Políticas (Reglas de Negocio) | J16: Excepción
C17: Parámettro | D17: Tipo de dato | E17: Descripci | F17: Tipo de Dato | G17: Descripción | H17: Política | I17: Descripción | J17: Detalle | K17: ¿Qué hago?
A18: ='E-Pedido'!B7 -> Crear pedido (Checkout) | B18: ='E-Pedido'!C7 -> El usuario finaliza su compra, procesa el pago y genera la orden de despacho | C18: pedidoNuevo | D18: Pedido | E18: Contiene la información base del nuevo pedido a registrar. | F18: Logico | G18: Retorna verdadero si el pedido se creó exitosamente. | H18: ='E-Pedido'!G7 -> PED-POL-01 | I18: ='E-Pedido'!H7 -> Asegurar que los datos requeridos sean válidos a nivel de tipo, formato, longitud y obligatoriedad. | J18: Generar excepción indicando qué campo no cumple con el formato o es obligatorio. | K18: Detener operación
H19: ='E-Pedido'!G8 -> PED-POL-02 | I19: ='E-Pedido'!H8 -> El total del pedido no puede ser negativo | J19: Generar excepción indicando que el carrito no es válido o está vacío. | K19: Detener operación
A20: ='E-Pedido'!B9 -> Actualizar estado del pedido | B20: ='E-Pedido'!C9 -> Cambiar la fase en la que se encuentra la orden (ej. de "Pagado" a "Enviado" o "Entregado") para el seguimiento logístico. | C20: pedidoModificado | D20: Pedido | E20: Contiene la información del pedido con el nuevo estado actualizado. | F20: Logico | G20: Retorna verdadero si el estado del pedido se actualizó correctamente. | H20: ='E-Pedido'!G9 -> PED-POL-03 | I20: ='E-Pedido'!H9 -> El idPedido a modificar debe existir previamente en el sistema. | J20: Generar excepción indicando que el pedido a actualizar no existe en la base de datos. | K20: Detener operación
H21: ='E-Pedido'!G10 -> PED-POL-04 | I21: ='E-Pedido'!H10 -> El estado del pedido debe ser uno de los valores válidos (Pendiente, Confirmado, Preparando, Enviado, Entregado, Cancelado) y solo avanza en orden, un paso a la vez: Pendiente → Confirmado → Preparando → Enviado → Entregado, sin retroceder. Solo se puede cancelar si está Pendiente o Confirmado. El administrador puede actualizar el estado del pedido. | J21: Generar excepción indicando que el cambio de estado no es válido porque salta un paso, va en reversa o el pedido ya no se puede cancelar. | K21: Detener operación
A22: ='E-Pedido'!B11 -> Cancelar pedido | B22: ='E-Pedido'!C11 -> Anular la compra antes de que el pedido entre en preparación, procesando un reembolso. | C22: idPedido | D22: alfanumerico | E22: Identificador exacto del pedido que el cliente o administrador desea cancelar. | F22: Logico | G22: Retorna verdadero si el pedido fue cancelado exitosamente. | H22: ='E-Pedido'!G11 -> PED-POL-05 | I22: ='E-Pedido'!H11 -> El idPedido a eliminar debe existir previamente en el sistema. | J22: Generar excepción indicando que el pedido a cancelar no se encuentra registrado. | K22: Detener operación
H23: ='E-Pedido'!G10 -> PED-POL-04 | I23: =I21 -> El estado del pedido debe ser uno de los valores válidos (Pendiente, Confirmado, Preparando, Enviado, Entregado, Cancelado) y solo avanza en orden, un paso a la vez: Pendiente → Confirmado → Preparando → Enviado → Entregado, sin retroceder. Solo se puede cancelar si está Pendiente o Confirmado. El administrador puede actualizar el estado del pedido. | J23: Generar excepción indicando que el pedido solo se puede cancelar si está Pendiente o Confirmado. | K23: Detener operación
A24: ='E-Pedido'!B13 -> Consultar pedidos (Tracking) | B24: ='E-Pedido'!C13 -> Listar las órdenes realizadas en el pasado para revisar garantías, volver a comprar o hacer auditoría. | C24: filtros | D24: Texto | E24: Parámetros opcionales para filtrar o buscar el historial de pedidos. | F24: Lista<Pedido> | G24: Retorna una colección con los objetos de los pedidos encontrados. | H24: ='E-Pedido'!G13 -> PED-POL-06 | I24: ='E-Pedido'!H13 -> El cliente solo puede ver sus propios pedidos; el administrador tiene acceso al historial global. | J24: Generar excepción indicando acceso denegado por intentar visualizar pedidos de otro usuario. | K24: Detener operación

Sheet E-Pedido
A1: << Ir al modelo de dominio | E1: << Ir al listado de objetos de dominio | I1: << Ir a la caracterización del objeto de dominio
A2: Objeto de Dominio: | B2: =ListadoObjetosDominio!B12 -> Pedido
A3: Descripción: | B3: =ListadoObjetosDominio!C12 -> Objeto de dominio que representa la confirmación formal, transaccional y definitiva de una compra realizada por un cliente en Imexcol.
A4: Actor | B4: Action/Command | D4: Entity/Aggregate/Object domain | E4: Read Model | G4: Business Rule/Policy | I4: External System | J4: Domain Event | K4: Hotspot/questions/Risk
A5: Actor | B5: Acción | C5: Descripción | D5: Objeto de dominio | E5: Información externa | G5: Políticas | I5: Sistema Externo | J5: Evento | K5: Aspectos por solucionar
E6: Información | F6: Descripción | G6: Número | H6: Descripción
A7: Cliente | B7: Crear pedido (Checkout) | C7: El usuario finaliza su compra, procesa el pago y genera la orden de despacho | D7: =ListadoObjetosDominio!B12 -> Pedido | E7: idCarrito, idcliente, idDireccion, fechaCreacion, totalCompra | F7: Pantalla final de pago (Checkout) con el resumen monetario y destino de entrega. | G7: PED-POL-01 | H7: Asegurar que los datos requeridos sean válidos a nivel de tipo, formato, longitud y obligatoriedad. | I7: Pasarela de pagos | J7: Pedido generado | K7: Riesgo de "Timeout" (tiempo de espera agotado) si la pasarela de pagos externa tarda mucho en responder y el usuario recarga la página.
G8: PED-POL-02 | H8: El total del pedido no puede ser negativo
A9: Administrador / Sistema | B9: Actualizar estado del pedido | C9: Cambiar la fase en la que se encuentra la orden (ej. de "Pagado" a "Enviado" o "Entregado") para el seguimiento logístico. | D9: =ListadoObjetosDominio!B12 -> Pedido | E9: idPedido, estadoLogsitico | F9: Panel de control de despachos o actualización automática vía Webhook de la transportadora. | G9: PED-POL-03 | H9: El idPedido a modificar debe existir previamente en el sistema. | I9: API Transportadora (Servientrega / Coordinadora) | J9: Estado logístico de pedido actualizado | K9: Si se marca como "Entregado" por error, el cliente no podrá abrir reclamos fácilmente si su paquete nunca llegó.
G10: PED-POL-04 | H10: El estado del pedido debe ser uno de los valores válidos (Pendiente, Confirmado, Preparando, Enviado, Entregado, Cancelado) y solo avanza en orden, un paso a la vez: Pendiente → Confirmado → Preparando → Enviado → Entregado, sin retroceder. Solo se puede cancelar si está Pendiente o Confirmado. El administrador puede actualizar el estado del pedido.
A11: Cliente / Administrador | B11: Cancelar pedido | C11: Anular la compra antes de que el pedido entre en preparación, procesando un reembolso. | D11: =ListadoObjetosDominio!B12 -> Pedido | E11: idPedido, estadoLogsitico | F11: Botón de "Cancelar compra" en el historial de pedidos o en el panel de soporte. | G11: PED-POL-05 | H11: El idPedido a eliminar debe existir previamente en el sistema. | I11: Pasarela de Pagos (API de Reembolsos) | J11: Pedido cancelado | K11: Mitigado: el sistema solo permite cancelar pedidos en estado Pendiente o Confirmado, antes de su preparación.
A13: Cliente / Administrador | B13: Consultar pedidos (Tracking) | C13: Listar las órdenes realizadas en el pasado para revisar garantías, volver a comprar o hacer auditoría. | D13: =ListadoObjetosDominio!B12 -> Pedido | E13: idPedido, idCarrito, idcliente, idDireccion, fechacreacion, estadoLogsitico, totalCompra | F13: Vista de "Mis Pedidos" en el perfil del cliente o general de ventas para el administrador. | G13: PED-POL-06 | H13: El cliente solo puede ver sus propios pedidos; el administrador tiene acceso al historial global. | I13: Base de datos | J13: Pedidos consultados | K13: N/A

Sheet P-Pedido
A1: << Ir al modelo de dominio | E1: << Ir al listado de objetos de dominio | I1: << Ir a la caracterización del objeto de dominio
A2: Objeto de Dominio: | B2: =ListadoObjetosDominio!B12 -> Pedido
A3: Descripción: | B3: =ListadoObjetosDominio!C12 -> Objeto de dominio que representa la confirmación formal, transaccional y definitiva de una compra realizada por un cliente en Imexcol.
A4: Business Rule/Policy
A5: Políticas
A6: Número | B6: Descripción
A7: PED-POL-01 | B7: Asegurar que los datos requeridos sean válidos a nivel de tipo, formato, longitud y obligatoriedad.
A8: PED-POL-02 | B8: El total del pedido no puede ser negativo
A9: PED-POL-03 | B9: El idPedido a modificar debe existir previamente en el sistema.
A10: PED-POL-04 | B10: El estado del pedido debe ser uno de los valores válidos (Pendiente, Confirmado, Preparando, Enviado, Entregado, Cancelado) y solo avanza en orden, un paso a la vez: Pendiente → Confirmado → Preparando → Enviado → Entregado, sin retroceder. Solo se puede cancelar si está Pendiente o Confirmado. El administrador puede actualizar el estado del pedido.
A11: PED-POL-05 | B11: El idPedido a eliminar debe existir previamente en el sistema.
A13: PED-POL-06 | B13: El cliente solo puede ver sus propios pedidos; el administrador tiene acceso al historial global.

Sheet M-LineaPedido
A1: << Ir al modelo de dominio | G1: << Ir al listado de objetos de dominio | I1: << Ir a la caracterización del objeto de dominio
A2: Nombre | B2: =ListadoObjetosDominio!B13 -> LineaPedido
A3: Descripción | B3: =ListadoObjetosDominio!C13 -> Objeto de dominio que representa el detalle individual de un pedido, permitiendo registrar de forma histórica cada producto adquirido, su cantidad y su valor al momento de confirmar la compra. (Evidencia histórica de la compra)
A4: Identificador único universal (UUID) de la línea de pedido. | B4: Referencia al pedido al que pertenece esta línea. | C4: Referencia al producto incluido en esta línea. | D4: Número de unidades del producto en la línea. | E4: Precio unitario congelado del producto al momento del pedido. | F4: Subtotal de la línea (cantidad × precioUnitario). | G4: Indica que un cliente no puede tener más de un carrito “Activo” simultáneamente
A5: id | B5: pedido | C5: producto | D5: cantidad | E5: precioUnitario | F5: subtotal | G5: CombinacionUnica1
A6: LP000000-1111-4222-8333-000000000001 | B6: PED12345-A1B2-4C3D-8E4F-000000000001 | C6: 4F8A0001-2222-4333-8444-555566667701 | D6: 1 | E6: 89900 | F6: 89900 | G6: =B6 -> PED12345-A1B2-4C3D-8E4F-000000000001
A7: LP000000-1111-4222-8333-000000000002 | B7: PED12345-A1B2-4C3D-8E4F-000000000002 | C7: 4F8A0001-2222-4333-8444-555566667702 | D7: 2 | E7: 145000 | F7: 290000 | G7: =B7 -> PED12345-A1B2-4C3D-8E4F-000000000002
A8: LP000000-1111-4222-8333-000000000003 | B8: PED12345-A1B2-4C3D-8E4F-000000000003 | C8: 4F8A0001-2222-4333-8444-555566667703 | D8: 3 | E8: 35500 | F8: 106500 | G8: =B8 -> PED12345-A1B2-4C3D-8E4F-000000000003
A9: LP000000-1111-4222-8333-000000000004 | B9: PED12345-A1B2-4C3D-8E4F-000000000004 | C9: 4F8A0001-2222-4333-8444-555566667705 | D9: 1 | E9: 189900 | F9: 189900 | G9: =B9 -> PED12345-A1B2-4C3D-8E4F-000000000004
A10: LP000000-1111-4222-8333-000000000005 | B10: PED12345-A1B2-4C3D-8E4F-000000000005 | C10: 4F8A0001-2222-4333-8444-555566667701 | D10: 2 | E10: 89900 | F10: 179800 | G10: =B10 -> PED12345-A1B2-4C3D-8E4F-000000000005
A13: Corresponde a los datos generales del objeto de dominio (nombre, descripción)
A14: Corresponde a las descripciones de los atributos
A15: Coresponde al nombre de los atributos
A16: Corresponde a los datos que son de libre ingreso
A17: Corresponde a los datos que se generarán automáticamente
A18: Corresponde a la combinación única 1
A19: Corresponde a referencias a otros objetos de dominio

Sheet C-LineaPedido
A1: << Ir al modelo de dominio | D1: << Ir al listado de objetos de dominio | G1: << Ir a la caracterización del objeto de dominio
A2: Nombre | B2: ='M-LineaPedido'!B2 -> LineaPedido
A3: Descripción | B3: ='M-LineaPedido'!B3 -> Objeto de dominio que representa el detalle individual de un pedido, permitiendo registrar de forma histórica cada producto adquirido, su cantidad y su valor al momento de confirmar la compra. (Evidencia histórica de la compra)
A4: Nombre atributo | B4: Descripción atributo | C4: Identificador del objeto de dominio | D4: Tipo de dato | E4: Obligatorio | F4: Longitud minima(si aplica longitud maxima(si aplica) | G4: Longitud maxima(si aplica longitud maxima(si aplica) | H4: Precisión (si aplica) | I4: Redondeo(si aplica) | J4: Rango inicial(si aplica) | K4: Rango final (si aplica) | L4: Formato(Si aplica) | M4: Reglas especiales(si aplica) | N4: Dato calculado | O4: Aplica ajuste del dato(si aplica) | P4: Carácter de ajuste(si aplica) | Q4: Quitar espacios en blanco al inicio(si aplica) | R4: Quitar espacios en blanco al fin(si aplica) | S4: Dato sensible(si aplica) | T4: Valor por defecto(si aplica) | U4: Auto generado | V4: =#REF! -> #REF! | W4: =#REF! -> #REF! | X4: =#REF! -> #REF! | Y4: =#REF! -> #REF!
A5: ='M-LineaPedido'!A5 -> id | B5: ='M-LineaPedido'!A4 -> Identificador único universal (UUID) de la línea de pedido. | C5: Si | D5: Alfanumerico | E5: Si | F5: 1 | L5: Mayusculas | N5: No | O5: No | Q5: Si | R5: Si | S5: No | U5: Si | V5: Requerido | W5: No requerido
A6: ='M-LineaPedido'!B5 -> pedido | B6: ='M-LineaPedido'!B4 -> Referencia al pedido al que pertenece esta línea. | C6: No | D6: <Pedido> | E6: Si | M6: El pedido maestro debe existir y estar en proceso | N6: No | S6: No | U6: No | V6: No requerido | W6: No requerido
A7: ='M-LineaPedido'!C5 -> producto | B7: ='M-LineaPedido'!C4 -> Referencia al producto incluido en esta línea. | C7: No | D7: <Producto> | E7: Si | M7: El producto debe estar Activo en el momento de crear la línea | N7: No | S7: No | U7: No | V7: Norequerido | W7: No requerido
A8: ='M-LineaPedido'!D5 -> cantidad | B8: ='M-LineaPedido'!D4 -> Número de unidades del producto en la línea. | C8: No | D8: Numerico entero | E8: Si | J8: 1 | K8: 9999 | M8: La cantidad comprada debe ser mayor a cero | N8: No | S8: No | T8: 1 | U8: No
A9: ='M-LineaPedido'!E5 -> precioUnitario | B9: ='M-LineaPedido'!E4 -> Precio unitario congelado del producto al momento del pedido. | C9: No | D9: Numerico decimal | E9: Si | H9: 2 | I9: Truncamiento | J9: 1 | K9: 99999 | M9: Se captura el precio actual del catálogo en el instante de la venta. Este valor se vuelve inmutable. | N9: No | S9: No | U9: Si
A11: Nombre combinación unica | B11: Descripción | C11: Atributos involucrados
A12: ='M-LineaPedido'!F5 -> subtotal | B12: ='M-LineaPedido'!F4 -> Subtotal de la línea (cantidad × precioUnitario). | C12: ='M-LineaPedido'!B5 -> pedido
C13: ='M-LineaPedido'!C5 -> producto
A15: Responsabilidad | B15: Descripción | C15: Entradas | F15: Salida | H15: Políticas (Reglas de Negocio) | J15: Excepción
C16: Parámettro | D16: Tipo de dato | E16: Descripci | F16: Tipo de Dato | G16: Descripción | H16: Política | I16: Descripción | J16: Detalle | K16: ¿Qué hago?
A17: ='E-LineaPedido'!B7 -> Registrar línea de pedido | B17: ='E-LineaPedido'!C7 -> Guardar el registro inmutable de un producto comprado, congelando su precio y cantidad exactos al momento del pago. | C17: lineaNueva | D17: LineaPedido | E17: Contiene la información de la línea de pedido que se va a registrar. | F17: Logico | G17: Retorna verdadero si la línea de pedido se registró correctamente. | H17: ='E-LineaPedido'!G7 -> LIN-POL-01 | I17: ='E-LineaPedido'!H7 -> Asegurar que los datos requeridos sean válidos a nivel de tipo, formato, longitud y obligatoriedad. | J17: Generar excepción indicando qué campo no cumple con el formato o es obligatorio. | K17: Detener operación
H18: ='E-LineaPedido'!G8 -> LIN-POL-02 | I18: ='E-LineaPedido'!H8 -> El idProducto debe existir en el catálogo, pero su estado actual no importa (incluso si fue inactivado después de la compra). | J18: Generar excepción indicando que el producto a registrar no existe en el histórico del catálogo. | K18: Detener operación
H19: ='E-LineaPedido'!G9 -> LIN-POL-03 | I19: ='E-LineaPedido'!H9 -> El precioCongelado debe ser una copia exacta del precio que tenía el producto al momento de la compra, asegurando inmutabilidad. | J19: Generar excepción indicando que el valor del precio congelado es inconsistente con el catálogo. | K19: Detener operación
A20: ='E-LineaPedido'!B10 -> Devolver / Cancelar línea (Reembolso parcial) | B20: ='E-LineaPedido'!C10 -> Anular un ítem específico del pedido porque llegó defectuoso o el cliente pidió garantía, sin cancelar todo el pedido. | C20: idLineaPedido | D20: alfanumerico | E20: Identificador exacto de la línea de pedido que se desea devolver o anular. | F20: Logico | G20: Retorna verdadero si la línea de pedido se devolvió o canceló exitosamente. | H20: ='E-LineaPedido'!G10 -> LIN-POL-04 | I20: ='E-LineaPedido'!H10 -> Solo se puede devolver una línea si el pedido padre (idPedido) está en estado "Entregado" o "Completado". | J20: Generar excepción indicando que el pedido padre aún no ha sido entregado o no es válido para devoluciones. | K20: Detener operación
A21: ='E-LineaPedido'!B11 -> Consultar detalle de pedido | B21: ='E-LineaPedido'!C11 -> Listar los productos exactos, cantidades y precios que el cliente compró dentro de un pedido específico. | C21: idPedido | D21: alfanumerico | E21: Identificador del pedido padre del cual se quieren obtener sus líneas de detalle. | F21: Lista<LineaPedido> | G21: Retorna una colección con los objetos de las líneas de pedido encontradas. | H21: ='E-LineaPedido'!G11 -> LIN-POL-05 | I21: ='E-LineaPedido'!H11 -> El cliente solo puede consultar las líneas de pedido que pertenezcan a un idPedido asociado a su cuenta. | J21: Generar excepción indicando acceso denegado por intentar visualizar el detalle de un pedido ajeno. | K21: Detener operación

Sheet E-LineaPedido
A1: << Ir al modelo de dominio | E1: << Ir al listado de objetos de dominio | I1: << Ir a la caracterización del objeto de dominio
A2: Objeto de Dominio: | B2: =ListadoObjetosDominio!B13 -> LineaPedido
A3: Descripción: | B3: =ListadoObjetosDominio!C13 -> Objeto de dominio que representa el detalle individual de un pedido, permitiendo registrar de forma histórica cada producto adquirido, su cantidad y su valor al momento de confirmar la compra. (Evidencia histórica de la compra)
A4: Actor | B4: Action/Command | D4: Entity/Aggregate/Object domain | E4: Read Model | G4: Business Rule/Policy | I4: External System | J4: Domain Event | K4: Hotspot/questions/Risk
A5: Actor | B5: Acción | C5: Descripción | D5: Objeto de dominio | E5: Información externa | G5: Políticas | I5: Sistema Externo | J5: Evento | K5: Aspectos por solucionar
E6: Información | F6: Descripción | G6: Número | H6: Descripción
A7: Sistema | B7: Registrar línea de pedido | C7: Guardar el registro inmutable de un producto comprado, congelando su precio y cantidad exactos al momento del pago. | D7: =ListadoObjetosDominio!B13 -> LineaPedido | E7: idPedido, idProducto, cantidad, precioCongelado | F7: Registro histórico interno que detalla qué artículos conforman el pedido total. | G7: LIN-POL-01 | H7: Asegurar que los datos requeridos sean válidos a nivel de tipo, formato, longitud y obligatoriedad. | I7: Software Contable | J7: Línea de pedido registrada | K7: Riesgo de que el producto se agote físicamente entre el momento en que estaba en el carrito y el milisegundo en que se crea la línea de pedido.
G8: LIN-POL-02 | H8: El idProducto debe existir en el catálogo, pero su estado actual no importa (incluso si fue inactivado después de la compra).
G9: LIN-POL-03 | H9: El precioCongelado debe ser una copia exacta del precio que tenía el producto al momento de la compra, asegurando inmutabilidad.
A10: Administrador | B10: Devolver / Cancelar línea (Reembolso parcial) | C10: Anular un ítem específico del pedido porque llegó defectuoso o el cliente pidió garantía, sin cancelar todo el pedido. | D10: =ListadoObjetosDominio!B13 -> LineaPedido | E10: idLineaPedido, idPedido, idProducto, cantidad, precioCongelado | F10: Panel de gestión de garantías y devoluciones en el administrador. | G10: LIN-POL-04 | H10: Solo se puede devolver una línea si el pedido padre (idPedido) está en estado "Entregado" o "Completado". | I10: Pasarela de Pagos (API de Reembolsos) | J10: Línea de pedido devuelta (reembolsada) | K10: Si se devuelve una línea de pedido, ¿el sistema debe retornar automáticamente esa "cantidad" al stock disponible del inventario?
A11: Cliente/Administrador | B11: Consultar detalle de pedido | C11: Listar los productos exactos, cantidades y precios que el cliente compró dentro de un pedido específico. | D11: LineaPedido | E11: idLineaPedido, idPedido, idProducto, cantidad, precioCongelado | F11: Vista de "Detalle de factura" o "Ítems del pedido" en el perfil del cliente. | G11: LIN-POL-05 | H11: El cliente solo puede consultar las líneas de pedido que pertenezcan a un idPedido asociado a su cuenta. | J11: Líneas de pedido consultadas | K11: N/A

Sheet P-LineaPedido
A1: << Ir al modelo de dominio | E1: << Ir al listado de objetos de dominio | I1: << Ir a la caracterización del objeto de dominio
A2: Objeto de Dominio: | B2: =ListadoObjetosDominio!B13 -> LineaPedido
A3: Descripción: | B3: =ListadoObjetosDominio!C13 -> Objeto de dominio que representa el detalle individual de un pedido, permitiendo registrar de forma histórica cada producto adquirido, su cantidad y su valor al momento de confirmar la compra. (Evidencia histórica de la compra)
A4: Business Rule/Policy
A5: Políticas
A6: Número | B6: Descripción
A7: LIN-POL-01 | B7: Asegurar que los datos requeridos sean válidos a nivel de tipo, formato, longitud y obligatoriedad.
A8: LIN-POL-02 | B8: El idProducto debe existir en el catálogo, pero su estado actual no importa (incluso si fue inactivado después de la compra).
A9: LIN-POL-03 | B9: El precioCongelado debe ser una copia exacta del precio que tenía el producto al momento de la compra, asegurando inmutabilidad.
A10: LIN-POL-04 | B10: Solo se puede devolver una línea si el pedido padre (idPedido) está en estado "Entregado" o "Completado".
A11: LIN-POL-05 | B11: El cliente solo puede consultar las líneas de pedido que pertenezcan a un idPedido asociado a su cuenta.

Sheet M-Pagos
A1: << Ir al modelo de dominio | H1: << Ir al listado de objetos de dominio | J1: << Ir a la caracterización del objeto de dominio
A2: Nombre | B2: =ListadoObjetosDominio!B14 -> Pago
A3: Descripción | B3: =ListadoObjetosDominio!C14 -> Objeto de dominio que representa el registro de la transacción financiera procesada a través de la pasarela de pagos para saldar un pedido.
A4: Identificador único universal (UUID) del pago. | B4: Referencia al pedido asociado al pago. | C4: Referencia al método de pago utilizado. | D4: Monto del pago en pesos colombianos (COP). | E4: Fecha en que se procesó el pago (LocalDate). | F4: Estado del pago (PENDIENTE, EN_PROCESO, APROBADO, RECHAZADO, REEMBOLSADO). | G4: Indica que cada intento de pago tiene un identificador único en el sistema, útil para trazabilidad y reclamos
A5: id | B5: pedido | C5: metodoPago | D5: monto | E5: fechaPago | F5: estado | G5: CombinacionUnica1
A6: PA000000-1111-4222-8333-BBBBBB000001 | B6: PED12345-A1B2-4C3D-8E4F-000000000001 | C6: MP000000-1111-4222-8333-AAAAAA000001 | D6: 89900 | E6: 2026-05-15 | F6: PENDIENTE | G6: =B6 -> PED12345-A1B2-4C3D-8E4F-000000000001
A7: PA000000-1111-4222-8333-BBBBBB000002 | B7: PED12345-A1B2-4C3D-8E4F-000000000002 | C7: MP000000-1111-4222-8333-AAAAAA000002 | D7: 290000 | E7: 2026-05-16 | F7: APROBADO | G7: =B7 -> PED12345-A1B2-4C3D-8E4F-000000000002
A8: PA000000-1111-4222-8333-BBBBBB000003 | B8: PED12345-A1B2-4C3D-8E4F-000000000003 | C8: MP000000-1111-4222-8333-AAAAAA000003 | D8: 106500 | E8: 2026-05-17 | F8: EN_PROCESO | G8: =B8 -> PED12345-A1B2-4C3D-8E4F-000000000003
A9: PA000000-1111-4222-8333-BBBBBB000004 | B9: PED12345-A1B2-4C3D-8E4F-000000000004 | C9: MP000000-1111-4222-8333-AAAAAA000002 | D9: 189900 | E9: 2026-05-18 | F9: APROBADO | G9: =B9 -> PED12345-A1B2-4C3D-8E4F-000000000004
A10: PA000000-1111-4222-8333-BBBBBB000005 | B10: PED12345-A1B2-4C3D-8E4F-000000000005 | C10: MP000000-1111-4222-8333-AAAAAA000004 | D10: 179800 | E10: 2026-05-19 | F10: RECHAZADO | G10: =B10 -> PED12345-A1B2-4C3D-8E4F-000000000005
A13: Corresponde a los datos generales del objeto de dominio (nombre, descripción)
A14: Corresponde a las descripciones de los atributos
A15: Coresponde al nombre de los atributos
A16: Corresponde a los datos que son de libre ingreso
A17: Corresponde a los datos que se generarán automáticamente
A18: Corresponde a la combinación única 1
A19: Corresponde a referencias a otros objetos de dominio

Sheet C-Pagos
A1: << Ir al modelo de dominio | D1: << Ir al listado de objetos de dominio | G1: << Ir a la caracterización del objeto de dominio
A2: Nombre | B2: ='M-Pagos'!B2 -> Pago
A3: Descripción | B3: ='M-Pagos'!B3 -> Objeto de dominio que representa el registro de la transacción financiera procesada a través de la pasarela de pagos para saldar un pedido.
A4: Nombre atributo | B4: Descripción atributo | C4: Identificador del objeto de dominio | D4: Tipo de dato | E4: Obligatorio | F4: Longitud minima(si aplica longitud maxima(si aplica) | G4: Longitud maxima(si aplica longitud maxima(si aplica) | H4: Precisión (si aplica) | I4: Redondeo(si aplica) | J4: Rango inicial(si aplica) | K4: Rango final (si aplica) | L4: Formato(Si aplica) | M4: Reglas especiales(si aplica) | N4: Dato calculado | O4: Aplica ajuste del dato(si aplica) | P4: Carácter de ajuste(si aplica) | Q4: Quitar espacios en blanco al inicio(si aplica) | R4: Quitar espacios en blanco al fin(si aplica) | S4: Dato sensible(si aplica) | T4: Valor por defecto(si aplica) | U4: Auto generado | V4: =#REF! -> #REF! | W4: =#REF! -> #REF! | X4: =#REF! -> #REF! | Y4: =#REF! -> #REF!
A5: ='M-Pagos'!A5 -> id | B5: ='M-Pagos'!A4 -> Identificador único universal (UUID) del pago. | C5: Si | D5: Alfanumerico | E5: Si | F5: 5 | L5: Mayusculas | M5: Código de autorización emitido por la pasarela de pagos | N5: No | O5: No | Q5: Si | R5: Si | S5: Si | U5: Si | V5: Requerido | W5: No requerido
A6: ='M-Pagos'!B5 -> pedido | B6: ='M-Pagos'!B4 -> Referencia al pedido asociado al pago. | C6: No | D6: <Pedido> | E6: Si | M6: El pedido debe existir y no estar cancelado | N6: No | S6: No | U6: No | V6: No requerido | W6: No requerido
A7: ='M-Pagos'!C5 -> metodoPago | B7: ='M-Pagos'!C4 -> Referencia al método de pago utilizado. | C7: No | D7: <MetodoPago> | E7: Si | H7: 2 | I7: Truncamiento | J7: 1 | K7: 999999 | M7: Debe ser igual al totalCompra liquidado en el Pedido | N7: No | S7: No | U7: Si | V7: Norequerido | W7: No requerido
A8: ='M-Pagos'!D5 -> monto | B8: ='M-Pagos'!D4 -> Monto del pago en pesos colombianos (COP). | C8: No | D8: Numerico decimal | E8: Si | M8: El método seleccionado debe estar Activo en el sistema | N8: No | S8: No | U8: No
A9: ='M-Pagos'!E5 -> fechaPago | B9: ='M-Pagos'!E4 -> Fecha en que se procesó el pago (LocalDate). | C9: No | D9: Fecha | E9: Si | F9: 6 | L9: Capitalizado | M9: Solo permite: 'Aprobado', 'Rechazado' o 'Pendiente' | N9: No | O9: No | Q9: Si | R9: Si | S9: No | T9: Pendiente | U9: No
A10: ='M-Pagos'!F5 -> estado | B10: ='M-Pagos'!F4 -> Estado del pago (PENDIENTE, EN_PROCESO, APROBADO, RECHAZADO, REEMBOLSADO). | C10: No | D10: Texto | E10: Si | F10: 5 | G10: 50 | L10: Mayusculas | M10: Solo se llena si la transacción es aprobada por el banco | N10: No | O10: No | Q10: Si | R10: Si | S10: Si | U10: Si
A11: ='M-Pagos'!#REF! -> #REF! | B11: ='M-Pagos'!#REF! -> #REF! | C11: No | D11: Fecha/Hora | E11: Si | M11: Registra el momento en que la pasarela emite una respuesta | N11: No | S11: No | U11: si
A13: Nombre combinación unica | B13: Descripción | C13: Atributos involucrados
A14: ='M-Pagos'!G5 -> CombinacionUnica1 | B14: ='M-Pagos'!G4 -> Indica que cada intento de pago tiene un identificador único en el sistema, útil para trazabilidad y reclamos | C14: ='M-Pagos'!A5 -> id
A17: Responsabilidad | B17: Descripción | C17: Entradas | F17: Salida | H17: Políticas (Reglas de Negocio) | J17: Excepción
C18: Parámettro | D18: Tipo de dato | E18: Descripci | F18: Tipo de Dato | G18: Descripción | H18: Política | I18: Descripción | J18: Detalle | K18: ¿Qué hago?
A19: ='E-Pagos'!B7 -> Procesar pago (Iniciar) | B19: ='E-Pagos'!C7 -> Enviar la información de cobro a la entidad financiera y registrar la transacción inicial. | C19: pagoNuevo | D19: Pago | E19: Contiene la información inicial de la transacción a registrar. | F19: Logico | G19: Retorna verdadero si el intento de pago se registró correctamente. | H19: ='E-Pagos'!G7 -> PAG-POL-01 | I19: ='E-Pagos'!H7 -> Asegurar que los datos requeridos sean válidos a nivel de tipo, formato, longitud y obligatoriedad. | J19: Generar excepción indicando qué campo no cumple con el formato o es obligatorio. | K19: Detener operación
H20: ='E-Pagos'!G8 -> PAG-POL-02 | I20: ='E-Pagos'!H8 -> El monto del pago debe ser mayor a cero | J20: Generar excepción indicando que el monto de la transacción difiere del total del pedido. | K20: Detener operación
H21: ='E-Pagos'!G9 -> PAG-POL-03 | I21: ='E-Pagos'!H9 -> El estado del pago debe ser uno de los valores válidos definidos (Pendiente, En proceso, Aprobado, Rechazado, Reembolsado). | J21: Generar excepción indicando que el pago no puede iniciar en un estado distinto a Pendiente. | K21: Detener operación
A22: ='E-Pagos'!B10 -> Actualizar estado de pago | B22: ='E-Pagos'!C10 -> Recibir la confirmación asíncrona del banco (aprobado o rechazado) y actualizar el sistema. | C22: pagoActualizado | D22: Pago | E22: Contiene el identificador del pago y el nuevo estado reportado por el banco. | F22: Logico | G22: Retorna verdadero si el estado del pago se actualizó exitosamente. | H22: ='E-Pagos'!G10 -> PAG-POL-04 | I22: ='E-Pagos'!H10 -> El idPago a modificar debe existir previamente en el sistema. | J22: Generar excepción indicando que el pago a actualizar no se encuentra registrado. | K22: Detener operación
H23: ='E-Pagos'!G11 -> 0 | I23: ='E-Pagos'!H11 -> 0 | J23: Generar excepción indicando que el pago ya finalizó su ciclo y su estado es inmutable. | K23: Detener operación
A24: ='E-Pagos'!#REF! -> #REF! | B24: ='E-Pagos'!#REF! -> #REF! | C24: idPago | D24: alfanumerico | E24: Identificador exacto del pago que se desea reembolsar o anular. | F24: Logico | G24: Retorna verdadero si el reembolso se emitió y registró correctamente. | H24: ='E-Pagos'!#REF! -> #REF! | I24: ='E-Pedido'!H12 -> 0 | J24: Generar excepción indicando que no se puede reembolsar un pago que aún no ha sido aprobado por el banco. | K24: Detener operación
A25: ='E-Pagos'!B12 -> Consultar pagos | B25: ='E-Pagos'!C12 -> Revisar el comprobante, el método usado y el estado de la transacción para conciliación contable o soporte. | C25: filtros | D25: Texto | E25: Parámetros opcionales para buscar o filtrar el historial de pagos. | F25: Lista<Pago> | G25: Retorna una colección con los objetos de los pagos encontrados. | H25: ='E-Pagos'!G12 -> PAG-POL-05 | I25: ='E-Pagos'!H12 -> El cliente solo puede ver los pagos de sus propios pedidos; el administrador tiene visión global. | J25: Generar excepción indicando acceso denegado por intentar visualizar datos financieros de otro usuario. | K25: Detener operación

Sheet E-Pagos
A1: << Ir al modelo de dominio | E1: << Ir al listado de objetos de dominio | I1: << Ir a la caracterización del objeto de dominio
A2: Objeto de Dominio: | B2: =ListadoObjetosDominio!B14 -> Pago
A3: Descripción: | B3: =ListadoObjetosDominio!C14 -> Objeto de dominio que representa el registro de la transacción financiera procesada a través de la pasarela de pagos para saldar un pedido.
A4: Actor | B4: Action/Command | D4: Entity/Aggregate/Object domain | E4: Read Model | G4: Business Rule/Policy | I4: External System | J4: Domain Event | K4: Hotspot/questions/Risk
A5: Actor | B5: Acción | C5: Descripción | D5: Objeto de dominio | E5: Información externa | G5: Políticas | I5: Sistema Externo | J5: Evento | K5: Aspectos por solucionar
E6: Información | F6: Descripción | G6: Número | H6: Descripción
A7: Cliente / Sistema | B7: Procesar pago (Iniciar) | C7: Enviar la información de cobro a la entidad financiera y registrar la transacción inicial. | D7: =ListadoObjetosDominio!B14 -> Pago | E7: idPedido, metodoPago, monto, fechaPago, estado | F7: Formulario de checkout y pantalla de redirección al banco o pasarela. | G7: PAG-POL-01 | H7: Asegurar que los datos requeridos sean válidos a nivel de tipo, formato, longitud y obligatoriedad. | I7: Pasarela de Pagos | J7: Intento de pago registrado | K7: Riesgo de Cobro Doble: ¿Qué pasa si el cliente entra en pánico porque la página no carga y presiona el botón "Pagar" 3 veces seguidas?
G8: PAG-POL-02 | H8: El monto del pago debe ser mayor a cero
G9: PAG-POL-03 | H9: El estado del pago debe ser uno de los valores válidos definidos (Pendiente, En proceso, Aprobado, Rechazado, Reembolsado).
A10: Sistema (Webhook) / Admin | B10: Actualizar estado de pago | C10: Recibir la confirmación asíncrona del banco (aprobado o rechazado) y actualizar el sistema. | D10: =ListadoObjetosDominio!B14 -> Pago | E10: idPago, estado, codigoAutorizacion, fechaHora | F10: Endpoint del servidor que escucha la respuesta del banco o panel administrativo. | G10: PAG-POL-04 | H10: El idPago a modificar debe existir previamente en el sistema. | I10: Pasarela de Pagos / Red Bancaria | J10: Estado de pago actualizado (Aprobado/Rechazado) | K10: Si el banco tarda 30 minutos en confirmar un pago por PSE, ¿el inventario del producto debe mantenerse bloqueado o se libera para otro cliente?
A12: Cliente / Administrador | B12: Consultar pagos | C12: Revisar el comprobante, el método usado y el estado de la transacción para conciliación contable o soporte. | D12: =ListadoObjetosDominio!B14 -> Pago | E12: idPago, idPedido, monto, metodo, estado, codigoAutorizacion, fechaHora | F12: Historial de transacciones en el perfil del cliente o reporte financiero del administrador. | G12: PAG-POL-05 | H12: El cliente solo puede ver los pagos de sus propios pedidos; el administrador tiene visión global. | J12: Pagos consultados | K12: Si la base de datos se vulnera, exponer métodos de pago o montos podría generar problemas de confidencialidad financiera.

Sheet P-Pagos
A1: << Ir al modelo de dominio | E1: << Ir al listado de objetos de dominio | I1: << Ir a la caracterización del objeto de dominio
A2: Objeto de Dominio: | B2: =ListadoObjetosDominio!B14 -> Pago
A3: Descripción: | B3: =ListadoObjetosDominio!C14 -> Objeto de dominio que representa el registro de la transacción financiera procesada a través de la pasarela de pagos para saldar un pedido.
A4: Business Rule/Policy
A5: Políticas
A6: Número | B6: Descripción
A7: PAG-POL-01 | B7: Asegurar que los datos requeridos sean válidos a nivel de tipo, formato, longitud y obligatoriedad.
A8: PAG-POL-02 | B8: El monto del pago debe ser mayor a cero
A9: PAG-POL-03 | B9: El estado del pago debe ser uno de los valores válidos definidos (Pendiente, En proceso, Aprobado, Rechazado, Reembolsado).
A10: PAG-POL-04 | B10: El idPago a modificar debe existir previamente en el sistema.
A12: PAG-POL-05 | B12: El cliente solo puede ver los pagos de sus propios pedidos; el administrador tiene visión global.

Sheet M-MetodoPago
A1: << Ir al modelo de dominio | G1: << Ir al listado de objetos de dominio | I1: << Ir a la caracterización del objeto de dominio
A2: Nombre | B2: =ListadoObjetosDominio!B15 -> MetodoPago
A3: Descripción | B3: =ListadoObjetosDominio!C15 -> Objeto de dominio que representa el instrumento financiero o forma transaccional utilizada por el cliente (tarjeta de crédito, PSE, etc.) para realizar el pago.
A4: Identificador único universal (UUID) del método de pago. | B4: Nombre comercial del método de pago. | C4: Descripción del método de pago (opcional). | D4: Indica si el método de pago está activo (true) o inactivo (false). | H4: Indica que cada intento de pago tiene un identificador único en el sistema, útil para trazabilidad y reclamos
A5: id | B5: nombre | C5: descripcion | D5: estado | H5: CombinacionUnica1
A6: MP000000-1111-4222-8333-AAAAAA000001 | B6: Tarjeta de crédito | C6: Visa, Mastercard, American Express. | D6: TRUE | G6: ACTIVO | H6: =A6 -> MP000000-1111-4222-8333-AAAAAA000001
A7: MP000000-1111-4222-8333-AAAAAA000002 | B7: PSE | C7: Pago seguro en línea débito bancos colombianos. | D7: TRUE | G7: INACTIVO | H7: =A7 -> MP000000-1111-4222-8333-AAAAAA000002
A8: MP000000-1111-4222-8333-AAAAAA000003 | B8: Nequi | C8: Billetera digital Bancolombia. | D8: TRUE | G8: ACTIVO | H8: =A8 -> MP000000-1111-4222-8333-AAAAAA000003
A9: MP000000-1111-4222-8333-AAAAAA000004 | B9: Efectivo contraentrega | C9: Pago en efectivo al recibir el pedido. | D9: TRUE | G9: INACTIVO | H9: =A9 -> MP000000-1111-4222-8333-AAAAAA000004
A10: MP000000-1111-4222-8333-AAAAAA000005 | B10: Daviplata | C10: Billetera digital Davivienda. | D10: FALSE | G10: ACTIVO | H10: =A10 -> MP000000-1111-4222-8333-AAAAAA000005
A13: Corresponde a los datos generales del objeto de dominio (nombre, descripción)
A14: Corresponde a las descripciones de los atributos
A15: Coresponde al nombre de los atributos
A16: Corresponde a los datos que son de libre ingreso
A17: Corresponde a los datos que se generarán automáticamente
A18: Corresponde a la combinación única 1
A19: Corresponde a referencias a otros objetos de dominio

Sheet C-MetodoPago
A1: << Ir al modelo de dominio | D1: << Ir al listado de objetos de dominio | G1: << Ir a la caracterización del objeto de dominio
A2: Nombre | B2: ='M-MetodoPago'!B2 -> MetodoPago
A3: Descripción | B3: ='M-MetodoPago'!B3 -> Objeto de dominio que representa el instrumento financiero o forma transaccional utilizada por el cliente (tarjeta de crédito, PSE, etc.) para realizar el pago.
A4: Nombre atributo | B4: Descripción atributo | C4: Identificador del objeto de dominio | D4: Tipo de dato | E4: Obligatorio | F4: Longitud minima(si aplica longitud maxima(si aplica) | G4: Longitud maxima(si aplica longitud maxima(si aplica) | H4: Precisión (si aplica) | I4: Redondeo(si aplica) | J4: Rango inicial(si aplica) | K4: Rango final (si aplica) | L4: Formato(Si aplica) | M4: Reglas especiales(si aplica) | N4: Dato calculado | O4: Aplica ajuste del dato(si aplica) | P4: Carácter de ajuste(si aplica) | Q4: Quitar espacios en blanco al inicio(si aplica) | R4: Quitar espacios en blanco al fin(si aplica) | S4: Dato sensible(si aplica) | T4: Valor por defecto(si aplica) | U4: Auto generado | V4: =#REF! -> #REF! | W4: =#REF! -> #REF! | X4: =#REF! -> #REF! | Y4: =#REF! -> #REF!
A5: ='M-MetodoPago'!A5 -> id | B5: ='M-MetodoPago'!A4 -> Identificador único universal (UUID) del método de pago. | C5: Si | D5: Alfanumerico | E5: Si | F5: 1 | L5: Mayusculas | N5: No | O5: No | Q5: Si | R5: Si | S5: No | U5: Si | V5: Requerido | W5: No requerido
A6: ='M-MetodoPago'!B5 -> nombre | B6: ='M-MetodoPago'!B4 -> Nombre comercial del método de pago. | C6: No | D6: Alfanumerico | E6: Si | F6: 3 | G6: 100 | L6: Capitalizado | M6: El nombre debe ser claro para el cliente en el checkout | N6: No | O6: No | Q6: Si | R6: Si | S6: No | U6: No | V6: No requerido | W6: No requerido
A8: Nombre combinación unica | B8: Descripción | C8: Atributos involucrados
A9: ='M-MetodoPago'!C5 -> descripcion | B9: ='M-MetodoPago'!C4 -> Descripción del método de pago (opcional). | C9: ='M-MetodoPago'!B5 -> nombre
A12: Responsabilidad | B12: Descripción | C12: Entradas | F12: Salida | H12: Políticas (Reglas de Negocio) | J12: Excepción
C13: Parámettro | D13: Tipo de dato | E13: Descripci | F13: Tipo de Dato | G13: Descripción | H13: Política | I13: Descripción | J13: Detalle | K13: ¿Qué hago?
A14: ='E-MetodoPago'!B7 -> Registrar método de pago | B14: ='E-MetodoPago'!C7 -> Crear una nueva opción de pago para que quede disponible en el checkout de la tienda. | C14: metodoNuevo | D14: MetodoPago | E14: Contiene la información del nuevo método de pago a registrar. | F14: Logico | G14: Retorna verdadero si el método se agregó exitosamente. | H14: ='E-MetodoPago'!G7 -> MET-POL-01 | I14: ='E-MetodoPago'!H7 -> Asegurar que los datos requeridos sean válidos a nivel de tipo de dato, formato, longitud y obligatoriedad. | J14: Generar excepción indicando qué campo no cumple con el formato o es obligatorio. | K14: Detener operación
H15: ='E-MetodoPago'!G8 -> MET-POL-02 | I15: ='E-MetodoPago'!H8 -> El nombre del método de pago no debe repetirse en el sistema. | J15: Generar excepción indicando que ya existe un método de pago con ese mismo nombre. | K15: Detener operación
A16: ='E-MetodoPago'!B9 -> Modificar método de pago | B16: ='E-MetodoPago'!C9 -> Actualizar la información de una opción de pago existente, como su nombre, descripción o disponibilidad. | C16: metodoModificado | D16: MetodoPago | E16: Contiene la información actualizada del método de pago. | F16: Logico | G16: Retorna verdadero si el método de pago se actualizó correctamente. | H16: ='E-MetodoPago'!G9 -> MET-POL-03 | I16: ='E-MetodoPago'!H9 -> El idMetodoPago a modificar debe existir previamente en el sistema. | J16: Generar excepción indicando que el método de pago a editar no se encuentra registrado. | K16: Detener operación
H17: ='E-MetodoPago'!G10 -> MET-POL-04 | I17: ='E-MetodoPago'!H10 -> Si se cambia el nombre, el nuevo valor no debe coincidir con otro método ya registrado. | J17: Generar excepción indicando que el nuevo nombre entra en conflicto con un método existente. | K17: Detener operación
A18: ='E-MetodoPago'!B11 -> Desactivar método de pago | B18: ='E-MetodoPago'!C11 -> Inhabilitar una opción de cobro para que deje de aparecer en el checkout sin borrar su historial. | C18: idMetodoPago | D18: alfanumerico | E18: Identificador exacto del método de pago que se desea borrar. | F18: Logico | G18: Retorna verdadero si el método de pago fue eliminado correctamente. | H18: ='E-MetodoPago'!G11 -> MET-POL-05 | I18: ='E-MetodoPago'!H11 -> El idMetodoPago debe existir previamente en el sistema. | J18: Generar excepción indicando que el método a eliminar no se encuentra en la base de datos. | K18: Detener operación
A19: ='E-MetodoPago'!B12 -> Consultar métodos de pago | B19: ='E-MetodoPago'!C12 -> Listar los métodos de pago disponibles para mostrarlos en el checkout o gestionarlos desde el panel administrativo. | C19: filtros | D19: Texto | E19: Parámetros opcionales para filtrar la búsqueda de métodos de pago. | F19: Lista<MetodoPago> | G19: Retorna una colección con los objetos de los métodos de pago encontrados. | H19: ='E-MetodoPago'!G12 -> MET-POL-06 | I19: ='E-MetodoPago'!H12 -> El cliente solo debe visualizar métodos con estado "Activo"; el administrador puede ver todos. | J19: Generar excepción indicando acceso denegado por intentar visualizar métodos inactivos sin permisos. | K19: Detener operación

Sheet E-MetodoPago
A1: << Ir al modelo de dominio | E1: << Ir al listado de objetos de dominio | I1: << Ir a la caracterización del objeto de dominio
A2: Objeto de Dominio: | B2: =ListadoObjetosDominio!B15 -> MetodoPago
A3: Descripción: | B3: =ListadoObjetosDominio!C15 -> Objeto de dominio que representa el instrumento financiero o forma transaccional utilizada por el cliente (tarjeta de crédito, PSE, etc.) para realizar el pago.
A4: Actor | B4: Action/Command | D4: Entity/Aggregate/Object domain | E4: Read Model | G4: Business Rule/Policy | I4: External System | J4: Domain Event | K4: Hotspot/questions/Risk
A5: Actor | B5: Acción | C5: Descripción | D5: Objeto de dominio | E5: Información externa | G5: Políticas | I5: Sistema Externo | J5: Evento | K5: Aspectos por solucionar
E6: Información | F6: Descripción | G6: Número | H6: Descripción
A7: Administrador | B7: Registrar método de pago | C7: Crear una nueva opción de pago para que quede disponible en el checkout de la tienda. | D7: =ListadoObjetosDominio!B15 -> MetodoPago | E7: nombre | F7: Formulario simple en el panel de configuración de la tienda. | G7: MET-POL-01 | H7: Asegurar que los datos requeridos sean válidos a nivel de tipo de dato, formato, longitud y obligatoriedad. | J7: Método de pago registrado | K7: Riesgo de habilitar un método que realmente no esté operativo en la pasarela o en el proceso interno de cobro.
G8: MET-POL-02 | H8: El nombre del método de pago no debe repetirse en el sistema.
A9: Administrador | B9: Modificar método de pago | C9: Actualizar la información de una opción de pago existente, como su nombre, descripción o disponibilidad. | D9: =ListadoObjetosDominio!B15 -> MetodoPago | E9: idMetodo, nombre | F9: Formulario pre-cargado con la información actual del método de pago. | G9: MET-POL-03 | H9: El idMetodoPago a modificar debe existir previamente en el sistema. | J9: Método de pago modificado | K9: Si se cambia un método usado históricamente, puede generarse confusión en reportes o conciliaciones antiguas.
G10: MET-POL-04 | H10: Si se cambia el nombre, el nuevo valor no debe coincidir con otro método ya registrado.
A11: Administrador | B11: Desactivar método de pago | C11: Inhabilitar una opción de cobro para que deje de aparecer en el checkout sin borrar su historial. | D11: =ListadoObjetosDominio!B15 -> MetodoPago | E11: idMetodo, nombre | F11: Vista de edición rápida en la configuración del administrador. | G11: MET-POL-05 | H11: El idMetodoPago debe existir previamente en el sistema. | J11: Método de pago desactivado | K11: Lo correcto es desactivar y no borrar, porque pagos históricos pueden seguir apuntando a ese método.
A12: Cliente / Administrador | B12: Consultar métodos de pago | C12: Listar los métodos de pago disponibles para mostrarlos en el checkout o gestionarlos desde el panel administrativo. | D12: =ListadoObjetosDominio!B15 -> MetodoPago | E12: idMetodo, nombre | F12: Vista del catálogo de métodos habilitados para cobrar en la tienda. | G12: MET-POL-06 | H12: El cliente solo debe visualizar métodos con estado "Activo"; el administrador puede ver todos. | J12: Métodos de pago consultados

Sheet P-MetodoPago
A1: << Ir al modelo de dominio | E1: << Ir al listado de objetos de dominio | I1: << Ir a la caracterización del objeto de dominio
A2: Objeto de Dominio: | B2: =ListadoObjetosDominio!B15 -> MetodoPago
A3: Descripción: | B3: =ListadoObjetosDominio!C15 -> Objeto de dominio que representa el instrumento financiero o forma transaccional utilizada por el cliente (tarjeta de crédito, PSE, etc.) para realizar el pago.
A4: Business Rule/Policy
A5: Políticas
A6: Número | B6: Descripción
A7: MET-POL-01 | B7: Asegurar que los datos requeridos sean válidos a nivel de tipo de dato, formato, longitud y obligatoriedad.
A8: MET-POL-02 | B8: El nombre del método de pago no debe repetirse en el sistema.
A9: MET-POL-03 | B9: El idMetodoPago a modificar debe existir previamente en el sistema.
A10: MET-POL-04 | B10: Si se cambia el nombre, el nuevo valor no debe coincidir con otro método ya registrado.
A11: MET-POL-05 | B11: El idMetodoPago debe existir previamente en el sistema.
A12: MET-POL-06 | B12: El cliente solo debe visualizar métodos con estado "Activo"; el administrador puede ver todos.

Sheet M-Factura
A1: << Ir al modelo de dominio | I1: << Ir al listado de objetos de dominio | K1: << Ir a la caracterización del objeto de dominio
A2: Nombre | B2: =ListadoObjetosDominio!B16 -> Factura
A3: Descripción | B3: =ListadoObjetosDominio!C16 -> Objeto de dominio que representa el comprobante legal y contable emitido al cliente con el desglose de impuestos una vez el pago ha sido exitoso.
A4: Identificador interno autogenerado por el sistema | B4: Referencia al objeto de dominio “Pago” exitoso que originó esta factura (Llave foránea) | C4: Número de factura electrónica | D4: Fecha y hora de emisión del comprobante contable | E4: Valor base de la compra sin impuestos (COP) | F4: Valor correspondiente al IVA (19%) u otros tributos (COP) | G4: Valor total legalmente facturado al cliente (COP) | H4: Indica que cada intento de pago tiene un identificador único en el sistema, útil para trazabilidad y reclamos
A5: idFactura | B5: idPago | C5: numeroFactura | D5: fechaEmision | E5: subtotal | F5: totalImpuestos | G5: totalFacturado | H5: Combinación única 1
A6: FAC-001 | B6: PAG-001 | C6: FE-10020 | D6: 46112 | E6: 12269 | F6: =E6*19% -> 2331.11 | G6: =E6+F6 -> 14600.11 | H6: =B6 -> PAG-001
A7: FAC-002 | B7: PAG-002 | C7: FE-10021 | D7: 46113 | E7: 12269 | F7: =E7*19% -> 2331.11 | G7: =E7+F7 -> 14600.11 | H7: =B7 -> PAG-002
A8: FAC-003 | B8: PAG-003 | C8: FE-10022 | D8: 46114 | E8: 12269 | F8: =E8*19% -> 2331.11 | G8: =E8+F8 -> 14600.11 | H8: =B8 -> PAG-003
A9: FAC-004 | B9: PAG-004 | C9: FE-10023 | D9: 46115 | E9: 12269 | F9: =E9*19% -> 2331.11 | G9: =E9+F9 -> 14600.11 | H9: =B9 -> PAG-004
A10: FAC-005 | B10: PAG-005 | C10: FE-10024 | D10: 46116 | E10: 12269 | F10: =E10*19% -> 2331.11 | G10: =E10+F10 -> 14600.11 | H10: =B10 -> PAG-005
A13: Corresponde a los datos generales del objeto de dominio (nombre, descripción)
A14: Corresponde a las descripciones de los atributos
A15: Coresponde al nombre de los atributos
A16: Corresponde a los datos que son de libre ingreso
A17: Corresponde a los datos que se generarán automáticamente
A18: Corresponde a la combinación única 1
A19: Corresponde a referencias a otros objetos de dominio

Sheet C-Factura
A1: << Ir al modelo de dominio | D1: << Ir al listado de objetos de dominio | G1: << Ir a la caracterización del objeto de dominio
A2: Nombre | B2: ='M-Factura'!B2 -> Factura
A3: Descripción | B3: ='M-Factura'!B3 -> Objeto de dominio que representa el comprobante legal y contable emitido al cliente con el desglose de impuestos una vez el pago ha sido exitoso.
A4: Nombre atributo | B4: Descripción atributo | C4: Identificador del objeto de dominio | D4: Tipo de dato | E4: Obligatorio | F4: Longitud minima(si aplica longitud maxima(si aplica) | G4: Longitud maxima(si aplica longitud maxima(si aplica) | H4: Precisión (si aplica) | I4: Redondeo(si aplica) | J4: Rango inicial(si aplica) | K4: Rango final (si aplica) | L4: Formato(Si aplica) | M4: Reglas especiales(si aplica) | N4: Dato calculado | O4: Aplica ajuste del dato(si aplica) | P4: Carácter de ajuste(si aplica) | Q4: Quitar espacios en blanco al inicio(si aplica) | R4: Quitar espacios en blanco al fin(si aplica) | S4: Dato sensible(si aplica) | T4: Valor por defecto(si aplica) | U4: Auto generado | V4: =#REF! -> #REF! | W4: =#REF! -> #REF! | X4: =#REF! -> #REF! | Y4: =#REF! -> #REF!
A5: ='M-Factura'!A5 -> idFactura | B5: ='M-Factura'!A4 -> Identificador interno autogenerado por el sistema | C5: Si | D5: alfanumerico | E5: Si | F5: 1 | G5: 30 | L5: Mayusculas | N5: No | O5: No | Q5: Si | R5: Si | S5: No | U5: Si | V5: Requerido | W5: No requerido
A6: ='M-Factura'!B5 -> idPago | B6: ='M-Factura'!B4 -> Referencia al objeto de dominio “Pago” exitoso que originó esta factura (Llave foránea) | C6: No | D6: <Pago> | E6: Si | M6: El pago referenciado debe estar en estado 'Aprobado' obligatoriamente | N6: No | S6: No | U6: No | V6: No requerido | W6: No requerido
A7: ='M-Factura'!C5 -> numeroFactura | B7: ='M-Factura'!C4 -> Número de factura electrónica | C7: No | D7: alfanumerico | E7: Si | F7: 5 | G7: 50 | L7: Mayusculas | M7: Debe cumplir con la resolución de facturación electrónica | N7: No | O7: No | Q7: Si | R7: Si | S7: Si | U7: Si | V7: Norequerido | W7: No requerido
A8: ='M-Factura'!D5 -> fechaEmision | B8: ='M-Factura'!D4 -> Fecha y hora de emisión del comprobante contable | C8: No | D8: Fecha/Hora | E8: Si | M8: Registra la marca de tiempo exacta de la generación del comprobante | N8: No | S8: No | U8: Si
A9: ='M-Factura'!E5 -> subtotal | B9: ='M-Factura'!E4 -> Valor base de la compra sin impuestos (COP) | C9: No | D9: Numerico decimal | E9: Si | H9: 2 | I9: Truncamiento | J9: 0 | K9: 99999 | M9: Base imponible sin impuestos | N9: Si | S9: No | U9: No
A10: ='M-Factura'!F5 -> totalImpuestos | B10: ='M-Factura'!F4 -> Valor correspondiente al IVA (19%) u otros tributos (COP) | C10: No | D10: Numerico decimal | E10: Si | H10: 2 | I10: Truncamiento | J10: 0 | K10: 99999 | M10: Se calcula aplicando la tarifa vigente de IVA (19%) sobre el subtotal | N10: Si | S10: No | U10: No
A11: ='M-Factura'!G5 -> totalFacturado | B11: ='M-Factura'!G4 -> Valor total legalmente facturado al cliente (COP) | C11: No | D11: Numerico decimal | E11: Si | H11: 2 | I11: Truncamiento | J11: 0 | K11: 99999 | M11: Es la suma matemática estricta del subtotal más el total de impuestos Si | N11: Si | S11: No | U11: No
A13: Nombre combinación unica | B13: Descripción | C13: Atributos involucrados
A14: ='M-Factura'!H5 -> Combinación única 1 | B14: ='M-Factura'!H4 -> Indica que cada intento de pago tiene un identificador único en el sistema, útil para trazabilidad y reclamos | C14: ='M-Factura'!B5 -> idPago
A17: Responsabilidad | B17: Descripción | C17: Entradas | F17: Salida | H17: Políticas (Reglas de Negocio) | J17: Excepción
C18: Parámettro | D18: Tipo de dato | E18: Descripci | F18: Tipo de Dato | G18: Descripción | H18: Política | I18: Descripción | J18: Detalle | K18: ¿Qué hago?
A19: ='E-Factura'!B7 -> Generar factura | B19: ='E-Factura'!C7 -> Crear el comprobante legal y fiscal de la venta una vez que el pago ha sido aprobado exitosamente. | C19: facturaNueva | D19: Factura | E19: Contiene la información de la factura que se va a emitir. | F19: Logico | G19: Retorna verdadero si la factura fue generada exitosamente. | H19: ='E-Factura'!G7 -> FAC-POL-01 | I19: ='E-Factura'!H7 -> Asegurar que los datos requeridos sean válidos a nivel de tipo, formato, longitud y obligatoriedad. | J19: Generar excepción indicando qué campo no cumple con el formato o es obligatorio. | K19: Detener operación
H20: ='E-Factura'!G8 -> FAC-POL-02 | I20: ='E-Factura'!H8 -> El idPago asociado debe existir y su estado debe ser obligatoriamente "Aprobado". | J20: Generar excepción indicando que el pago no existe o aún no ha sido aprobado. | K20: Detener operación
H21: ='E-Factura'!G9 -> FAC-POL-03 | I21: ='E-Factura'!H9 -> El totalFacturado debe ser la suma matemática exacta del subtotal más el totalImpuestos. calculados. | J21: Generar excepción indicando que la sumatoria de los montos no coincide con el total. | K21: Detener operación
A22: ='E-Factura'!B10 -> Anular factura (Nota de Crédito) | B22: ='E-Factura'!C10 -> Invalidar una factura previamente emitida por motivo de devolución de mercancía o error en los datos. | C22: idFactura | D22: alfanumerico | E22: Identificador exacto de la factura que se desea anular. | F22: Logico | G22: Retorna verdadero si la factura se anuló correctamente y se generó la nota crédito. | H22: ='E-Factura'!G10 -> FAC-POL-04 | I22: ='E-Factura'!H10 -> El idFactura a anular debe existir previamente en el sistema. | J22: Generar excepción indicando que la factura que se intenta anular no existe en la base de datos. | K22: Detener operación
H23: ='E-Factura'!G11 -> FAC-POL-05 | I23: ='E-Factura'!H11 -> El sistema no modifica la factura original (es inmutable), sino que debe registrar su estado como "Anulada" y generar una Nota de Crédito. | J23: Generar excepción indicando que no se puede alterar o borrar el registro original de la factura. | K23: Detener operación
A24: ='E-Factura'!B12 -> Consultar y descargar factura | B24: ='E-Factura'!C12 -> Permitir al usuario ver el detalle fiscal de su compra o descargar la representación gráfica (PDF). | C24: filtros | D24: Texto | E24: Parámetros opcionales para buscar o filtrar el historial de facturas. | F24: Lista<Factura> | G24: Retorna una colección con los objetos de las facturas encontradas. | H24: ='E-Factura'!G12 -> FAC-POL-06 | I24: ='E-Factura'!H12 -> El cliente solo puede consultar y descargar las facturas asociadas a sus propios pedidos. | J24: Generar excepción indicando acceso denegado por intentar visualizar facturas de otro usuario. | K24: Detener operación

Sheet E-Factura
A1: << Ir al modelo de dominio | E1: << Ir al listado de objetos de dominio | I1: << Ir a la caracterización del objeto de dominio
A2: Objeto de Dominio: | B2: =ListadoObjetosDominio!B16 -> Factura
A3: Descripción: | B3: =ListadoObjetosDominio!C16 -> Objeto de dominio que representa el comprobante legal y contable emitido al cliente con el desglose de impuestos una vez el pago ha sido exitoso.
A4: Actor | B4: Action/Command | D4: Entity/Aggregate/Object domain | E4: Read Model | G4: Business Rule/Policy | I4: External System | J4: Domain Event | K4: Hotspot/questions/Risk
A5: Actor | B5: Acción | C5: Descripción | D5: Objeto de dominio | E5: Información externa | G5: Políticas | I5: Sistema Externo | J5: Evento | K5: Aspectos por solucionar
E6: Información | F6: Descripción | G6: Número | H6: Descripción
A7: Sistema / Administrador | B7: Generar factura | C7: Crear el comprobante legal y fiscal de la venta una vez que el pago ha sido aprobado exitosamente. | D7: =ListadoObjetosDominio!B16 -> Factura | E7: idPago, numeroFactura, fechaEmision, subtotal, totalImpuestos, totalFacturado | F7: Registro oficial que desglosa el costo de los productos y los impuestos aplicados a la compra. | G7: FAC-POL-01 | H7: Asegurar que los datos requeridos sean válidos a nivel de tipo, formato, longitud y obligatoriedad. | I7: Proveedor de Facturación Electrónica | J7: Factura generada | K7: Riesgo de fallo de conexión con el proveedor tecnológico al intentar timbrar la factura electrónica.
G8: FAC-POL-02 | H8: El idPago asociado debe existir y su estado debe ser obligatoriamente "Aprobado".
G9: FAC-POL-03 | H9: El totalFacturado debe ser la suma matemática exacta del subtotal más el totalImpuestos. calculados.
A10: Administrador | B10: Anular factura (Nota de Crédito) | C10: Invalidar una factura previamente emitida por motivo de devolución de mercancía o error en los datos. | D10: =ListadoObjetosDominio!B16 -> Factura | E10: idFactura, numeroFactura, totalFacturado | F10: Panel contable de reversiones y garantías en el administrador del e-commerce. | G10: FAC-POL-04 | H10: El idFactura a anular debe existir previamente en el sistema. | I10: Proveedor de Facturación Electrónica | J10: Factura anulada | K10: Si un administrador anula una factura de un periodo fiscal (mes o año) que ya fue cerrado por contabilidad, se crea un descuadre legal.
G11: FAC-POL-05 | H11: El sistema no modifica la factura original (es inmutable), sino que debe registrar su estado como "Anulada" y generar una Nota de Crédito.
A12: Cliente / Administrador | B12: Consultar y descargar factura | C12: Permitir al usuario ver el detalle fiscal de su compra o descargar la representación gráfica (PDF). | D12: =ListadoObjetosDominio!B16 -> Factura | E12: idFactura, idPago, numeroFactura, fechaEmision, subtotal, totalImpuestos, totalFacturado | F12: Vista detallada del recibo o enlace para descargar la versión en PDF o XML. | G12: FAC-POL-06 | H12: El cliente solo puede consultar y descargar las facturas asociadas a sus propios pedidos. | I12: Sistema de Almacenamiento | J12: Facturas consultadas | K12: Riesgo de rendimiento y almacenamiento si el sistema genera y guarda los PDFs de todas las facturas en lugar de generarlos "al vuelo" cuando el cliente los pide.

Sheet P-Factura
A1: << Ir al modelo de dominio | E1: << Ir al listado de objetos de dominio | I1: << Ir a la caracterización del objeto de dominio
A2: Objeto de Dominio: | B2: =ListadoObjetosDominio!B16 -> Factura
A3: Descripción: | B3: =ListadoObjetosDominio!C16 -> Objeto de dominio que representa el comprobante legal y contable emitido al cliente con el desglose de impuestos una vez el pago ha sido exitoso.
A4: Business Rule/Policy
A5: Políticas
A6: Número | B6: Descripción
A7: FAC-POL-01 | B7: Asegurar que los datos requeridos sean válidos a nivel de tipo, formato, longitud y obligatoriedad.
A8: FAC-POL-02 | B8: El idPago asociado debe existir y su estado debe ser obligatoriamente "Aprobado".
A9: FAC-POL-03 | B9: El totalFacturado debe ser la suma matemática exacta del subtotal más el totalImpuestos. calculados.
A10: FAC-POL-04 | B10: El idFactura a anular debe existir previamente en el sistema.
A11: FAC-POL-05 | B11: El sistema no modifica la factura original (es inmutable), sino que debe registrar su estado como "Anulada" y generar una Nota de Crédito.
A12: FAC-POL-06 | B12: El cliente solo puede consultar y descargar las facturas asociadas a sus propios pedidos.

Sheet M-Envio
A1: << Ir al modelo de dominio | G1: << Ir al listado de objetos de dominio | I1: << Ir a la caracterización del objeto de dominio
A2: Nombre | B2: =ListadoObjetosDominio!B17 -> Envio
A3: Descripción | B3: =ListadoObjetosDominio!C17 -> Objeto de dominio que representa el proceso logístico y de despacho de un pedido aprobado hacia la dirección de entrega del cliente.
A4: Identificador único universal (UUID) del envío. | B4: Referencia al pedido al que pertenece el envío. | C4: Nombre de la empresa transportadora encargada del envío. | D4: Número de guía proporcionado por la transportadora. | E4: Fecha en que se despachó el envío (LocalDate). | F4: Fecha estimada o real de entrega del envío (LocalDate, opcional). | G4: Estado del envío (PREPARANDO, EN_TRANSITO, ENTREGADO, DEVUELTO, EXTRAVIADO). | H4: Indica que cada intento de pago tiene un identificador único en el sistema, útil para trazabilidad y reclamos
A5: id | B5: pedido | C5: transportadora | D5: numeroGuia | E5: fechaEnvio | F5: fechaEntrega | G5: estado | H5: CombinacionUnica1
A6: EN000000-1111-4222-8333-CCCCCC000001 | B6: PED12345-A1B2-4C3D-8E4F-000000000002 | C6: Servientrega | D6: SERV-30012345678 | E6: 2026-05-17 | F6: 2026-05-19 | G6: EN_TRANSITO | H6: =D6 -> SERV-30012345678
A7: EN000000-1111-4222-8333-CCCCCC000002 | B7: PED12345-A1B2-4C3D-8E4F-000000000003 | C7: Coordinadora | D7: COOR-21456789012 | E7: 2026-05-18 | F7: 'M-MetodoPago'!B6 | G7: PREPARANDO | H7: =D7 -> COOR-21456789012
A8: EN000000-1111-4222-8333-CCCCCC000003 | B8: PED12345-A1B2-4C3D-8E4F-000000000004 | C8: Inter Rapídisimo | D8: INTE-70009876543 | E8: 2026-05-19 | F8: 2026-05-20 | G8: ENTREGADO | H8: =D8 -> INTE-70009876543
A9: EN000000-1111-4222-8333-CCCCCC000004 | B9: PED12345-A1B2-4C3D-8E4F-000000000005 | C9: TCC | D9: TCC-54321987654 | E9: 2026-05-19 | F9: 'M-MetodoPago'!B6 | G9: EN_TRANSITO | H9: =D9 -> TCC-54321987654
A10: EN000000-1111-4222-8333-CCCCCC000005 | B10: PED12345-A1B2-4C3D-8E4F-000000000001 | C10: Envia | D10: ENVI-09876543210 | E10: 2026-05-20 | F10: 'M-MetodoPago'!B6 | G10: PREPARANDO | H10: =D10 -> ENVI-09876543210
A13: Corresponde a los datos generales del objeto de dominio (nombre, descripción)
A14: Corresponde a las descripciones de los atributos
A15: Coresponde al nombre de los atributos
A16: Corresponde a los datos que son de libre ingreso
A17: Corresponde a los datos que se generarán automáticamente
A18: Corresponde a la combinación única 1
A19: Corresponde a referencias a otros objetos de dominio

Sheet C-Envio
A1: << Ir al modelo de dominio | D1: << Ir al listado de objetos de dominio | G1: << Ir a la caracterización del objeto de dominio
A2: Nombre | B2: ='M-Envio'!B2 -> Envio
A3: Descripción | B3: ='M-Envio'!B3 -> Objeto de dominio que representa el proceso logístico y de despacho de un pedido aprobado hacia la dirección de entrega del cliente.
A4: Nombre atributo | B4: Descripción atributo | C4: Identificador del objeto de dominio | D4: Tipo de dato | E4: Obligatorio | F4: Longitud minima(si aplica longitud maxima(si aplica) | G4: Longitud maxima(si aplica longitud maxima(si aplica) | H4: Precisión (si aplica) | I4: Redondeo(si aplica) | J4: Rango inicial(si aplica) | K4: Rango final (si aplica) | L4: Formato(Si aplica) | M4: Reglas especiales(si aplica) | N4: Dato calculado | O4: Aplica ajuste del dato(si aplica) | P4: Carácter de ajuste(si aplica) | Q4: Quitar espacios en blanco al inicio(si aplica) | R4: Quitar espacios en blanco al fin(si aplica) | S4: Dato sensible(si aplica) | T4: Valor por defecto(si aplica) | U4: Auto generado | V4: =#REF! -> #REF! | W4: =#REF! -> #REF! | X4: =#REF! -> #REF! | Y4: =#REF! -> #REF!
A5: ='M-Envio'!A5 -> id | B5: ='M-Envio'!A4 -> Identificador único universal (UUID) del envío. | C5: Si | D5: Alfanumerico | E5: Si | F5: 1 | L5: Mayusculas | N5: No | O5: No | Q5: Si | R5: Si | S5: No | U5: Si | V5: Requerido | W5: No requerido
A6: ='M-Envio'!B5 -> pedido | B6: ='M-Envio'!B4 -> Referencia al pedido al que pertenece el envío. | C6: No | D6: <Pedido> | E6: Si | M6: El pedido maestro debe existir y estar Pagado para poder despacharse | N6: No | S6: No | U6: No | V6: No requerido | W6: No requerido
A7: ='M-Envio'!C5 -> transportadora | B7: ='M-Envio'!C4 -> Nombre de la empresa transportadora encargada del envío. | C7: No | D7: Texto | E7: Si | F7: 3 | G7: 100 | L7: Capitalizado | M7: Debe corresponder a una empresa logística aliada (Servientrega, TCC, etc.) | N7: No | O7: No | Q7: Si | R7: Si | S7: No | U7: No | V7: Norequerido | W7: No requerido
A8: ='M-Envio'!D5 -> numeroGuia | B8: ='M-Envio'!D4 -> Número de guía proporcionado por la transportadora. | C8: No | D8: Alfanumerico | E8: Si | F8: 3 | G8: 100 | L8: Mayusculas | M8: No debe contener espacios en blanco intermedios | N8: No | O8: No | Q8: Si | R8: Si | S8: No | U8: No
A9: ='M-Envio'!E5 -> fechaEnvio | B9: ='M-Envio'!E4 -> Fecha en que se despachó el envío (LocalDate). | C9: No | D9: Fecha | E9: Si | M9: No puede ser anterior a la fecha de creación del pedido | N9: No | S9: No | U9: No
A11: Nombre combinación unica | B11: Descripción | C11: Atributos involucrados
A12: ='M-Envio'!F5 -> fechaEntrega | B12: ='M-Envio'!F4 -> Fecha estimada o real de entrega del envío (LocalDate, opcional). | C12: ='M-Envio'!D5 -> numeroGuia
A15: Responsabilidad | B15: Descripción | C15: Entradas | F15: Salida | H15: Políticas (Reglas de Negocio) | J15: Excepción
C16: Parámettro | D16: Tipo de dato | E16: Descripci | F16: Tipo de Dato | G16: Descripción | H16: Política | I16: Descripción | J16: Detalle | K16: ¿Qué hago?
A17: ='E-Envio'!B7 -> Registrar envío (Despachar) | B17: ='E-Envio'!C7 -> Crear la orden de transporte físico asociando el pedido pagado con una empresa de mensajería externa. | C17: envioNuevo | D17: Envío | E17: Contiene la información logística y de despacho a registrar. | F17: Logico | G17: Retorna verdadero si el envío se creó y despachó exitosamente. | H17: ='E-Envio'!G7 -> ENV-POL-01 | I17: ='E-Envio'!H7 -> Asegurar que los datos requeridos sean válidos a nivel de tipo, formato, longitud y obligatoriedad. | J17: Generar excepción indicando qué campo no cumple con el formato o es obligatorio. | K17: Detener operación
H18: ='E-Envio'!G8 -> ENV-POL-02 | I18: ='E-Envio'!H8 -> El idPedido asociado debe existir, estar pagado y no tener otro envío activo. | J18: Generar excepción indicando que el pedido no es válido para despacho o ya fue enviado. | K18: Detener operación
A19: ='E-Envio'!B9 -> Modificar envío (Corregir) | B19: ='E-Envio'!C9 -> Actualizar los datos de despacho si hubo un error al generar la guía o si la caja se reasignó a otra empresa de transporte. | C19: envioModificado | D19: Envío | E19: Contiene la información del envío con los datos de guía actualizados. | F19: Logico | G19: Retorna verdadero si el envío se actualizó correctamente. | H19: ='E-Envio'!G9 -> ENV-POL-03 | I19: ='E-Envio'!H9 -> El idEnvio a modificar debe existir previamente en el sistema. | J19: Generar excepción indicando que el envío a corregir no existe en la base de datos. | K19: Detener operación
A20: ='E-Envio'!B10 -> Consultar envío (Tracking) | B20: ='E-Envio'!C10 -> Consultar la ubicación actual y el estado del paquete físico utilizando su número de guía. | C20: idPedido | D20: alfanumerico | E20: Identificador del pedido del cual se quiere conocer la información de envío. | F20: Lista<Envío> | G20: Retorna una colección con los objetos de envío asociados a la búsqueda. | H20: ='E-Envio'!G10 -> ENV-POL-04 | I20: ='E-Envio'!H10 -> El cliente solo puede rastrear los envíos asociados a sus propios pedidos. | J20: Generar excepción indicando acceso denegado por intentar rastrear el paquete de otro usuario. | K20: Detener operación

Sheet E-Envio
